Workbook

Sheet Financial Statements
A1: date | B1: revenue | C1: grossProfit | D1: generalAndAdministrativeExpenses | E1: sellingAndMarketingExpenses | F1: sellingGeneralAndAdministrativeExpenses | G1: researchAndDevelopmentExpenses | H1: otherExpenses | I1: operatingIncome | J1: interestExpense | K1: interestIncome | L1: incomeTaxExpense | M1: netIncome | N1: weightedAverageShsOut | O1: weightedAverageShsOutDil | P1: freeCashFlow | Q1: accountsReceivables | R1: accountsPayables | S1: inventory_x | T1: depreciationAndAmortization | U1: stockBasedCompensation | V1: deferredIncomeTax | W1: changeInWorkingCapital | X1: otherWorkingCapital | Y1: netChangeInCash | Z1: netCashProvidedByOperatingActivities | AA1: capitalExpenditure | AB1: investmentsInPropertyPlantAndEquipment | AC1: acquisitionsNet | AD1: purchasesOfInvestments | AE1: netCashUsedForInvestingActivites | AF1: debtRepayment | AG1: commonStockIssued | AH1: commonStockRepurchased | AI1: dividendsPaid | AJ1: netCashUsedProvidedByFinancingActivities | AK1: effectOfForexChangesOnCash | AL1: cashAndCashEquivalents | AM1: shortTermInvestments | AN1: cashAndShortTermInvestments | AO1: netReceivables | AP1: inventory_y | AQ1: otherCurrentAssets | AR1: totalCurrentAssets | AS1: propertyPlantEquipmentNet | AT1: goodwill | AU1: intangibleAssets | AV1: longTermInvestments | AW1: totalNonCurrentAssets | AX1: totalAssets | AY1: accountPayables | AZ1: shortTermDebt | BA1: longTermDebt | BB1: totalLiabilities | BC1: totalEquity | BD1: EBITDA | BE1: FCFsimple
A2: 2024-07-31 | B2: 963872000 | C2: 725523000 | D2: 106434000 | E2: 355471000 | F2: 460457000 | G2: 250908000 | H2: -1031000 | I2: 14158000 | J2: 6549000 | K2: 51526000 | L2: 10914000 | M2: 47013000 | N2: 244091000 | O2: 251265000 | P2: 272871000 | Q2: 41811000 | R2: -348000 | S2: 0 | T2: 52584000 | U2: 200877000 | V2: -1674000 | W2: -50919000 | X2: -92382000 | Y2: 336099000 | Z2: 326641000 | AA2: -53770000 | AB2: -53770000 | AC2: 4995000 | AD2: -1044000 | AE2: -49890000 | AF2: 0 | AG2: 57740000 | AH2: 0 | AI2: 0 | AJ2: 57496000 | AK2: 877000 | AL2: 4038536000 | AM2: 0 | AN2: 4038536000 | AO2: 661045000 | AP2: 0 | AQ2: 230821000 | AR2: 4930402000 | AS2: 694371000 | AT2: 721996000 | AU2: 115686000 | AV2: 58246000 | AW2: 2272072000 | AX2: 7202474000 | AY2: 21067000 | AZ2: 17031000 | BA2: 743238000 | BB2: 4311884000 | BC2: 2890590000 | BD2: 66742000 | BE2: 12972000
A3: 2024-04-30 | B3: 921036000 | C3: 696033000 | D3: 103734000 | E3: 350114000 | F3: 453848000 | G3: 235249000 | H3: 7656000 | I3: 6936000 | J3: 6511000 | K3: 45850000 | L3: 7667000 | M3: 42820000 | N3: 242389000 | O3: 250164000 | P3: 323066000 | Q3: 150249000 | R3: 276000 | S3: 0 | T3: 48684000 | U3: 183125000 | V3: -255000 | W3: 31632000 | X3: -118893000 | Y3: 327368000 | Z3: 383228000 | AA3: -60162000 | AB3: -60162000 | AC3: -95876000 | AD3: -1658000 | AE3: -50598000 | AF3: 0 | AG3: 823000 | AH3: 0 | AI3: 0 | AJ3: -3018000 | AK3: -1917000 | AL3: 3702437000 | AM3: 0 | AN3: 3702437000 | AO3: 702856000 | AP3: 0 | AQ3: 191678000 | AR3: 4596971000 | AS3: 675979000 | AT3: 721973000 | AU3: 122024000 | AV3: 58419000 | AW3: 2245014000 | AX3: 6841985000 | AY3: 21299000 | AZ3: 16020000 | BA3: 742866000 | BB3: 4273203000 | BC3: 2568781999 | BD3: 55620000 | BE3: -4542000
A4: 2024-01-31 | B4: 845335000 | C4: 636079000 | D4: 102737000 | E4: 290357000 | F4: 390982000 | G4: 213998000 | H4: 3616000 | I4: 31099000 | J4: 6422000 | K4: 41685000 | L4: 13609000 | M4: 53699000 | N4: 240856000 | O4: 247936000 | P4: 272980000 | Q4: -283557000 | R4: -21259000 | S4: -62886000 | T4: 42369000 | U4: 176272000 | V4: -1032000 | W4: 7042000 | X4: 311858000 | Y4: 406197000 | Z4: 347016000 | AA4: -74036000 | AB4: -74036000 | AC4: -281000 | AD4: -5000000 | AE4: 20395000 | AF4: 0 | AG4: 33460000 | AH4: 76375000 | AI4: 0 | AJ4: 33460000 | AK4: 5369000 | AL4: 3375069000 | AM4: 99591000 | AN4: 3474660000 | AO4: 853105000 | AP4: 1 | AQ4: 183172000 | AR4: 4510937000 | AS4: 668383000 | AT4: 638041000 | AU4: 114518000 | AV4: 56244000 | AW4: 2135583000 | AX4: 6646520000 | AY4: 28180000 | AZ4: 14150000 | BA4: 742494000 | BB4: 4309431000 | BC4: 2337089000 | BD4: 73468000 | BE4: -568000
A5: 2023-10-31 | B5: 786014000 | C5: 591010000 | D5: 105589000 | E5: 286186000 | F5: 391775000 | G5: 196072000 | H5: -474000 | I5: 3163000 | J5: 547000 | K5: 40086000 | L5: 9603000 | M5: 26665000 | N5: 239297000 | O5: 243799000 | P5: 239598000 | Q5: -20860000 | R5: 5343000 | S5: 55327000 | T5: 38425000 | U5: 159614000 | V5: -2003000 | W5: -11734000 | X5: -51544000 | Y5: -195858000 | Z5: 273518000 | AA5: -33920000 | AB5: -33920000 | AC5: -238749000 | AD5: -196167000 | AE5: -468836000 | AF5: 0 | AG5: 2053000 | AH5: 0 | AI5: 0 | AJ5: 2053000 | AK5: -4494000 | AL5: 2968872000 | AM5: 197522000 | AN5: 3166394000 | AO5: 561872000 | AP5: 209216000 | AQ5: 141651000 | AR5: 4079133000 | AS5: 631978000 | AT5: 637678000 | AU5: 109423000 | AV5: 59541000 | AW5: 1751923000 | AX5: 5831056000 | AY5: 56968000 | AZ5: 14430000 | BA5: 780493000 | BB5: 3770209000 | BC5: 2060847000 | BD5: 41588000 | BE5: 7668000
A6: 2023-07-31 | B6: 731626000 | C6: 548709000 | D6: 153246000 | E6: 231474000 | F6: 384720000 | G6: 179362000 | H6: -1734000 | I6: -15373000 | J6: 6444000 | K6: 36638000 | L6: 4611000 | M6: 8472000 | N6: 237911000 | O6: 242144000 | P6: 188791000 | Q6: -78371000 | R6: 15614000 | S6: 7559000 | T6: 33877000 | U6: 164777000 | V6: -97000 | W6: -23823000 | X6: 31375000 | Y6: 339439000 | Z6: 244781000 | AA6: -55990000 | AB6: -55990000 | AC6: -97750000 | AD6: -2250000 | AE6: 41760000 | AF6: 0 | AG6: 46906000 | AH6: 0 | AI6: 0 | AJ6: 49737000 | AK6: 1273000 | AL6: 3167215000 | AM6: 0 | AN6: 3167215000 | AO6: 539463000 | AP6: 197111000 | AQ6: 146597000 | AR6: 4050386000 | AS6: 607766000 | AT6: 430697000 | AU6: 79139000 | AV6: 59541000 | AW6: 1470072000 | AX6: 5520458000 | AY6: 37073000 | AZ6: 16133000 | BA6: 774438000 | BB6: 3650358000 | BC6: 1870100000 | BD6: 18504000 | BE6: -37486000
A7: 2023-04-30 | B7: 692580000 | C7: 523350000 | D7: 82634000 | E7: 281107000 | F7: 363741000 | G7: 179065000 | H7: 230000 | I7: 11295000 | J7: 6387000 | K7: 30521000 | L7: 4409000 | M7: 491000 | N7: 236414000 | O7: 240598000 | P7: 227726000 | Q7: 165089000 | R7: -18596000 | S7: 0 | T7: 30583000 | U7: 130856000 | V7: -255000 | W7: 80041000 | X7: -66452000 | Y7: 374641000 | Z7: 300892000 | AA7: -73166000 | AB7: -73166000 | AC7: 10902000 | AD7: -10803000 | AE7: 66031000 | AF7: 0 | AG7: 2651000 | AH7: 0 | AI7: 0 | AJ7: 7908000 | AK7: -190000 | AL7: 2829677000 | AM7: 100000000 | AN7: 2929677000 | AO7: 461092000 | AP7: 186901000 | AQ7: 131100000 | AR7: 3708770000 | AS7: 574180000 | AT7: 430755000 | AU7: 83215000 | AV7: 57877000 | AW7: 1429088000 | AX7: 5137858000 | AY7: 16900000 | AZ7: 16215000 | BA7: 778151000 | BB7: 3503499000 | BC7: 1634359000 | BD7: 41878000 | BE7: -31288000
A8: 2023-01-31 | B8: 637367000 | C8: 461763000 | D8: 84979000 | E8: 246439000 | F8: 331418000 | G8: 191845000 | H8: -2782000 | I8: -61500000 | J8: 6352000 | K8: 27016000 | L8: 5314000 | M8: -48932000 | N8: 235027000 | O8: 235027000 | P8: 207904000 | Q8: -140869000 | R8: -40470000 | S8: 0 | T8: 27850000 | U8: 152347000 | V8: -980000 | W8: 87465000 | X8: 268804000 | Y8: -11134000 | Z8: 273293000 | AA8: -65389000 | AB8: -65389000 | AC8: 115000 | AD8: -253866000 | AE8: -319140000 | AF8: 0 | AG8: 27233000 | AH8: 59419000 | AI8: 0 | AJ8: 27233000 | AK8: 5579000 | AL8: 2455369000 | AM8: 250000000 | AN8: 2705369000 | AO8: 626181000 | AP8: 186855000 | AQ8: 121862000 | AR8: 3640267000 | AS8: 532271000 | AT8: 430645000 | AU8: 86889000 | AV8: 47270000 | AW8: 1386273000 | AX8: 5026540000 | AY8: 45372000 | AZ8: 13046000 | BA8: 770572000 | BB8: 3539106000 | BC8: 1487434000 | BD8: -33650000 | BE8: -99039000
A9: 2022-10-31 | B9: 580882000 | C9: 422654000 | D9: 84148000 | E9: 239672000 | F9: 323820000 | G9: 155256000 | H9: 750000 | I9: -56422000 | J9: 6334000 | K9: 16245000 | L9: 8870000 | M9: -54631000 | N9: 233785000 | O9: 233785000 | P9: 174077000 | Q9: -66512000 | R9: 24213000 | S9: 0 | T9: 23622000 | U9: 140113000 | V9: 682000 | W9: 86693000 | X9: 128992000 | Y9: 147664000 | Z9: 242851000 | AA9: -68774000 | AB9: -68774000 | AC9: -18464000 | AD9: -10181000 | AE9: -97419000 | AF9: -1591000 | AG9: 1477000 | AH9: 0 | AI9: 0 | AJ9: -114000 | AK9: -2744000 | AL9: 2466551000 | AM9: 0 | AN9: 2466551000 | AO9: 485313000 | AP9: 162260000 | AQ9: 89489000 | AR9: 3203613000 | AS9: 455651000 | AT9: 430285000 | AU9: 89500000 | AV9: 46395000 | AW9: 1265830000 | AX9: 4469443000 | AY9: 89289000 | AZ9: 10423000 | BA9: 758617000 | BB9: 3131811000 | BC9: 1337632000 | BD9: -32800000 | BE9: -101574000
A10: 2022-07-31 | B10: 535153000 | C10: 394586000 | D10: 80263000 | E10: 224766000 | F10: 305029000 | G10: 137864000 | H10: 3380000 | I10: -48307000 | J10: 6335000 | K10: 7727000 | L10: 4778000 | M10: -49285000 | N10: 232554000 | O10: 232554000 | P10: 135757000 | Q10: -49670000 | R10: 37225000 | S10: 0 | T10: 21909000 | U10: 131550000 | V10: -148000 | W10: 63882000 | X10: 93969000 | Y10: 167658000 | Z10: 209906000 | AA10: -74149000 | AB10: -74149000 | AC10: 2501000 | AD10: -5000000 | AE10: -79149000 | AF10: 0 | AG10: 36258000 | AH10: 0 | AI10: 0 | AJ10: 38759000 | AK10: -1858000 | AL10: 2318858000 | AM10: 0 | AN10: 2318858000 | AO10: 418799000 | AP10: 1 | AQ10: 90198000 | AR10: 2975980000 | AS10: 411475000 | AT10: 416066000 | AU10: 89840000 | AV10: 35585000 | AW10: 1178256000 | AX10: 4154236000 | AY10: 53817000 | AZ10: 10316000 | BA10: 761601000 | BB10: 2910889000 | BC10: 1243347000 | BD10: -26398000 | BE10: -100547000
A11: 2022-04-30 | B11: 487834000 | C11: 361002000 | D11: 67954000 | E11: 193532000 | F11: 261486000 | G11: 123399000 | H11: 3212000 | I11: -23883000 | J11: 5752000 | K11: 1507000 | L11: 3440000 | M11: -30409000 | N11: 225164285 | O11: 231179000 | P11: 156832000 | Q11: -1058000 | R11: -36431000 | S11: 0 | T11: 20429000 | U11: 102494000 | V11: 1752000 | W11: 82401000 | X11: 119890000 | Y11: 156103000 | Z11: 214957000 | AA11: -58125000 | AB11: -58125000 | AC11: 1462000 | AD11: -2825000 | AE11: -60950000 | AF11: 0 | AG11: 3106000 | AH11: 0 | AI11: 0 | AJ11: 3106000 | AK11: -2472000 | AL11: 2152736000 | AM11: 0 | AN11: 2152736000 | AO11: 369130000 | AP11: 135681000 | AQ11: 75511000 | AR11: 2733058000 | AS11: 345010000 | AT11: 416228000 | AU11: 93945000 | AV11: 28665000 | AW11: 1102777000 | AX11: 3835835000 | AY11: 11024000 | AZ11: 9967000 | BA11: 762086000 | BB11: 2718838000 | BC11: 1116997000 | BD11: -3454000 | BE11: -61579000
A12: 2022-01-31 | B12: 431010000 | C12: 318390000 | D12: 74312000 | E12: 162594000 | F12: 236906000 | G12: 105018000 | H12: 1679000 | I12: -23534000 | J12: 6302000 | K12: 0 | L12: 13582000 | M12: -41980000 | N12: 229662000 | O12: 229662000 | P12: 127330000 | Q12: -84710000 | R12: 40281000 | S12: -48172000 | T12: 20491000 | U12: 92637000 | V12: -14682000 | W12: 65818000 | X12: 158419000 | Y12: 89125000 | Z12: 159718000 | AA12: -32388000 | AB12: -32388000 | AC12: -60772000 | AD12: -500000 | AE12: -93660000 | AF12: 0 | AG12: 25928000 | AH12: 50277000 | AI12: 0 | AJ12: 26178000 | AK12: -3111000 | AL12: 1996633000 | AM12: 0 | AN12: 1996633000 | AO12: 368145000 | AP12: 126822000 | AQ12: 79352000 | AR12: 2570952000 | AS12: 292312000 | AT12: 416445000 | AU12: 97336000 | AV12: 23632000 | AW12: 1047429000 | AX12: 3618381000 | AY12: 47634000 | AZ12: 9820000 | BA12: 764896000 | BB12: 2580738000 | BC12: 1037643000 | BD12: -3043000 | BE12: -35431000
A13: 2021-10-31 | B13: 380051000 | C13: 278387000 | D13: 56061000 | E13: 164960000 | F13: 221021000 | G13: 97630000 | H13: 690000 | I13: -40264000 | J13: 6403000 | K13: 1019000 | L13: 4473000 | M13: -50455000 | N13: 228293000 | O13: 228293000 | P13: 122823000 | Q13: -16387000 | R13: -12416000 | S13: 0 | T13: 17859000 | U13: 86666000 | V13: -339000 | W13: 73146000 | X13: 89533000 | Y13: 120457000 | Z13: 159058000 | AA13: -36235000 | AB13: -36235000 | AC13: 4250000 | AD13: -8500000 | AE13: -44735000 | AF13: 0 | AG13: 3304000 | AH13: 0 | AI13: 0 | AJ13: 7554000 | AK13: -1420000 | AL13: 1907508000 | AM13: 0 | AN13: 1907508000 | AO13: 283272000 | AP13: 108636000 | AQ13: 60670000 | AR13: 2360086000 | AS13: 276117000 | AT13: 373889000 | AU13: 82870000 | AV13: 22665000 | AW13: 939531000 | AX13: 3299617000 | AY13: 7167000 | AZ13: 9706000 | BA13: 767040000 | BB13: 2340047000 | BC13: 959570000 | BD13: -22405000 | BE13: -58640000
... A27: 2018-01-31 | B27: 38717000 | C27: 19547000 | D27: 6121000 | E27: 34265000 | F27: 40386000 | G27: 15928000 | H27: 0 | I27: -36767000 | J27: 0 | K27: 190000 | L27: 483000 | M27: -41717000 | N27: 43055020 | O27: 43055000 | P27: -10170000 | Q27: -19521000 | R27: 0 | S27: 0 | T27: -671000 | U27: 1338000 | V27: 0 | W27: -23235000 | X27: -3714000 | Y27: -2937000 | Z27: -6725000 | AA27: -3445000 | AB27: -3445000 | AC27: 0 | AD27: 0 | AE27: 53000 | AF27: 0 | AG27: 0 | AH27: 0 | AI27: 0 | AJ27: 3532000 | AK27: 203000 | AL27: 63179000 | AM27: 2593000 | AN27: 65772000 | AO27: 59614000 | AP27: 1 | AQ27: 28224999 | AR27: 153611000 | AS27: 30854000 | AT27: 8421000 | AU27: 11636000 | AV27: 0 | AW27: 64092000 | AX27: 217703000 | AY27: 12261000 | AZ27: 0 | BA27: 15971000 | BB27: 236161000 | BC27: -18458000 | BD27: -37438000 | BE27: -40883000

Sheet Margins
A1: date | B1: revenue | C1: grossProfit | D1: generalAndAdministrativeExpenses | E1: sellingAndMarketingExpenses | F1: sellingGeneralAndAdministrativeExpenses | G1: researchAndDevelopmentExpenses | H1: otherExpenses | I1: operatingIncome | J1: interestExpense | K1: interestIncome | L1: incomeTaxExpense | M1: netIncome | N1: weightedAverageShsOut | O1: weightedAverageShsOutDil | P1: freeCashFlow | Q1: accountsReceivables | R1: accountsPayables | S1: inventory_x | T1: depreciationAndAmortization | U1: stockBasedCompensation | V1: deferredIncomeTax | W1: changeInWorkingCapital | X1: otherWorkingCapital | Y1: netChangeInCash | Z1: netCashProvidedByOperatingActivities | AA1: capitalExpenditure | AB1: investmentsInPropertyPlantAndEquipment | AC1: acquisitionsNet | AD1: purchasesOfInvestments | AE1: netCashUsedForInvestingActivites | AF1: debtRepayment | AG1: commonStockIssued | AH1: commonStockRepurchased | AI1: dividendsPaid | AJ1: netCashUsedProvidedByFinancingActivities | AK1: effectOfForexChangesOnCash | AL1: cashAndCashEquivalents | AM1: shortTermInvestments | AN1: cashAndShortTermInvestments | AO1: netReceivables | AP1: inventory_y | AQ1: otherCurrentAssets | AR1: totalCurrentAssets | AS1: propertyPlantEquipmentNet | AT1: goodwill | AU1: intangibleAssets | AV1: longTermInvestments | AW1: totalNonCurrentAssets | AX1: totalAssets | AY1: accountPayables | AZ1: shortTermDebt | BA1: longTermDebt | BB1: totalLiabilities | BC1: totalEquity | BD1: EBITDA | BE1: FCFsimple
A2: 2024-07-31 | B2: 1 | C2: 0.753 | D2: 0.11 | E2: 0.369 | F2: 0.478 | G2: 0.26 | H2: -0.001 | I2: 0.015 | J2: 0.007 | K2: 0.053 | L2: 0.011 | M2: 0.049 | N2: 0.253 | O2: 0.261 | P2: 0.283 | Q2: 0.043 | R2: 0 | S2: 0 | T2: 0.055 | U2: 0.208 | V2: -0.002 | W2: -0.053 | X2: -0.096 | Y2: 0.349 | Z2: 0.339 | AA2: -0.056 | AB2: -0.056 | AC2: 0.005 | AD2: -0.001 | AE2: -0.052 | AF2: 0 | AG2: 0.06 | AH2: 0 | AI2: 0 | AJ2: 0.06 | AK2: 0.001 | AL2: 4.19 | AM2: 0 | AN2: 4.19 | AO2: 0.686 | AP2: 0 | AQ2: 0.239 | AR2: 5.115 | AS2: 0.72 | AT2: 0.749 | AU2: 0.12 | AV2: 0.06 | AW2: 2.357 | AX2: 7.472 | AY2: 0.022 | AZ2: 0.018 | BA2: 0.771 | BB2: 4.474 | BC2: 2.999 | BD2: 0.069 | BE2: 0.013
A3: 2024-04-30 | B3: 1 | C3: 0.756 | D3: 0.113 | E3: 0.38 | F3: 0.493 | G3: 0.255 | H3: 0.008 | I3: 0.008 | J3: 0.007 | K3: 0.05 | L3: 0.008 | M3: 0.046 | N3: 0.263 | O3: 0.272 | P3: 0.351 | Q3: 0.163 | R3: 0 | S3: 0 | T3: 0.053 | U3: 0.199 | V3: 0 | W3: 0.034 | X3: -0.129 | Y3: 0.355 | Z3: 0.416 | AA3: -0.065 | AB3: -0.065 | AC3: -0.104 | AD3: -0.002 | AE3: -0.055 | AF3: 0 | AG3: 0.001 | AH3: 0 | AI3: 0 | AJ3: -0.003 | AK3: -0.002 | AL3: 4.02 | AM3: 0 | AN3: 4.02 | AO3: 0.763 | AP3: 0 | AQ3: 0.208 | AR3: 4.991 | AS3: 0.734 | AT3: 0.784 | AU3: 0.132 | AV3: 0.063 | AW3: 2.437 | AX3: 7.429 | AY3: 0.023 | AZ3: 0.017 | BA3: 0.807 | BB3: 4.64 | BC3: 2.789 | BD3: 0.06 | BE3: -0.005
A4: 2024-01-31 | B4: 1 | C4: 0.752 | D4: 0.122 | E4: 0.343 | F4: 0.463 | G4: 0.253 | H4: 0.004 | I4: 0.037 | J4: 0.008 | K4: 0.049 | L4: 0.016 | M4: 0.064 | N4: 0.285 | O4: 0.293 | P4: 0.323 | Q4: -0.335 | R4: -0.025 | S4: -0.074 | T4: 0.05 | U4: 0.209 | V4: -0.001 | W4: 0.008 | X4: 0.369 | Y4: 0.481 | Z4: 0.411 | AA4: -0.088 | AB4: -0.088 | AC4: 0 | AD4: -0.006 | AE4: 0.024 | AF4: 0 | AG4: 0.04 | AH4: 0.09 | AI4: 0 | AJ4: 0.04 | AK4: 0.006 | AL4: 3.993 | AM4: 0.118 | AN4: 4.11 | AO4: 1.009 | AP4: 0 | AQ4: 0.217 | AR4: 5.336 | AS4: 0.791 | AT4: 0.755 | AU4: 0.135 | AV4: 0.067 | AW4: 2.526 | AX4: 7.863 | AY4: 0.033 | AZ4: 0.017 | BA4: 0.878 | BB4: 5.098 | BC4: 2.765 | BD4: 0.087 | BE4: -0.001
A5: 2023-10-31 | B5: 1 | C5: 0.752 | D5: 0.134 | E5: 0.364 | F5: 0.498 | G5: 0.249 | H5: -0.001 | I5: 0.004 | J5: 0.001 | K5: 0.051 | L5: 0.012 | M5: 0.034 | N5: 0.304 | O5: 0.31 | P5: 0.305 | Q5: -0.027 | R5: 0.007 | S5: 0.07 | T5: 0.049 | U5: 0.203 | V5: -0.003 | W5: -0.015 | X5: -0.066 | Y5: -0.249 | Z5: 0.348 | AA5: -0.043 | AB5: -0.043 | AC5: -0.304 | AD5: -0.25 | AE5: -0.596 | AF5: 0 | AG5: 0.003 | AH5: 0 | AI5: 0 | AJ5: 0.003 | AK5: -0.006 | AL5: 3.777 | AM5: 0.251 | AN5: 4.028 | AO5: 0.715 | AP5: 0.266 | AQ5: 0.18 | AR5: 5.19 | AS5: 0.804 | AT5: 0.811 | AU5: 0.139 | AV5: 0.076 | AW5: 2.229 | AX5: 7.419 | AY5: 0.072 | AZ5: 0.018 | BA5: 0.993 | BB5: 4.797 | BC5: 2.622 | BD5: 0.053 | BE5: 0.01
A6: 2023-07-31 | B6: 1 | C6: 0.75 | D6: 0.209 | E6: 0.316 | F6: 0.526 | G6: 0.245 | H6: -0.002 | I6: -0.021 | J6: 0.009 | K6: 0.05 | L6: 0.006 | M6: 0.012 | N6: 0.325 | O6: 0.331 | P6: 0.258 | Q6: -0.107 | R6: 0.021 | S6: 0.01 | T6: 0.046 | U6: 0.225 | V6: 0 | W6: -0.033 | X6: 0.043 | Y6: 0.464 | Z6: 0.335 | AA6: -0.077 | AB6: -0.077 | AC6: -0.134 | AD6: -0.003 | AE6: 0.057 | AF6: 0 | AG6: 0.064 | AH6: 0 | AI6: 0 | AJ6: 0.068 | AK6: 0.002 | AL6: 4.329 | AM6: 0 | AN6: 4.329 | AO6: 0.737 | AP6: 0.269 | AQ6: 0.2 | AR6: 5.536 | AS6: 0.831 | AT6: 0.589 | AU6: 0.108 | AV6: 0.081 | AW6: 2.009 | AX6: 7.545 | AY6: 0.051 | AZ6: 0.022 | BA6: 1.059 | BB6: 4.989 | BC6: 2.556 | BD6: 0.025 | BE6: -0.051
A7: 2023-04-30 | B7: 1 | C7: 0.756 | D7: 0.119 | E7: 0.406 | F7: 0.525 | G7: 0.259 | H7: 0 | I7: 0.016 | J7: 0.009 | K7: 0.044 | L7: 0.006 | M7: 0.001 | N7: 0.341 | O7: 0.347 | P7: 0.329 | Q7: 0.238 | R7: -0.027 | S7: 0 | T7: 0.044 | U7: 0.189 | V7: 0 | W7: 0.116 | X7: -0.096 | Y7: 0.541 | Z7: 0.434 | AA7: -0.106 | AB7: -0.106 | AC7: 0.016 | AD7: -0.016 | AE7: 0.095 | AF7: 0 | AG7: 0.004 | AH7: 0 | AI7: 0 | AJ7: 0.011 | AK7: 0 | AL7: 4.086 | AM7: 0.144 | AN7: 4.23 | AO7: 0.666 | AP7: 0.27 | AQ7: 0.189 | AR7: 5.355 | AS7: 0.829 | AT7: 0.622 | AU7: 0.12 | AV7: 0.084 | AW7: 2.063 | AX7: 7.418 | AY7: 0.024 | AZ7: 0.023 | BA7: 1.124 | BB7: 5.059 | BC7: 2.36 | BD7: 0.06 | BE7: -0.045
A8: 2023-01-31 | B8: 1 | C8: 0.724 | D8: 0.133 | E8: 0.387 | F8: 0.52 | G8: 0.301 | H8: -0.004 | I8: -0.096 | J8: 0.01 | K8: 0.042 | L8: 0.008 | M8: -0.077 | N8: 0.369 | O8: 0.369 | P8: 0.326 | Q8: -0.221 | R8: -0.063 | S8: 0 | T8: 0.044 | U8: 0.239 | V8: -0.002 | W8: 0.137 | X8: 0.422 | Y8: -0.017 | Z8: 0.429 | AA8: -0.103 | AB8: -0.103 | AC8: 0 | AD8: -0.398 | AE8: -0.501 | AF8: 0 | AG8: 0.043 | AH8: 0.093 | AI8: 0 | AJ8: 0.043 | AK8: 0.009 | AL8: 3.852 | AM8: 0.392 | AN8: 4.245 | AO8: 0.982 | AP8: 0.293 | AQ8: 0.191 | AR8: 5.711 | AS8: 0.835 | AT8: 0.676 | AU8: 0.136 | AV8: 0.074 | AW8: 2.175 | AX8: 7.886 | AY8: 0.071 | AZ8: 0.02 | BA8: 1.209 | BB8: 5.553 | BC8: 2.334 | BD8: -0.053 | BE8: -0.155
A9: 2022-10-31 | B9: 1 | C9: 0.728 | D9: 0.145 | E9: 0.413 | F9: 0.557 | G9: 0.267 | H9: 0.001 | I9: -0.097 | J9: 0.011 | K9: 0.028 | L9: 0.015 | M9: -0.094 | N9: 0.402 | O9: 0.402 | P9: 0.3 | Q9: -0.115 | R9: 0.042 | S9: 0 | T9: 0.041 | U9: 0.241 | V9: 0.001 | W9: 0.149 | X9: 0.222 | Y9: 0.254 | Z9: 0.418 | AA9: -0.118 | AB9: -0.118 | AC9: -0.032 | AD9: -0.018 | AE9: -0.168 | AF9: -0.003 | AG9: 0.003 | AH9: 0 | AI9: 0 | AJ9: 0 | AK9: -0.005 | AL9: 4.246 | AM9: 0 | AN9: 4.246 | AO9: 0.835 | AP9: 0.279 | AQ9: 0.154 | AR9: 5.515 | AS9: 0.784 | AT9: 0.741 | AU9: 0.154 | AV9: 0.08 | AW9: 2.179 | AX9: 7.694 | AY9: 0.154 | AZ9: 0.018 | BA9: 1.306 | BB9: 5.391 | BC9: 2.303 | BD9: -0.056 | BE9: -0.175
A10: 2022-07-31 | B10: 1 | C10: 0.737 | D10: 0.15 | E10: 0.42 | F10: 0.57 | G10: 0.258 | H10: 0.006 | I10: -0.09 | J10: 0.012 | K10: 0.014 | L10: 0.009 | M10: -0.092 | N10: 0.435 | O10: 0.435 | P10: 0.254 | Q10: -0.093 | R10: 0.07 | S10: 0 | T10: 0.041 | U10: 0.246 | V10: 0 | W10: 0.119 | X10: 0.176 | Y10: 0.313 | Z10: 0.392 | AA10: -0.139 | AB10: -0.139 | AC10: 0.005 | AD10: -0.009 | AE10: -0.148 | AF10: 0 | AG10: 0.068 | AH10: 0 | AI10: 0 | AJ10: 0.072 | AK10: -0.003 | AL10: 4.333 | AM10: 0 | AN10: 4.333 | AO10: 0.783 | AP10: 0 | AQ10: 0.169 | AR10: 5.561 | AS10: 0.769 | AT10: 0.777 | AU10: 0.168 | AV10: 0.066 | AW10: 2.202 | AX10: 7.763 | AY10: 0.101 | AZ10: 0.019 | BA10: 1.423 | BB10: 5.439 | BC10: 2.323 | BD10: -0.049 | BE10: -0.188
A11: 2022-04-30 | B11: 1 | C11: 0.74 | D11: 0.139 | E11: 0.397 | F11: 0.536 | G11: 0.253 | H11: 0.007 | I11: -0.049 | J11: 0.012 | K11: 0.003 | L11: 0.007 | M11: -0.062 | N11: 0.462 | O11: 0.474 | P11: 0.321 | Q11: -0.002 | R11: -0.075 | S11: 0 | T11: 0.042 | U11: 0.21 | V11: 0.004 | W11: 0.169 | X11: 0.246 | Y11: 0.32 | Z11: 0.441 | AA11: -0.119 | AB11: -0.119 | AC11: 0.003 | AD11: -0.006 | AE11: -0.125 | AF11: 0 | AG11: 0.006 | AH11: 0 | AI11: 0 | AJ11: 0.006 | AK11: -0.005 | AL11: 4.413 | AM11: 0 | AN11: 4.413 | AO11: 0.757 | AP11: 0.278 | AQ11: 0.155 | AR11: 5.602 | AS11: 0.707 | AT11: 0.853 | AU11: 0.193 | AV11: 0.059 | AW11: 2.261 | AX11: 7.863 | AY11: 0.023 | AZ11: 0.02 | BA11: 1.562 | BB11: 5.573 | BC11: 2.29 | BD11: -0.007 | BE11: -0.126
A12: 2022-01-31 | B12: 1 | C12: 0.739 | D12: 0.172 | E12: 0.377 | F12: 0.55 | G12: 0.244 | H12: 0.004 | I12: -0.055 | J12: 0.015 | K12: 0 | L12: 0.032 | M12: -0.097 | N12: 0.533 | O12: 0.533 | P12: 0.295 | Q12: -0.197 | R12: 0.093 | S12: -0.112 | T12: 0.048 | U12: 0.215 | V12: -0.034 | W12: 0.153 | X12: 0.368 | Y12: 0.207 | Z12: 0.371 | AA12: -0.075 | AB12: -0.075 | AC12: -0.141 | AD12: -0.001 | AE12: -0.217 | AF12: 0 | AG12: 0.06 | AH12: 0.117 | AI12: 0 | AJ12: 0.061 | AK12: -0.007 | AL12: 4.632 | AM12: 0 | AN12: 4.632 | AO12: 0.854 | AP12: 0.294 | AQ12: 0.184 | AR12: 5.965 | AS12: 0.678 | AT12: 0.966 | AU12: 0.226 | AV12: 0.055 | AW12: 2.43 | AX12: 8.395 | AY12: 0.111 | AZ12: 0.023 | BA12: 1.775 | BB12: 5.988 | BC12: 2.407 | BD12: -0.007 | BE12: -0.082
A13: 2021-10-31 | B13: 1 | C13: 0.732 | D13: 0.148 | E13: 0.434 | F13: 0.582 | G13: 0.257 | H13: 0.002 | I13: -0.106 | J13: 0.017 | K13: 0.003 | L13: 0.012 | M13: -0.133 | N13: 0.601 | O13: 0.601 | P13: 0.323 | Q13: -0.043 | R13: -0.033 | S13: 0 | T13: 0.047 | U13: 0.228 | V13: -0.001 | W13: 0.192 | X13: 0.236 | Y13: 0.317 | Z13: 0.419 | AA13: -0.095 | AB13: -0.095 | AC13: 0.011 | AD13: -0.022 | AE13: -0.118 | AF13: 0 | AG13: 0.009 | AH13: 0 | AI13: 0 | AJ13: 0.02 | AK13: -0.004 | AL13: 5.019 | AM13: 0 | AN13: 5.019 | AO13: 0.745 | AP13: 0.286 | AQ13: 0.16 | AR13: 6.21 | AS13: 0.727 | AT13: 0.984 | AU13: 0.218 | AV13: 0.06 | AW13: 2.472 | AX13: 8.682 | AY13: 0.019 | AZ13: 0.026 | BA13: 2.018 | BB13: 6.157 | BC13: 2.525 | BD13: -0.059 | BE13: -0.154
... A27: 2018-01-31 | B27: 1 | C27: 0.505 | D27: 0.158 | E27: 0.885 | F27: 1.043 | G27: 0.411 | H27: 0 | I27: -0.95 | J27: 0 | K27: 0.005 | L27: 0.012 | M27: -1.077 | N27: 1.112 | O27: 1.112 | P27: -0.263 | Q27: -0.504 | R27: 0 | S27: 0 | T27: -0.017 | U27: 0.035 | V27: 0 | W27: -0.6 | X27: -0.096 | Y27: -0.076 | Z27: -0.174 | AA27: -0.089 | AB27: -0.089 | AC27: 0 | AD27: 0 | AE27: 0.001 | AF27: 0 | AG27: 0 | AH27: 0 | AI27: 0 | AJ27: 0.091 | AK27: 0.005 | AL27: 1.632 | AM27: 0.067 | AN27: 1.699 | AO27: 1.54 | AP27: 0 | AQ27: 0.729 | AR27: 3.968 | AS27: 0.797 | AT27: 0.218 | AU27: 0.301 | AV27: 0 | AW27: 1.655 | AX27: 5.623 | AY27: 0.317 | AZ27: 0 | BA27: 0.413 | BB27: 6.1 | BC27: -0.477 | BD27: -0.967 | BE27: -1.056

Sheet Quarterly % Change
A1: date | B1: revenue | C1: grossProfit | D1: generalAndAdministrativeExpenses | E1: sellingAndMarketingExpenses | F1: sellingGeneralAndAdministrativeExpenses | G1: researchAndDevelopmentExpenses | H1: otherExpenses | I1: operatingIncome | J1: interestExpense | K1: interestIncome | L1: incomeTaxExpense | M1: netIncome | N1: weightedAverageShsOut | O1: weightedAverageShsOutDil | P1: freeCashFlow | Q1: accountsReceivables | R1: accountsPayables | S1: inventory_x | T1: depreciationAndAmortization | U1: stockBasedCompensation | V1: deferredIncomeTax | W1: changeInWorkingCapital | X1: otherWorkingCapital | Y1: netChangeInCash | Z1: netCashProvidedByOperatingActivities | AA1: capitalExpenditure | AB1: investmentsInPropertyPlantAndEquipment | AC1: acquisitionsNet | AD1: purchasesOfInvestments | AE1: netCashUsedForInvestingActivites | AF1: debtRepayment | AG1: commonStockIssued | AH1: commonStockRepurchased | AI1: dividendsPaid | AJ1: netCashUsedProvidedByFinancingActivities | AK1: effectOfForexChangesOnCash | AL1: cashAndCashEquivalents | AM1: shortTermInvestments | AN1: cashAndShortTermInvestments | AO1: netReceivables | AP1: inventory_y | AQ1: otherCurrentAssets | AR1: totalCurrentAssets | AS1: propertyPlantEquipmentNet | AT1: goodwill | AU1: intangibleAssets | AV1: longTermInvestments | AW1: totalNonCurrentAssets | AX1: totalAssets | AY1: accountPayables | AZ1: shortTermDebt | BA1: longTermDebt | BB1: totalLiabilities | BC1: totalEquity | BD1: EBITDA | BE1: FCFsimple
A2: 2024-07-31 | B2: 0.047 | C2: 0.042 | D2: 0.026 | E2: 0.015 | F2: 0.015 | G2: 0.067 | H2: -1.135 | I2: 1.041 | J2: 0.006 | K2: 0.124 | L2: 0.424 | M2: 0.098 | N2: 0.007 | O2: 0.004 | P2: -0.155 | Q2: -0.722 | R2: -2.261 | T2: 0.08 | U2: 0.097 | V2: 5.565 | W2: -2.61 | X2: -0.223 | Y2: 0.027 | Z2: -0.148 | AA2: -0.106 | AB2: -0.106 | AC2: -1.052 | AD2: -0.37 | AE2: -0.014 | AG2: 69.158 | AJ2: -20.051 | AK2: -1.457 | AL2: 0.091 | AN2: 0.091 | AO2: -0.059 | AQ2: 0.204 | AR2: 0.073 | AS2: 0.027 | AT2: 0 | AU2: -0.052 | AV2: -0.003 | AW2: 0.012 | AX2: 0.053 | AY2: -0.011 | AZ2: 0.063 | BA2: 0.001 | BB2: 0.009 | BC2: 0.125 | BD2: 0.2 | BE2: -3.856
A3: 2024-04-30 | B3: 0.09 | C3: 0.094 | D3: 0.01 | E3: 0.206 | F3: 0.161 | G3: 0.099 | H3: 1.117 | I3: -0.777 | J3: 0.014 | K3: 0.1 | L3: -0.437 | M3: -0.203 | N3: 0.006 | O3: 0.009 | P3: 0.183 | Q3: -1.53 | R3: -1.013 | S3: -1 | T3: 0.149 | U3: 0.039 | V3: -0.753 | W3: 3.492 | X3: -1.381 | Y3: -0.194 | Z3: 0.104 | AA3: -0.187 | AB3: -0.187 | AC3: 340.196 | AD3: -0.668 | AE3: -3.481 | AG3: -0.975 | AH3: -1 | AJ3: -1.09 | AK3: -1.357 | AL3: 0.097 | AM3: -1 | AN3: 0.066 | AO3: -0.176 | AP3: -1 | AQ3: 0.046 | AR3: 0.019 | AS3: 0.011 | AT3: 0.132 | AU3: 0.066 | AV3: 0.039 | AW3: 0.051 | AX3: 0.029 | AY3: -0.244 | AZ3: 0.132 | BA3: 0.001 | BB3: -0.008 | BC3: 0.099 | BD3: -0.243 | BE3: 6.996
A4: 2024-01-31 | B4: 0.075 | C4: 0.076 | D4: -0.027 | E4: 0.015 | F4: -0.002 | G4: 0.091 | H4: -8.629 | I4: 8.832 | J4: 10.74 | K4: 0.04 | L4: 0.417 | M4: 1.014 | N4: 0.007 | O4: 0.017 | P4: 0.139 | Q4: 12.593 | R4: -4.979 | S4: -2.137 | T4: 0.103 | U4: 0.104 | V4: -0.485 | W4: -1.6 | X4: -7.05 | Y4: -3.074 | Z4: 0.269 | AA4: 1.183 | AB4: 1.183 | AC4: -0.999 | AD4: -0.975 | AE4: -1.044 | AG4: 15.298 | AH4: inf | AJ4: 15.298 | AK4: -2.195 | AL4: 0.137 | AM4: -0.496 | AN4: 0.097 | AO4: 0.518 | AP4: -1 | AQ4: 0.293 | AR4: 0.106 | AS4: 0.058 | AT4: 0.001 | AU4: 0.047 | AV4: -0.055 | AW4: 0.219 | AX4: 0.14 | AY4: -0.505 | AZ4: -0.019 | BA4: -0.049 | BB4: 0.143 | BC4: 0.134 | BD4: 0.767 | BE4: -1.074
A5: 2023-10-31 | B5: 0.074 | C5: 0.077 | D5: -0.311 | E5: 0.236 | F5: 0.018 | G5: 0.093 | H5: -0.727 | I5: -1.206 | J5: -0.915 | K5: 0.094 | L5: 1.083 | M5: 2.147 | N5: 0.006 | O5: 0.007 | P5: 0.269 | Q5: -0.734 | R5: -0.658 | S5: 6.319 | T5: 0.134 | U5: -0.031 | V5: 19.649 | W5: -0.507 | X5: -2.643 | Y5: -1.577 | Z5: 0.117 | AA5: -0.394 | AB5: -0.394 | AC5: 1.442 | AD5: 86.185 | AE5: -12.227 | AG5: -0.956 | AJ5: -0.959 | AK5: -4.53 | AL5: -0.063 | AM5: inf | AN5: 0 | AO5: 0.042 | AP5: 0.061 | AQ5: -0.034 | AR5: 0.007 | AS5: 0.04 | AT5: 0.481 | AU5: 0.383 | AV5: 0 | AW5: 0.192 | AX5: 0.056 | AY5: 0.537 | AZ5: -0.106 | BA5: 0.008 | BB5: 0.033 | BC5: 0.102 | BD5: 1.248 | BE5: -1.205
A6: 2023-07-31 | B6: 0.056 | C6: 0.048 | D6: 0.855 | E6: -0.177 | F6: 0.058 | G6: 0.002 | H6: -8.539 | I6: -2.361 | J6: 0.009 | K6: 0.2 | L6: 0.046 | M6: 16.255 | N6: 0.006 | O6: 0.006 | P6: -0.171 | Q6: -1.475 | R6: -1.84 | S6: inf | T6: 0.108 | U6: 0.259 | V6: -0.62 | W6: -1.298 | X6: -1.472 | Y6: -0.094 | Z6: -0.186 | AA6: -0.235 | AB6: -0.235 | AC6: -9.966 | AD6: -0.792 | AE6: -0.368 | AG6: 16.694 | AJ6: 5.289 | AK6: -7.7 | AL6: 0.119 | AM6: -1 | AN6: 0.081 | AO6: 0.17 | AP6: 0.055 | AQ6: 0.118 | AR6: 0.092 | AS6: 0.058 | AT6: 0 | AU6: -0.049 | AV6: 0.029 | AW6: 0.029 | AX6: 0.074 | AY6: 1.194 | AZ6: -0.005 | BA6: -0.005 | BB6: 0.042 | BC6: 0.144 | BD6: -0.558 | BE6: 0.198
A7: 2023-04-30 | B7: 0.087 | C7: 0.133 | D7: -0.028 | E7: 0.141 | F7: 0.098 | G7: -0.067 | H7: -1.083 | I7: -1.184 | J7: 0.006 | K7: 0.13 | L7: -0.17 | M7: -1.01 | N7: 0.006 | O7: 0.024 | P7: 0.095 | Q7: -2.172 | R7: -0.54 | T7: 0.098 | U7: -0.141 | V7: -0.74 | W7: -0.085 | X7: -1.247 | Y7: -34.648 | Z7: 0.101 | AA7: 0.119 | AB7: 0.119 | AC7: 93.8 | AD7: -0.957 | AE7: -1.207 | AG7: -0.903 | AH7: -1 | AJ7: -0.71 | AK7: -1.034 | AL7: 0.152 | AM7: -0.6 | AN7: 0.083 | AO7: -0.264 | AP7: 0 | AQ7: 0.076 | AR7: 0.019 | AS7: 0.079 | AT7: 0 | AU7: -0.042 | AV7: 0.224 | AW7: 0.031 | AX7: 0.022 | AY7: -0.628 | AZ7: 0.243 | BA7: 0.01 | BB7: -0.01 | BC7: 0.099 | BD7: -2.245 | BE7: -0.684
A8: 2023-01-31 | B8: 0.097 | C8: 0.093 | D8: 0.01 | E8: 0.028 | F8: 0.023 | G8: 0.236 | H8: -4.709 | I8: 0.09 | J8: 0.003 | K8: 0.663 | L8: -0.401 | M8: -0.104 | N8: 0.005 | O8: 0.005 | P8: 0.194 | Q8: 1.118 | R8: -2.671 | T8: 0.179 | U8: 0.087 | V8: -2.437 | W8: 0.009 | X8: 1.084 | Y8: -1.075 | Z8: 0.125 | AA8: -0.049 | AB8: -0.049 | AC8: -1.006 | AD8: 23.935 | AE8: 2.276 | AF8: -1 | AG8: 17.438 | AH8: inf | AJ8: -239.886 | AK8: -3.033 | AL8: -0.005 | AM8: inf | AN8: 0.097 | AO8: 0.29 | AP8: 0.152 | AQ8: 0.362 | AR8: 0.136 | AS8: 0.168 | AT8: 0.001 | AU8: -0.029 | AV8: 0.019 | AW8: 0.095 | AX8: 0.125 | AY8: -0.492 | AZ8: 0.252 | BA8: 0.016 | BB8: 0.13 | BC8: 0.112 | BD8: 0.026 | BE8: -0.025
A9: 2022-10-31 | B9: 0.085 | C9: 0.071 | D9: 0.048 | E9: 0.066 | F9: 0.062 | G9: 0.126 | H9: -0.778 | I9: 0.168 | J9: 0 | K9: 1.102 | L9: 0.856 | M9: 0.108 | N9: 0.005 | O9: 0.005 | P9: 0.282 | Q9: 0.339 | R9: -0.35 | T9: 0.078 | U9: 0.065 | V9: -5.608 | W9: 0.357 | X9: 0.373 | Y9: -0.119 | Z9: 0.157 | AA9: -0.072 | AB9: -0.072 | AC9: -8.383 | AD9: 1.036 | AE9: 0.231 | AF9: -inf | AG9: -0.959 | AJ9: -1.003 | AK9: 0.477 | AL9: 0.064 | AN9: 0.064 | AO9: 0.159 | AP9: 162259999 | AQ9: -0.008 | AR9: 0.076 | AS9: 0.107 | AT9: 0.034 | AU9: -0.004 | AV9: 0.304 | AW9: 0.074 | AX9: 0.076 | AY9: 0.659 | AZ9: 0.01 | BA9: -0.004 | BB9: 0.076 | BC9: 0.076 | BD9: 0.243 | BE9: 0.01
A10: 2022-07-31 | B10: 0.097 | C10: 0.093 | D10: 0.181 | E10: 0.161 | F10: 0.167 | G10: 0.117 | H10: 0.052 | I10: 1.023 | J10: 0.101 | K10: 4.127 | L10: 0.389 | M10: 0.621 | N10: 0.033 | O10: 0.006 | P10: -0.134 | Q10: 45.947 | R10: -2.022 | T10: 0.072 | U10: 0.283 | V10: -1.084 | W10: -0.225 | X10: -0.216 | Y10: 0.074 | Z10: -0.023 | AA10: 0.276 | AB10: 0.276 | AC10: 0.711 | AD10: 0.77 | AE10: 0.299 | AG10: 10.674 | AJ10: 11.479 | AK10: -0.248 | AL10: 0.077 | AN10: 0.077 | AO10: 0.135 | AP10: -1 | AQ10: 0.195 | AR10: 0.089 | AS10: 0.193 | AT10: 0 | AU10: -0.044 | AV10: 0.241 | AW10: 0.068 | AX10: 0.083 | AY10: 3.882 | AZ10: 0.035 | BA10: -0.001 | BB10: 0.071 | BC10: 0.113 | BD10: 6.643 | BE10: 0.633
A11: 2022-04-30 | B11: 0.132 | C11: 0.134 | D11: -0.086 | E11: 0.19 | F11: 0.104 | G11: 0.175 | H11: 0.913 | I11: 0.015 | J11: -0.087 | K11: inf | L11: -0.747 | M11: -0.276 | N11: -0.02 | O11: 0.007 | P11: 0.232 | Q11: -0.988 | R11: -1.904 | S11: -1 | T11: -0.003 | U11: 0.106 | V11: -1.119 | W11: 0.252 | X11: -0.243 | Y11: 0.752 | Z11: 0.346 | AA11: 0.795 | AB11: 0.795 | AC11: -1.024 | AD11: 4.65 | AE11: -0.349 | AG11: -0.88 | AH11: -1 | AJ11: -0.881 | AK11: -0.205 | AL11: 0.078 | AN11: 0.078 | AO11: 0.003 | AP11: 0.07 | AQ11: -0.048 | AR11: 0.063 | AS11: 0.18 | AT11: -0.001 | AU11: -0.035 | AV11: 0.213 | AW11: 0.053 | AX11: 0.06 | AY11: -0.769 | AZ11: 0.015 | BA11: -0.004 | BB11: 0.054 | BC11: 0.076 | BD11: 0.135 | BE11: 0.738
A12: 2022-01-31 | B12: 0.134 | C12: 0.144 | D12: 0.326 | E12: -0.014 | F12: 0.072 | G12: 0.076 | H12: 1.433 | I12: -0.416 | J12: -0.016 | K12: -1 | L12: 2.036 | M12: -0.168 | N12: 0.006 | O12: 0.006 | P12: 0.037 | Q12: 4.169 | R12: -4.244 | S12: -inf | T12: 0.147 | U12: 0.069 | V12: 42.31 | W12: -0.1 | X12: 0.769 | Y12: -0.26 | Z12: 0.004 | AA12: -0.106 | AB12: -0.106 | AC12: -15.299 | AD12: -0.941 | AE12: 1.094 | AG12: 6.847 | AH12: inf | AJ12: 2.465 | AK12: 1.191 | AL12: 0.047 | AN12: 0.047 | AO12: 0.3 | AP12: 0.167 | AQ12: 0.308 | AR12: 0.089 | AS12: 0.059 | AT12: 0.114 | AU12: 0.175 | AV12: 0.043 | AW12: 0.115 | AX12: 0.097 | AY12: 5.646 | AZ12: 0.012 | BA12: -0.003 | BB12: 0.103 | BC12: 0.081 | BD12: -0.864 | BE12: -0.396
A13: 2021-10-31 | B13: 0.125 | C13: 0.126 | D13: 0.114 | E13: 0.072 | F13: 0.082 | G13: 0.079 | H13: 0.115 | I13: -0.151 | J13: 0.017 | K13: inf | L13: 0.055 | M13: -0.12 | N13: 0.009 | O13: 0.009 | P13: 0.668 | Q13: -0.706 | R13: -1.779 | T13: 0.11 | U13: 0.136 | V13: -2.111 | W13: 0.656 | X13: -0.104 | Y13: 0.18 | Z13: 0.466 | AA13: 0.04 | AB13: 0.04 | AC13: -13.537 | AD13: 0.417 | AE13: 0.086 | AG13: -0.9 | AJ13: -0.791 | AK13: -0.011 | AL13: 0.067 | AN13: 0.067 | AO13: 0.063 | AP13: 0.138 | AQ13: -0.411 | AR13: 0.048 | AS13: 0.101 | AT13: -0.001 | AU13: -0.032 | AV13: 0.6 | AW13: 0.063 | AX13: 0.052 | AY13: -0.635 | AZ13: 0.035 | BA13: -0.001 | BB13: 0.052 | BC13: 0.053 | BD13: -0.285 | BE13: -0.114
A14: 2021-07-31 | B14: 0.115 | C14: 0.102 | D14: 0.188 | E14: 0.139 | F14: 0.15 | G14: 0.157 | H14: -0.87 | I14: 0.512 | J14: 0.108 | L14: -0.915 | M14: -0.326 | N14: 0.01 | O14: 0.01 | P14: -0.372 | Q14: -2.771 | R14: -2.51 | S14: -1 | T14: 0.119 | U14: 0.403 | V14: -1.075 | W14: -0.681 | X14: 0.369 | Y14: -1.437 | Z14: -0.265 | AA14: 0.152 | AB14: 0.152 | AC14: -0.999 | AD14: 3.584 | AE14: -0.893 | AG14: 7.841 | AJ14: 12.871 | AK14: -2.204 | AL14: 0.061 | AN14: 0.061 | AO14: 0.262 | AP14: 0.118 | AQ14: 0.826 | AR14: 0.105 | AS14: 0.1 | AT14: -0.001 | AU14: -0.037 | AV14: 0.735 | AW14: 0.048 | AX14: 0.088 | AY14: 4.664 | AZ14: 0.004 | BA14: -0.002 | BB14: 0.097 | BC14: 0.068 | BD14: 0.845 | BE14: 0.401
A15: 2021-04-30 | B15: 0.143 | C15: 0.132 | D15: 0.194 | E15: 0.202 | F15: 0.2 | G15: 0.183 | H15: 5.991 | I15: 0.984 | J15: 4.418 | L15: 16.677 | M15: 3.476 | N15: 0.011 | O15: 0.011 | P15: 0.207 | Q15: -1.474 | R15: -3.215 | S15: 0.46 | T15: 0.214 | U15: 0.139 | V15: 49.16 | W15: 1.663 | X15: -0.121 | Y15: -1.272 | Z15: 0.289 | AA15: 0.752 | AB15: 0.752 | AC15: 7361.646 | AD15: -3.265 | AE15: 21.25 | AF15: -1 | AG15: -1.174 | AH15: -1 | AJ15: -0.997 | AK15: 0.204 | AL15: -0.122 | AN15: -0.122 | AO15: -0.117 | AP15: 0.056 | AQ15: 0.052 | AR15: -0.111 | AS15: 0.12 | AT15: 3.482 | AU15: 4.668 | AV15: 2.266 | AW15: 0.915 | AX15: 0.054 | AY15: -0.713 | AZ15: 0.04 | BA15: 0 | BB15: 0.09 | BC15: -0.021 | BD15: 3.279 | BE15: 1.225
A16: 2021-01-31 | B16: 0.14 | C16: 0.16 | D16: 0.11 | E16: 0.065 | F16: 0.075 | G16: 0.148 | H16: 1.507 | I16: -0.346 | J16: 4.435 | L16: 5.279 | M16: -0.225 | N16: 0.01 | O16: 0.01 | P16: 0.277 | Q16: 1.991 | R16: -2.549 | S16: -0.059 | T16: 0.129 | U16: 0.175 | V16: -0.547 | W16: 0.226 | X16: 1.36 | Y16: -179.594 | Z16: 0.293 | AA16: 0.391 | AB16: 0.391 | AC16: -0.999 | AD16: -2.156 | AE16: -0.824 | AF16: 0 | AG16: -2 | AH16: inf | AJ16: 146.076 | AK16: -10.438 | AL16: 0.81 | AM16: -1 | AN16: 0.81 | AO16: 0.384 | AP16: 0.295 | AQ16: 0.174 | AR16: 0.71 | AS16: 0.014 | AT16: 0.005 | AU16: -0.042 | AV16: 0 | AW16: 0.077 | AX16: 0.562 | AY16: 0.61 | AZ16: 0.038 | BA16: 21.644 | BB16: 0.991 | BC16: 0.07 | BD16: -0.71 | BE16: -0.187
A17: 2020-10-31 | B17: 0.168 | C17: 0.182 | D17: 0.103 | E17: 0.11 | F17: 0.109 | G17: 0.14 | H17: -0.628 | I17: -0.194 | J17: 0.109 | L17: 0.023 | M17: -0.179 | N17: 0.012 | O17: 0.012 | P17: 1.347 | Q17: 3.788 | R17: -1.628 | S17: -5.536 | T17: 0.1 | U17: 0.077 | V17: -0.572 | W17: 1.067 | X17: 0.281 | Y17: -1.08 | Z17: 0.608 | AA17: -0.451 | AB17: -0.451 | AC17: -inf | AD17: -0.5 | AE17: 3.167 | AF17: -inf | AG17: inf | AJ17: -0.812 | AK17: -1.134 | AL17: -0.005 | AM17: inf | AN17: -0.005 | AO17: 0.158 | AP17: 0.159 | AQ17: -0.052 | AR17: 0.019 | AS17: 0.036 | AT17: 9.224 | AU17: 46.135 | AV17: 0.25 | AW17: 0.358 | AX17: 0.082 | AY17: -0.259 | AZ17: 0 | BA17: -0.059 | BB17: 0.133 | BC17: 0.029 | BD17: -0.332 | BE17: -0.394
A18: 2020-07-31 | B18: 0.117 | C18: 0.102 | D18: 0.156 | E18: 0.079 | F18: 0.096 | G18: 0.244 | H18: -0.839 | I18: 0.328 | J18: 0.217 | L18: -0.574 | M18: 0.554 | N18: 0.017 | O18: 0.017 | P18: -0.627 | Q18: -1.224 | R18: 0.034 | S18: -3.422 | T18: 0.147 | U18: 0.595 | V18: -0.326 | W18: -0.709 | X18: -0.35 | Y18: -0.919 | Z18: -0.442 | AA18: 0.953 | AB18: 0.953 | AC18: -1 | AD18: -0.988 | AE18: -1.037 | AJ18: 2.996 | AK18: 64.333 | AL18: 0.059 | AN18: 0.059 | AO18: 0.035 | AP18: 0.008 | AQ18: 0.05 | AR18: 0.054 | AS18: 0.108 | AT18: 0.063 | AU18: -0.172 | AV18: 1 | AW18: 0.111 | AX18: 0.064 | AY18: 0.55 | AZ18: 0.295 | BA18: 0.098 | BB18: 0.077 | BC18: 0.052 | BD18: 0.434 | BE18: 0.667
A19: 2020-04-30 | B19: 0.171 | C19: 0.207 | D19: -0.011 | E19: 0.163 | F19: 0.119 | G19: 0.049 | H19: 0.415 | I19: -0.275 | J19: -0.014 | L19: 2.111 | M19: -0.323 | N19: 0.027 | O19: 0.027 | P19: 0.717 | Q19: -2.063 | R19: -1.504 | S19: -0.773 | T19: 0.169 | U19: -0.03 | V19: -3.967 | W19: 0.363 | X19: -0.407 | Y19: -2.546 | Z19: 0.491 | AA19: -0.25 | AB19: -0.25 | AC19: -0.096 | AD19: -0.857 | AE19: -2.109 | AG19: -1 | AH19: -1 | AJ19: -0.748 | AK19: -1.11 | AL19: 2.795 | AM19: -1 | AN19: 0.102 | AO19: -0.126 | AP19: 0.243 | AQ19: -0.111 | AR19: 0.066 | AS19: 0.285 | AT19: -0.009 | AU19: -0.205 | AV19: 0 | AW19: 0.161 | AX19: 0.081 | AY19: 3.854 | AZ19: -0.901 | BA19: inf | BB19: 0.157 | BC19: 0.014 | BD19: -0.406 | BE19: -0.345
A20: 2020-01-31 | B20: 0.216 | C20: 0.238 | D20: 0.172 | E20: 0.104 | F20: 0.12 | G20: 0.075 | H20: -0.105 | I20: -0.192 | J20: 0.098 | L20: -0.233 | M20: -0.2 | N20: 0.017 | O20: 0.017 | P20: 6.19 | Q20: -0.37 | R20: -inf | S20: inf | T20: 0.198 | U20: 0.109 | V20: 4.5 | W20: 0.399 | X20: 0.05 | Y20: -45.346 | Z20: 0.711 | AA20: -0.511 | AB20: -0.511 | AC20: 0.096 | AD20: 7.456 | AE20: 19.986 | AG20: inf | AH20: inf | AJ20: -29.213 | AK20: -1.278 | AL20: -0.644 | AM20: 6.185 | AN20: 0.094 | AO20: 0.132 | AP20: 0.196 | AQ20: 0.361 | AR20: 0.112 | AS20: 0.051 | AT20: -0.009 | AU20: -0.173 | AV20: inf | AW20: 0.15 | AX20: 0.119 | AY20: -0.744 | AZ20: 0.012 | BB20: 0.229 | BC20: 0.036 | BD20: -0.263 | BE20: -0.385
A21: 2019-10-31 | B21: 0.157 | C21: 0.147 | D21: -0.286 | E21: 0.052 | F21: -0.055 | G21: 0.138 | H21: -8.936 | I21: -0.239 | J21: -0.195 | L21: -0.317 | M21: -0.316 | N21: 0.569 | O21: 0.569 | P21: -1.242 | Q21: 0.094 | T21: 0.086 | U21: -0.264 | V21: -0.992 | W21: -14.999 | X21: 1.658 | Y21: -0.983 | Z21: -7.217 | AA21: 0.377 | AB21: 0.377 | AC21: 0.431 | AD21: 0.066 | AE21: -0.207 | AJ21: -1.001 | AK21: -2.49 | AL21: 0.015 | AM21: -0.042 | AN21: 0.008 | AO21: 0.264 | AP21: 0.056 | AQ21: 0.292 | AR21: 0.048 | AS21: 0.199 | AT21: 0.002 | AU21: -0.137 | AW21: 0.221 | AX21: 0.072 | AY21: 3.657 | AZ21: 0.261 | BB21: 0.215 | BC21: -0.015 | BD21: -0.279 | BE21: -0.058
A22: 2019-07-31 | B22: 0.125 | C22: 0.146 | D22: 1.551 | E22: 0.148 | F22: 0.391 | G22: 0.325 | H22: -2.145 | I22: 0.965 | J22: 163 | L22: 0.067 | M22: 0.997 | N22: -0.339 | O22: -0.339 | P22: 0.81 | Q22: -6.242 | R22: -1 | S22: -1 | T22: 0.088 | U22: 6.958 | V22: 10.71 | W22: -1.234 | X22: 0.58 | Y22: 138.545 | Z22: -5.392 | AA22: 0.309 | AB22: 0.309 | AC22: -0.332 | AD22: 0.27 | AE22: -9.311 | AJ22: -772.751 | AK22: 2.058 | AL22: 6.88 | AM22: 0.145 | AN22: 3.723 | AO22: 0.319 | AP22: 0.299 | AQ22: 0.296 | AR22: 2.23 | AS22: 0.251 | AT22: -0.004 | AU22: -0.16 | AW22: 0.137 | AX22: 1.562 | AY22: -0.886 | AZ22: 0.2 | BB22: -0.529 | BC22: -2.501 | BD22: 1.177 | BE22: 0.78
A23: 2019-04-30 | B23: 0.194 | C23: 0.25 | D23: -0.111 | E23: 0.152 | F23: 0.096 | G23: 0.085 | H23: 0.227 | I23: -0.175 | J23: inf | L23: 0.705 | M23: -0.169 | N23: 0.149 | O23: 0.149 | P23: 121.977 | Q23: -1.347 | R23: inf | S23: -inf | T23: 0.054 | U23: 0.21 | V23: 1.703 | W23: -0.621 | X23: -0.643 | Y23: -0.073 | Z23: -0.91 | AA23: 0.1 | AB23: 0.1 | AC23: 0.132 | AD23: -0.192 | AE23: -1.388 | AJ23: 1.714 | AK23: -1.642 | AL23: 0.052 | AM23: -0.205 | AN23: -0.087 | AO23: -0.055 | AP23: -0.432 | AQ23: 19.492 | AR23: -0.061 | AS23: 0.171 | AT23: -0.017 | AU23: -0.161 | AW23: 0.435 | AX23: 0.056 | AY23: 0.446 | AZ23: -0.154 | BB23: 1.629 | BC23: -7.499 | BD23: -0.216 | BE23: -0.097
A24: 2019-01-31 | B24: 0.212 | C24: 0.212 | D24: -0.019 | E24: 0.058 | F24: 0.041 | G24: -0.153 | H24: 0.059 | I24: -0.258 | L24: -0.348 | M24: -0.261 | N24: 0 | O24: 0 | P24: -0.99 | Q24: -0.228 | T24: 0.242 | U24: -0.77 | V24: -0.841 | W24: 1.269 | X24: 0.365 | Y24: -1.154 | Z24: -5.344 | AA24: 0.689 | AB24: 0.689 | AC24: -0.048 | AD24: 0.164 | AE24: -0.708 | AJ24: -1.04 | AK24: -4.268 | AL24: 0.059 | AM24: -0.044 | AN24: 0.001 | AO24: 0.2 | AP24: inf | AQ24: -0.97 | AR24: 0.084 | AS24: 0.523 | AT24: 0.008 | AU24: -0.917 | AW24: 0.212 | AX24: 0.112 | AY24: 0.196 | AZ24: inf | BB24: 0.603 | BC24: -0.227 | BD24: -0.308 | BE24: -0.111
A25: 2018-10-31 | B25: 0.404 | C25: 0.581 | D25: 1.009 | E25: 0.273 | F25: 0.388 | G25: 0.474 | H25: -2.595 | I25: 0.271 | J25: -1 | L25: 3.421 | M25: 0.259 | N25: 0 | O25: 0 | P25: -0.219 | Q25: -1.969 | T25: 0.218 | U25: 6.83 | V25: 10.91 | W25: -0.21 | X25: -9.197 | Y25: 1.328 | Z25: -0.431 | AA25: -0.089 | AB25: -0.089 | AC25: inf | AD25: -inf | AE25: 3.704 | AJ25: 17.027 | AK25: -0.446 | AL25: -2.269 | AM25: -0.179 | AN25: 1.91 | AO25: inf | AQ25: inf | AR25: 3.646 | AS25: inf | AT25: inf | AU25: inf | AW25: -2.277 | AX25: inf | AY25: inf | BB25: inf | BC25: -6.231 | BD25: 0.277 | BE25: 0.183
A26: 2018-04-30 | B26: 0.221 | C26: 0.427 | D26: 0.107 | E26: 0.069 | F26: 0.074 | G26: 0.106 | H26: -inf | I26: -0.099 | J26: inf | K26: -1 | L26: -0.749 | M26: -0.194 | N26: 2.976 | O26: 2.976 | P26: 0.647 | Q26: -2.06 | T26: -5.693 | U26: 0.285 | V26: inf | W26: -1.716 | X26: 0.09 | Y26: 3.69 | Z26: -0.049 | AA26: 2.006 | AB26: 2.006 | AE26: -147.34 | AJ26: -0.873 | AK26: -1.365 | AL26: -2.041 | AM26: 49.73 | AN26: 0 | AO26: -1 | AP26: -1 | AQ26: -1 | AR26: -0.572 | AS26: -1 | AT26: -1 | AU26: -1 | AW26: -2.026 | AX26: -1 | AY26: -1 | BA26: -1 | BB26: -1 | BC26: 0 | BD26: -0.2 | BE26: -0.014
A27: 2018-01-31

Sheet Yearly % Change
A1: date | B1: revenue | C1: grossProfit | D1: generalAndAdministrativeExpenses | E1: sellingAndMarketingExpenses | F1: sellingGeneralAndAdministrativeExpenses | G1: researchAndDevelopmentExpenses | H1: otherExpenses | I1: operatingIncome | J1: interestExpense | K1: interestIncome | L1: incomeTaxExpense | M1: netIncome | N1: weightedAverageShsOut | O1: weightedAverageShsOutDil | P1: freeCashFlow | Q1: accountsReceivables | R1: accountsPayables | S1: inventory_x | T1: depreciationAndAmortization | U1: stockBasedCompensation | V1: deferredIncomeTax | W1: changeInWorkingCapital | X1: otherWorkingCapital | Y1: netChangeInCash | Z1: netCashProvidedByOperatingActivities | AA1: capitalExpenditure | AB1: investmentsInPropertyPlantAndEquipment | AC1: acquisitionsNet | AD1: purchasesOfInvestments | AE1: netCashUsedForInvestingActivites | AF1: debtRepayment | AG1: commonStockIssued | AH1: commonStockRepurchased | AI1: dividendsPaid | AJ1: netCashUsedProvidedByFinancingActivities | AK1: effectOfForexChangesOnCash | AL1: cashAndCashEquivalents | AM1: shortTermInvestments | AN1: cashAndShortTermInvestments | AO1: netReceivables | AP1: inventory_y | AQ1: otherCurrentAssets | AR1: totalCurrentAssets | AS1: propertyPlantEquipmentNet | AT1: goodwill | AU1: intangibleAssets | AV1: longTermInvestments | AW1: totalNonCurrentAssets | AX1: totalAssets | AY1: accountPayables | AZ1: shortTermDebt | BA1: longTermDebt | BB1: totalLiabilities | BC1: totalEquity | BD1: EBITDA | BE1: FCFsimple
A2: 2024-07-31 | B2: 0.317 | C2: 0.322 | D2: -0.305 | E2: 0.536 | F2: 0.197 | G2: 0.399 | H2: -0.405 | I2: -1.921 | J2: 0.016 | K2: 0.406 | L2: 1.367 | M2: 4.549 | N2: 0.026 | O2: 0.038 | P2: 0.445 | Q2: -1.534 | R2: -1.022 | S2: -1 | T2: 0.552 | U2: 0.219 | V2: 16.258 | W2: 1.137 | X2: -3.944 | Y2: -0.01 | Z2: 0.334 | AA2: -0.04 | AB2: -0.04 | AC2: -1.051 | AD2: -0.536 | AE2: -2.195 | AG2: 0.231 | AJ2: 0.156 | AK2: -0.311 | AL2: 0.275 | AN2: 0.275 | AO2: 0.225 | AP2: -1 | AQ2: 0.575 | AR2: 0.217 | AS2: 0.142 | AT2: 0.676 | AU2: 0.462 | AV2: -0.022 | AW2: 0.546 | AX2: 0.305 | AY2: -0.432 | AZ2: 0.056 | BA2: -0.04 | BB2: 0.181 | BC2: 0.546 | BD2: 2.607 | BE2: -1.346
A3: 2024-04-30 | B3: 0.33 | C3: 0.33 | D3: 0.255 | E3: 0.245 | F3: 0.248 | G3: 0.314 | H3: 32.287 | I3: -0.386 | J3: 0.019 | K3: 0.502 | L3: 0.739 | M3: 86.21 | N3: 0.025 | O3: 0.04 | P3: 0.419 | Q3: -0.09 | R3: -1.015 | T3: 0.592 | U3: 0.399 | V3: 0 | W3: -0.605 | X3: 0.789 | Y3: -0.126 | Z3: 0.274 | AA3: -0.178 | AB3: -0.178 | AC3: -9.794 | AD3: -0.847 | AE3: -1.766 | AG3: -0.69 | AJ3: -1.382 | AK3: 9.089 | AL3: 0.308 | AM3: -1 | AN3: 0.264 | AO3: 0.524 | AP3: -1 | AQ3: 0.462 | AR3: 0.239 | AS3: 0.177 | AT3: 0.676 | AU3: 0.466 | AV3: 0.009 | AW3: 0.571 | AX3: 0.332 | AY3: 0.26 | AZ3: -0.012 | BA3: -0.045 | BB3: 0.22 | BC3: 0.572 | BD3: 0.328 | BE3: -0.855
A4: 2024-01-31 | B4: 0.326 | C4: 0.378 | D4: 0.209 | E4: 0.178 | F4: 0.18 | G4: 0.115 | H4: -2.3 | I4: -1.506 | J4: 0.011 | K4: 0.543 | L4: 1.561 | M4: -2.097 | N4: 0.025 | O4: 0.055 | P4: 0.313 | Q4: 1.013 | R4: -0.475 | S4: -inf | T4: 0.521 | U4: 0.157 | V4: 0.053 | W4: -0.919 | X4: 0.16 | Y4: -37.483 | Z4: 0.27 | AA4: 0.132 | AB4: 0.132 | AC4: -3.443 | AD4: -0.98 | AE4: -1.064 | AG4: 0.229 | AH4: 0.285 | AJ4: 0.229 | AK4: -0.038 | AL4: 0.375 | AM4: -0.602 | AN4: 0.284 | AO4: 0.362 | AP4: -1 | AQ4: 0.503 | AR4: 0.239 | AS4: 0.256 | AT4: 0.482 | AU4: 0.318 | AV4: 0.19 | AW4: 0.541 | AX4: 0.322 | AY4: -0.379 | AZ4: 0.085 | BA4: -0.036 | BB4: 0.218 | BC4: 0.571 | BD4: -3.183 | BE4: -0.994
A5: 2023-10-31 | B5: 0.353 | C5: 0.398 | D5: 0.255 | E5: 0.194 | F5: 0.21 | G5: 0.263 | H5: -1.632 | I5: -1.056 | J5: -0.914 | K5: 1.468 | L5: 0.083 | M5: -1.488 | N5: 0.024 | O5: 0.043 | P5: 0.376 | Q5: -0.686 | R5: -0.779 | S5: inf | T5: 0.627 | U5: 0.139 | V5: -3.937 | W5: -1.135 | X5: -1.4 | Y5: -2.326 | Z5: 0.126 | AA5: -0.507 | AB5: -0.507 | AC5: 11.931 | AD5: 18.268 | AE5: 3.813 | AF5: -1 | AG5: 0.39 | AJ5: -19.009 | AK5: 0.638 | AL5: 0.204 | AM5: inf | AN5: 0.284 | AO5: 0.158 | AP5: 0.289 | AQ5: 0.583 | AR5: 0.273 | AS5: 0.387 | AT5: 0.482 | AU5: 0.223 | AV5: 0.283 | AW5: 0.384 | AX5: 0.305 | AY5: -0.362 | AZ5: 0.384 | BA5: 0.029 | BB5: 0.204 | BC5: 0.541 | BD5: -2.268 | BE5: -1.075
A6: 2023-07-31 | B6: 0.367 | C6: 0.391 | D6: 0.909 | E6: 0.03 | F6: 0.261 | G6: 0.301 | H6: -1.513 | I6: -0.682 | J6: 0.017 | K6: 3.742 | L6: -0.035 | M6: -1.172 | N6: 0.023 | O6: 0.041 | P6: 0.391 | Q6: 0.578 | R6: -0.581 | S6: inf | T6: 0.546 | U6: 0.253 | V6: -0.345 | W6: -1.373 | X6: -0.666 | Y6: 1.025 | Z6: 0.166 | AA6: -0.245 | AB6: -0.245 | AC6: -40.084 | AD6: -0.55 | AE6: -1.528 | AG6: 0.294 | AJ6: 0.283 | AK6: -1.685 | AL6: 0.366 | AN6: 0.366 | AO6: 0.288 | AP6: 197110999 | AQ6: 0.625 | AR6: 0.361 | AS6: 0.477 | AT6: 0.035 | AU6: -0.119 | AV6: 0.673 | AW6: 0.248 | AX6: 0.329 | AY6: -0.311 | AZ6: 0.564 | BA6: 0.017 | BB6: 0.254 | BC6: 0.504 | BD6: -1.701 | BE6: -0.627
A7: 2023-04-30 | B7: 0.42 | C7: 0.45 | D7: 0.216 | E7: 0.453 | F7: 0.391 | G7: 0.451 | H7: -0.928 | I7: -1.473 | J7: 0.11 | K7: 19.253 | L7: 0.282 | M7: -1.016 | N7: 0.05 | O7: 0.041 | P7: 0.452 | Q7: -157.039 | R7: -0.49 | T7: 0.497 | U7: 0.277 | V7: -1.146 | W7: -0.029 | X7: -1.554 | Y7: 1.4 | Z7: 0.4 | AA7: 0.259 | AB7: 0.259 | AC7: 6.457 | AD7: 2.824 | AE7: -2.083 | AG7: -0.146 | AJ7: 1.546 | AK7: -0.923 | AL7: 0.314 | AM7: inf | AN7: 0.361 | AO7: 0.249 | AP7: 0.378 | AQ7: 0.736 | AR7: 0.357 | AS7: 0.664 | AT7: 0.035 | AU7: -0.114 | AV7: 1.019 | AW7: 0.296 | AX7: 0.339 | AY7: 0.533 | AZ7: 0.627 | BA7: 0.021 | BB7: 0.289 | BC7: 0.463 | BD7: -13.124 | BE7: -0.492
A8: 2023-01-31 | B8: 0.479 | C8: 0.45 | D8: 0.144 | E8: 0.516 | F8: 0.399 | G8: 0.827 | H8: -2.657 | I8: 1.613 | J8: 0.008 | K8: inf | L8: -0.609 | M8: 0.166 | N8: 0.023 | O8: 0.023 | P8: 0.633 | Q8: 0.663 | R8: -2.005 | S8: -1 | T8: 0.359 | U8: 0.645 | V8: -0.933 | W8: 0.329 | X8: 0.697 | Y8: -1.125 | Z8: 0.711 | AA8: 1.019 | AB8: 1.019 | AC8: -1.002 | AD8: 506.732 | AE8: 2.407 | AG8: 0.05 | AH8: 0.182 | AJ8: 0.04 | AK8: -2.793 | AL8: 0.23 | AM8: inf | AN8: 0.355 | AO8: 0.701 | AP8: 0.473 | AQ8: 0.536 | AR8: 0.416 | AS8: 0.821 | AT8: 0.034 | AU8: -0.107 | AV8: 1 | AW8: 0.324 | AX8: 0.389 | AY8: -0.047 | AZ8: 0.329 | BA8: 0.007 | BB8: 0.371 | BC8: 0.433 | BD8: 10.058 | BE8: 1.795
A9: 2022-10-31 | B9: 0.528 | C9: 0.518 | D9: 0.501 | E9: 0.453 | F9: 0.465 | G9: 0.59 | H9: 0.087 | I9: 0.401 | J9: -0.011 | K9: 14.942 | L9: 0.983 | M9: 0.083 | N9: 0.024 | O9: 0.024 | P9: 0.417 | Q9: 3.059 | R9: -2.95 | T9: 0.323 | U9: 0.617 | V9: -3.012 | W9: 0.185 | X9: 0.441 | Y9: 0.226 | Z9: 0.527 | AA9: 0.898 | AB9: 0.898 | AC9: -5.344 | AD9: 0.198 | AE9: 1.178 | AF9: -inf | AG9: -0.553 | AJ9: -1.015 | AK9: 0.932 | AL9: 0.293 | AN9: 0.293 | AO9: 0.713 | AP9: 0.494 | AQ9: 0.475 | AR9: 0.357 | AS9: 0.65 | AT9: 0.151 | AU9: 0.08 | AV9: 1.047 | AW9: 0.347 | AX9: 0.355 | AY9: 11.458 | AZ9: 0.074 | BA9: -0.011 | BB9: 0.338 | BC9: 0.394 | BD9: 0.464 | BE9: 0.732
A10: 2022-07-31 | B10: 0.585 | C10: 0.596 | D10: 0.594 | E10: 0.461 | F10: 0.494 | G10: 0.524 | H10: 4.46 | I10: 0.019 | J10: 0.006 | K10: inf | L10: 0.127 | M10: -0.14 | N10: 0.027 | O10: 0.027 | P10: 0.844 | Q10: -0.109 | R10: 1.335 | T10: 0.362 | U10: 0.724 | V10: -1.485 | W10: 0.446 | X10: -0.059 | Y10: 0.643 | Z10: 0.935 | AA10: 1.129 | AB10: 1.129 | AC10: -8.378 | AD10: -0.167 | AE10: 0.922 | AG10: 0.092 | AJ10: 0.071 | AK10: 0.294 | AL10: 0.298 | AN10: 0.298 | AO10: 0.571 | AP10: -1 | AQ10: -0.124 | AR10: 0.321 | AS10: 0.641 | AT10: 0.112 | AU10: 0.05 | AV10: 1.512 | AW10: 0.333 | AX10: 0.325 | AY10: 1.74 | AZ10: 0.1 | BA10: -0.009 | BB10: 0.308 | BC10: 0.364 | BD10: -0.157 | BE10: 0.52
A11: 2022-04-30 | B11: 0.611 | C11: 0.609 | D11: 0.604 | E11: 0.432 | F11: 0.473 | G11: 0.578 | H11: -0.326 | I11: -0.238 | J11: 0.012 | K11: inf | L11: -0.931 | M11: -0.642 | N11: 0.005 | O11: 0.031 | P11: 0.337 | Q11: -1.034 | R11: 2.449 | S11: -1 | T11: 0.421 | U11: 0.885 | V11: -1.431 | W11: -0.405 | X11: 0.643 | Y11: -1.668 | Z11: 0.457 | AA11: 0.923 | AB11: 0.923 | AC11: -1.004 | AD11: 1.158 | AE11: -0.842 | AG11: -0.173 | AJ11: 0.19 | AK11: -3.072 | AL11: 0.278 | AN11: 0.278 | AO11: 0.748 | AP11: 0.589 | AQ11: 0.339 | AR11: 0.341 | AS11: 0.513 | AT11: 0.111 | AU11: 0.057 | AV11: 2.511 | AW11: 0.308 | AX11: 0.331 | AY11: 2.179 | AZ11: 0.068 | BA11: -0.01 | BB11: 0.341 | BC11: 0.309 | BD11: -0.797 | BE11: 0.305
A12: 2022-01-31 | B12: 0.627 | C12: 0.606 | D12: 1.094 | E12: 0.446 | F12: 0.601 | G12: 0.589 | H12: 1.462 | I12: 0.489 | J12: 5.008 | L12: 3.796 | M12: 1.209 | N12: 0.036 | O12: 0.036 | P12: 0.31 | Q12: 0.277 | R12: 7.446 | S12: -2.574 | T12: 0.731 | U12: 0.942 | V12: 180.259 | W12: 0.265 | X12: 0.909 | Y12: -0.896 | Z12: 0.395 | AA12: 0.877 | AB12: 0.877 | AC12: 1265.083 | AD12: -1.865 | AE12: 4.414 | AF12: -1 | AG12: -2.205 | AH12: 0.467 | AJ12: -0.966 | AK12: -4.139 | AL12: 0.041 | AN12: 0.041 | AO12: 0.539 | AP12: 0.569 | AQ12: 0.48 | AR12: 0.122 | AS12: 0.436 | AT12: 3.983 | AU12: 5.209 | AV12: 8.453 | AW12: 1.379 | AX12: 0.324 | AY12: 2.948 | AZ12: 0.094 | BA12: -0.007 | BB12: 0.387 | BC12: 0.19 | BD12: -0.233 | BE12: 0.67
A13: 2021-10-31 | B13: 0.635 | C13: 0.629 | D13: 0.755 | E13: 0.562 | F13: 0.607 | G13: 0.697 | H13: 1.537 | I13: 0.667 | J13: 32.176 | K13: inf | L13: 8.918 | M13: 1.057 | N13: 0.041 | O13: 0.041 | P13: 0.614 | Q13: -0.261 | R13: 3.034 | S13: -1 | T13: 0.704 | U13: 1.134 | V13: 0.894 | W13: 0.724 | X13: 1.547 | Y13: -26.053 | Z13: 0.797 | AA13: 1.921 | AB13: 1.921 | AC13: -1.05 | AD13: 16 | AE13: -0.545 | AF13: -1 | AG13: -0.846 | AJ13: 0.461 | AK13: 12.524 | AL13: 0.8 | AM13: -1 | AN13: 0.8 | AO13: 0.64 | AP13: 0.74 | AQ13: 0.328 | AR13: 0.76 | AS13: 0.375 | AT13: 3.498 | AU13: 4.067 | AV13: 8.066 | AW13: 1.299 | AX13: 0.886 | AY13: -0.044 | AZ13: 0.123 | BA13: 21.556 | BB13: 1.503 | BC13: 0.178 | BD13: 0.638 | BE13: 1.248
A14: 2021-07-31 | B14: 0.697 | C14: 0.71 | D14: 0.738 | E14: 0.617 | F14: 0.646 | G14: 0.792 | H14: -0.154 | I14: 0.581 | J14: 35.184 | L14: 8.61 | M14: 0.919 | N14: 0.045 | O14: 0.045 | P14: 1.272 | Q14: 11.033 | R14: 2.255 | S14: -1 | T14: 0.689 | U14: 1.023 | V14: -1.73 | W14: 1.151 | X14: 2.64 | Y14: 0.708 | Z14: 0.971 | AA14: 0.541 | AB14: 0.541 | AC14: -inf | AD14: 5 | AE14: 0.744 | AG14: inf | AJ14: 0.314 | AK14: -2.832 | AL14: 0.678 | AN14: 0.678 | AO14: 0.786 | AP14: 0.773 | AQ14: 1.137 | AR14: 0.711 | AS14: 0.294 | AT14: 45.035 | AU14: 245.628 | AV14: 6.082 | AW14: 1.937 | AX14: 0.939 | AY14: 0.941 | AZ14: 0.085 | BA14: 20.258 | BB14: 1.697 | BC14: 0.151 | BD14: 0.53 | BE14: 0.536
A15: 2021-04-30 | B15: 0.701 | C15: 0.71 | D15: 0.692 | E15: 0.533 | F15: 0.568 | G15: 0.927 | H15: 0.052 | I15: 0.389 | J15: 38.741 | L15: 47.322 | M15: 3.425 | N15: 0.052 | O15: 0.052 | P15: 0.348 | Q15: 0.524 | R15: -3.23 | S15: 14.092 | T15: 0.731 | U15: 1.3 | V15: 5.553 | W15: 0.963 | X15: 0.728 | Y15: -1.316 | Z15: 0.497 | AA15: 1.611 | AB15: 1.611 | AC15: -188.783 | AD15: -0.985 | AE15: -1.606 | AG15: inf | AJ15: -0.622 | AK15: 98.417 | AL15: 0.677 | AN15: 0.677 | AO15: 0.465 | AP15: 0.599 | AQ15: 0.229 | AR15: 0.632 | AS15: 0.304 | AT15: 47.952 | AU15: 211.055 | AV15: 7.165 | AW15: 2.112 | AX15: 0.896 | AY15: -0.469 | AZ15: 0.399 | BA15: 22.395 | BB15: 1.646 | BC15: 0.133 | BD15: 0.189 | BE15: 0.826
A16: 2021-01-31 | B16: 0.742 | C16: 0.823 | D16: 0.401 | E16: 0.483 | F16: 0.463 | G16: 0.708 | H16: -0.787 | I16: -0.492 | J16: 6.234 | L16: 7.505 | M16: -0.331 | N16: 0.068 | O16: 0.068 | P16: 0.918 | Q16: 2.412 | R16: -1.508 | S16: 1.344 | T16: 0.666 | U16: 0.958 | V16: -1.388 | W16: 0.005 | X16: 0.165 | Y16: -2.793 | Z16: 0.731 | AA16: 0.118 | AB16: 0.118 | AC16: -1.023 | AD16: -1.001 | AE16: -0.97 | AF16: -inf | AG16: -1.032 | AH16: 1.771 | AJ16: 26.848 | AK16: -10.092 | AL16: 6.246 | AM16: -1 | AN16: 1.104 | AO16: 0.45 | AP16: 0.882 | AQ16: 0.039 | AR16: 0.956 | AS16: 0.495 | AT16: 9.822 | AU16: 28.748 | AV16: 1.5 | AW16: 0.887 | AX16: 0.945 | AY16: 7.97 | AZ16: -0.866 | BA16: inf | BB16: 1.809 | BC16: 0.174 | BD16: -0.835 | BE16: -0.462
A17: 2020-10-31 | B17: 0.858 | C17: 0.948 | D17: 0.478 | E17: 0.538 | F17: 0.523 | G17: 0.599 | H17: -0.924 | I17: -0.373 | J17: 0.462 | L17: 0.039 | M17: -0.309 | N17: 0.075 | O17: 0.075 | P17: 9.797 | Q17: -0.281 | R17: -inf | S17: inf | T17: 0.767 | U17: 0.849 | V17: -5.711 | W17: 0.146 | X17: -0.482 | Y17: -1.445 | Z17: 1.291 | AA17: -0.607 | AB17: -0.607 | AC17: -46.031 | AD17: -0.993 | AE17: 2.609 | AF17: -inf | AG17: inf | AJ17: -6.342 | AK17: -1.268 | AL17: 0.425 | AM17: -0.972 | AN17: 0.271 | AO17: 0.186 | AP17: 0.738 | AQ17: 0.205 | AR17: 0.273 | AS17: 0.55 | AT17: 9.666 | AU17: 24.677 | AV17: inf | AW17: 1.015 | AX17: 0.393 | AY17: 0.429 | AZ17: -0.87 | BA17: inf | BB17: 0.734 | BC17: 0.136 | BD17: -0.58 | BE17: -0.594
A18: 2020-07-31 | B18: 0.84 | C18: 0.889 | D18: -0.043 | E18: 0.457 | F18: 0.299 | G18: 0.596 | H18: -2.623 | I18: -0.408 | J18: 0.061 | L18: -0.306 | M18: -0.424 | N18: 0.666 | O18: 0.666 | P18: -2.112 | Q18: -0.836 | R18: inf | S18: -inf | T18: 0.744 | U18: 0.263 | V18: -1.089 | W18: -8.764 | X18: 0.075 | Y18: -0.907 | Z18: -9.855 | AA18: -0.015 | AB18: -0.015 | AC18: -1 | AD18: -0.985 | AE18: -0.314 | AJ18: -0.96 | AK18: -3.981 | AL18: 0.453 | AM18: -1 | AN18: 0.288 | AO18: 0.295 | AP18: 0.583 | AQ18: 0.641 | AR18: 0.309 | AS18: 0.794 | AT18: 0.045 | AU18: -0.53 | AV18: inf | AW18: 0.811 | AX18: 0.38 | AY18: 7.986 | AZ18: -0.836 | BA18: inf | BB18: 0.86 | BC18: 0.088 | BD18: -0.547 | BE18: -0.368
A19: 2020-04-30 | B19: 0.853 | C19: 0.964 | D19: 1.111 | E19: 0.551 | F19: 0.647 | G19: 0.7 | H19: 10.505 | I19: -0.124 | J19: 142 | L19: 0.741 | M19: -0.26 | N19: 0.084 | O19: 0.084 | P19: -6.4 | Q19: 2.842 | R19: 0.681 | S19: -1.227 | T19: 0.655 | U19: 5.3 | V19: -2.55 | W19: 5.247 | X19: 1.613 | Y19: 160.438 | Z19: 68.666 | AA19: -0.339 | AB19: -0.339 | AC19: -0.051 | AD19: 0.639 | AE19: 152.386 | AJ19: -8.815 | AK19: -1.14 | AL19: 9.807 | AM19: -1 | AN19: 4.741 | AO19: 0.651 | AP19: 1.039 | AQ19: 1.026 | AR19: 3.011 | AS19: 1.025 | AT19: -0.02 | AU19: -0.523 | AV19: inf | AW19: 0.854 | AX19: 2.322 | AY19: -0.342 | AZ19: -0.848 | BA19: inf | BB19: -0.187 | BC19: -2.552 | BD19: -0.312 | BE19: -0.325
A20: 2020-01-31 | B20: 0.891 | C20: 1.033 | D20: 0.898 | E20: 0.536 | F20: 0.613 | G20: 0.758 | H20: 8.978 | I20: -0.003 | J20: inf | L20: -0.046 | M20: -0.091 | N20: 0.212 | O20: 0.212 | P20: -387.84 | Q20: 0.256 | R20: -inf | S20: inf | T20: 0.491 | U20: 6.854 | V20: 0.412 | W20: 0.737 | X20: 0.573 | Y20: -97.807 | Z20: 3.182 | AA20: -0.032 | AB20: -0.032 | AC20: 0.188 | AD20: 8.254 | AE20: 52.614 | AG20: inf | AH20: inf | AJ20: -85.031 | AK20: -1.813 | AL20: 1.995 | AM20: 5.269 | AN20: 3.759 | AO20: 0.784 | AP20: -0.069 | AQ20: 45.71 | AR20: 2.536 | AS20: 0.846 | AT20: -0.028 | AU20: -0.497 | AV20: inf | AW20: 1.291 | AX20: 2.243 | AY20: -0.804 | AZ20: 0.296 | BB20: 0.847 | BC20: 8.947 | BD20: -0.092 | BE20: -0.07
A21: 2019-10-31 | B21: 0.885 | C21: 0.99 | D21: 0.588 | E21: 0.473 | F21: 0.499 | G21: 0.386 | H21: 10.812 | I21: -0.085 | J21: inf | L21: -0.189 | M21: -0.161 | N21: 0.192 | O21: 0.192 | P21: -1.539 | Q21: 0.537 | T21: 0.545 | U21: 0.632 | V21: -0.959 | W21: 1.819 | X21: 1.045 | Y21: -1.337 | Z21: -11.617 | AA21: 2.347 | AB21: 2.347 | AC21: 0.031 | AD21: 0.274 | AE21: -0.253 | AJ21: -1.12 | AK21: -10.561 | AL21: 7.91 | AM21: -0.166 | AN21: 3.355 | AO21: 0.891 | AP21: inf | AQ21: 0.023 | AR21: 2.447 | AS21: 1.675 | AT21: -0.011 | AU21: -0.949 | AW21: 1.415 | AX21: 2.224 | AY21: -0.085 | AZ21: inf | BB21: 1.41 | BC21: 6.426 | BD21: -0.148 | BE21: 0.346
A22: 2019-07-31 | B22: 1.286 | C22: 1.743 | D22: 3.465 | E22: 0.783 | F22: 1.202 | G22: 0.796 | H22: 1.374 | I22: 0.529 | J22: -0.146 | L22: 4.248 | M22: 0.544 | N22: -0.24 | O22: -0.24 | P22: 0.741 | Q22: -2.362 | T22: 0.734 | U22: 16.37 | V22: 59.051 | W22: -1.159 | X22: -7.306 | Y22: -47.451 | Z22: -0.028 | AA22: 1.216 | AB22: 1.216 | AC22: inf | AD22: -inf | AE22: 3.434 | AJ22: 1515 | AK22: 2.554 | AL22: -12.142 | AM22: -0.285 | AN22: 11.571 | AO22: inf | AP22: inf | AQ22: inf | AR22: 14.287 | AS22: inf | AT22: inf | AU22: inf | AW22: -3.526 | AX22: inf | AY22: inf | AZ22: inf | BB22: inf | BC22: -40.446 | BD22: 0.508 | BE22: 0.69
A23: 2019-04-30 | B23: 1.482 | C23: 2.418 | D23: 0.938 | E23: 0.659 | F23: 0.701 | G23: 0.499 | H23: inf | I23: -0.299 | J23: inf | K23: -1 | L23: 0.232 | M23: -0.377 | N23: 3.568 | O23: 3.568 | P23: 0.584 | Q23: -1.275 | R23: inf | S23: -inf | T23: -8.48 | U23: 1.804 | V23: inf | W23: -1.486 | X23: -5.352 | Y23: -2.561 | Z23: -1.21 | AA23: 4.087 | AB23: 4.087 | AC23: inf | AD23: -inf | AE23: 77.075 | AJ23: -1.25 | AK23: -1.424 | AL23: 0.472 | AM23: 30.649 | AN23: 1.662 | AO23: 0.465 | AP23: 26192999 | AQ23: -0.198 | AR23: 1.026 | AS23: 1.799 | AT23: -0.073 | AU23: -0.924 | AW23: 1.28 | AX23: 1.101 | AY23: -0.191 | AZ23: inf | BA23: -1 | BB23: 2.991 | BC23: 25.285 | BD23: -0.446 | BE23: -0.064
A24: 2019-01-31
A25: 2018-10-31
A26: 2018-04-30
A27: 2018-01-31

Sheet Annual Aggregated
A1: date | B1: revenue | C1: grossProfit | D1: generalAndAdministrativeExpenses | E1: sellingAndMarketingExpenses | F1: sellingGeneralAndAdministrativeExpenses | G1: researchAndDevelopmentExpenses | H1: otherExpenses | I1: operatingIncome | J1: interestExpense | K1: interestIncome | L1: incomeTaxExpense | M1: netIncome | N1: weightedAverageShsOut | O1: weightedAverageShsOutDil | P1: freeCashFlow | Q1: accountsReceivables | R1: accountsPayables | S1: inventory_x | T1: depreciationAndAmortization | U1: stockBasedCompensation | V1: deferredIncomeTax | W1: changeInWorkingCapital | X1: otherWorkingCapital | Y1: netChangeInCash | Z1: netCashProvidedByOperatingActivities | AA1: capitalExpenditure | AB1: investmentsInPropertyPlantAndEquipment | AC1: acquisitionsNet | AD1: purchasesOfInvestments | AE1: netCashUsedForInvestingActivites | AF1: debtRepayment | AG1: commonStockIssued | AH1: commonStockRepurchased | AI1: dividendsPaid | AJ1: netCashUsedProvidedByFinancingActivities | AK1: effectOfForexChangesOnCash | AL1: cashAndCashEquivalents | AM1: shortTermInvestments | AN1: cashAndShortTermInvestments | AO1: netReceivables | AP1: inventory_y | AQ1: otherCurrentAssets | AR1: totalCurrentAssets | AS1: propertyPlantEquipmentNet | AT1: goodwill | AU1: intangibleAssets | AV1: longTermInvestments | AW1: totalNonCurrentAssets | AX1: totalAssets | AY1: accountPayables | AZ1: shortTermDebt | BA1: longTermDebt | BB1: totalLiabilities | BC1: totalEquity | BD1: EBITDA | BE1: FCFsimple
A2: 2024 | B2: 2730243000 | C2: 2057635000 | D2: 312905000 | E2: 995942000 | F2: 1305287000 | G2: 700155000 | H2: 10241000 | I2: 52193000 | J2: 19482000 | K2: 139061000 | L2: 32190000 | M2: 143532000 | N2: 727336000 | O2: 749365000 | P2: 868917000 | Q2: -91497000 | R2: -21331000 | S2: -62886000 | T2: 143637000 | U2: 560274000 | V2: -2961000 | W2: -12245000 | X2: 100583000 | Y2: 1069664000 | Z2: 1056885000 | AA2: -187968000 | AB2: -187968000 | AC2: -91162000 | AD2: -7702000 | AE2: -80093000 | AF2: 0 | AG2: 92023000 | AH2: 76375000 | AI2: 0 | AJ2: 87938000 | AK2: 4329000 | AL2: 11116042000 | AM2: 99591000 | AN2: 11215633000 | AO2: 2217006000 | AP2: 1 | AQ2: 605671000 | AR2: 14038310000 | AS2: 2038733000 | AT2: 2082010000 | AU2: 352228000 | AV2: 172909000 | AW2: 6652669000 | AX2: 20690979000 | AY2: 70546000 | AZ2: 47201000 | BA2: 2228598000 | BB2: 12894518000 | BC2: 7796460999 | BD2: 195830000 | BE2: 7862000
A3: 2023 | B3: 2847587000 | C3: 2124832000 | D3: 426448000 | E3: 1045206000 | F3: 1471654000 | G3: 746344000 | H3: -4760000 | I3: -62415000 | J3: 19730000 | K3: 134261000 | L3: 23937000 | M3: -13304000 | N3: 948649000 | O3: 961568000 | P3: 864019000 | Q3: -75011000 | R3: -38109000 | S3: 62886000 | T3: 130735000 | U3: 607594000 | V3: -3335000 | W3: 131949000 | X3: 182183000 | Y3: 507088000 | Z3: 1092484000 | AA3: -228465000 | AB3: -228465000 | AC3: -325482000 | AD3: -463086000 | AE3: -680185000 | AF3: 0 | AG3: 78843000 | AH3: 59419000 | AI3: 0 | AJ3: 86931000 | AK3: 2168000 | AL3: 11421133000 | AM3: 547522000 | AN3: 11968655000 | AO3: 2188608000 | AP3: 780083000 | AQ3: 541210000 | AR3: 15478556000 | AS3: 2346195000 | AT3: 1929775000 | AU3: 358666000 | AV3: 224229000 | AW3: 6037356000 | AX3: 21515912000 | AY3: 156313000 | AZ3: 59824000 | BA3: 3103654000 | BB3: 14463172000 | BC3: 7052740000 | BD3: 68320000 | BE3: -160145000
A4: 2022 | B4: 2034879000 | C4: 1496632000 | D4: 306677000 | E4: 820564000 | F4: 1127241000 | G4: 521537000 | H4: 9021000 | I4: -152146000 | J4: 24723000 | K4: 25479000 | L4: 30670000 | M4: -176305000 | N4: 921165285 | O4: 927180000 | P4: 593996000 | Q4: -201950000 | R4: 65288000 | S4: -48172000 | T4: 86451000 | U4: 466794000 | V4: -12396000 | W4: 298794000 | X4: 501270000 | Y4: 560550000 | Z4: 827432000 | AA4: -233436000 | AB4: -233436000 | AC4: -75273000 | AD4: -18506000 | AE4: -331178000 | AF4: -1591000 | AG4: 66769000 | AH4: 50277000 | AI4: 0 | AJ4: 67929000 | AK4: -10185000 | AL4: 8934778000 | AM4: 0 | AN4: 8934778000 | AO4: 1641387000 | AP4: 424763001 | AQ4: 334550000 | AR4: 11483603000 | AS4: 1504448000 | AT4: 1679024000 | AU4: 370621000 | AV4: 134277000 | AW4: 4594292000 | AX4: 16077895000 | AY4: 201764000 | AZ4: 40526000 | BA4: 3047200000 | BB4: 11342276000 | BC4: 4735619000 | BD4: -65695000 | BE4: -299131000
A5: 2021 | B5: 1285513000 | C5: 948180000 | D5: 184261000 | E5: 566401000 | F5: 750662000 | G5: 332335000 | H5: 6759000 | I5: -134817000 | J5: 19431000 | K5: 1019000 | L5: 61605000 | M5: -211824000 | N5: 900508000 | O5: 900508000 | P5: 410975000 | Q5: -106967000 | R5: -2264000 | S5: 75313000 | T5: 60155000 | U5: 265029000 | V5: -4178000 | W5: 307949000 | X5: 345396000 | Y5: 847582000 | Z5: 529529000 | AA5: -118554000 | AB5: -118554000 | AC5: -349544000 | AD5: -15231000 | AE5: -488157000 | AF5: -1563000 | AG5: 18725999 | AH5: 34263000 | AI5: 0 | AJ5: 806882000 | AK5: -672000 | AL5: 7298164000 | AM5: 0 | AN5: 7298164000 | AO5: 1000244000 | AP5: 370344000 | AQ5: 273636000 | AR5: 8942388000 | AS5: 958294000 | AT5: 1206346000 | AU5: 272978000 | AV5: 47495000 | AW5: 3106978000 | AX5: 12049366000 | AY5: 42342000 | AZ5: 37390000 | BA5: 3075063000 | BB5: 8453124000 | BC5: 3596242000 | BD5: -74662000 | BE5: -193216000
A6: 2020 | B6: 761618000 | C6: 555388000 | D6: 111286000 | E6: 364670000 | F6: 475956000 | G6: 187291000 | H6: 8740000 | I6: -107859000 | J6: 655000 | K6: 0 | L6: 2261000 | M6: -102035000 | N6: 856790000 | O6: 856790000 | P6: 246189000 | Q6: -25591000 | R6: -2832000 | S6: 41382000 | T6: 35412000 | U6: 126324000 | V6: -1008000 | W6: 185356000 | X6: 176066000 | Y6: 316321000 | Z6: 308210000 | AA6: -62021000 | AB6: -62021000 | AC6: -81506000 | AD6: -679408000 | AE6: -59387000 | AF6: -1563000 | AG6: 686614000 | AH6: 12365000 | AI6: 0 | AJ6: 66916000 | AK6: 582000 | AL6: 3394449000 | AM6: 649766000 | AN6: 4041715000 | AO6: 631185000 | AP6: 212640000 | AQ6: 191335000 | AR6: 5076875000 | AS6: 705416000 | AT6: 106637000 | AU6: 17649000 | AV6: 6500000 | AW6: 1213888000 | AX6: 6290763000 | AY6: 25485000 | AZ6: 91127000 | BA6: 103047000 | BB6: 3188203000 | BC6: 3102560000 | BD6: -72447000 | BE6: -134468000
A7: 2019 | B7: 409759000 | C7: 284554000 | D7: 77086000 | E7: 240130000 | F7: 317216000 | G7: 113502000 | H7: 3843000 | I7: -146164000 | J7: 297000 | K7: 0 | L7: 2013000 | M7: -144631000 | N7: 702077971 | O7: 702077971 | P7: -38351000 | Q7: -69108000 | R7: 2818000 | S7: -13057000 | T7: 21172000 | U7: 58679000 | V7: 5270000 | W7: 75495000 | X7: 154842000 | Y7: 660143000 | Z7: 49644000 | AA7: -87995000 | AB7: -87995000 | AC7: 6960000 | AD7: -251779000 | AE7: -68187000 | AF7: 0 | AG7: 0 | AH7: 0 | AI7: 0 | AJ7: 678509000 | AK7: 177000 | AL7: 1657814000 | AM7: 369399000 | AN7: 2027213000 | AO7: 440781000 | AP7: 142286000 | AQ7: 91011000 | AR7: 2701291000 | AS7: 397577000 | AT7: 31330000 | AU7: 3302000 | AV7: 0 | AW7: 616929000 | AX7: 3318220000 | AY7: 23140000 | AZ7: 214683000 | BA7: 0 | BB7: 2283602000 | BC7: 1034618000 | BD7: -124992000 | BE7: -212987000
A8: 2018 | B8: 152385000 | C8: 91547000 | D8: 26512000 | E8: 117496000 | F8: 144008000 | G8: 59511000 | H8: 113000 | I8: -111972000 | J8: 192000 | K8: 190000 | L8: 1139000 | M8: -117657000 | N8: 385459020 | O8: 385459000 | P8: -39995000 | Q8: -18889000 | R8: 0 | S8: 0 | T8: 6315000 | U8: 16517000 | V8: 1007000 | W8: 6537000 | X8: 25426000 | Y8: -48783000 | Z8: -16757000 | AA8: -23238000 | AB8: -23238000 | AC8: 1841000 | AD8: -55049000 | AE8: -44189000 | AF8: 0 | AG8: 0 | AH8: 0 | AI8: 0 | AJ8: 12075000 | AK8: 88000 | AL8: 80869000 | AM8: 242104000 | AN8: 322973000 | AO8: 136679000 | AP8: 1 | AQ8: 65299999 | AR8: 524952000 | AS8: 79259000 | AT8: 16303000 | AU8: 24219000 | AV8: 0 | AW8: 82305000 | AX8: 607257000 | AY8: 17994000 | AZ8: 0 | BA8: 15971000 | BB8: 459845000 | BC8: 59643000 | BD8: -105657000 | BE8: -128895000

Sheet Annual % Change
A1: date | B1: revenue | C1: grossProfit | D1: generalAndAdministrativeExpenses | E1: sellingAndMarketingExpenses | F1: sellingGeneralAndAdministrativeExpenses | G1: researchAndDevelopmentExpenses | H1: otherExpenses | I1: operatingIncome | J1: interestExpense | K1: interestIncome | L1: incomeTaxExpense | M1: netIncome | N1: weightedAverageShsOut | O1: weightedAverageShsOutDil | P1: freeCashFlow | Q1: accountsReceivables | R1: accountsPayables | S1: inventory_x | T1: depreciationAndAmortization | U1: stockBasedCompensation | V1: deferredIncomeTax | W1: changeInWorkingCapital | X1: otherWorkingCapital | Y1: netChangeInCash | Z1: netCashProvidedByOperatingActivities | AA1: capitalExpenditure | AB1: investmentsInPropertyPlantAndEquipment | AC1: acquisitionsNet | AD1: purchasesOfInvestments | AE1: netCashUsedForInvestingActivites | AF1: debtRepayment | AG1: commonStockIssued | AH1: commonStockRepurchased | AI1: dividendsPaid | AJ1: netCashUsedProvidedByFinancingActivities | AK1: effectOfForexChangesOnCash | AL1: cashAndCashEquivalents | AM1: shortTermInvestments | AN1: cashAndShortTermInvestments | AO1: netReceivables | AP1: inventory_y | AQ1: otherCurrentAssets | AR1: totalCurrentAssets | AS1: propertyPlantEquipmentNet | AT1: goodwill | AU1: intangibleAssets | AV1: longTermInvestments | AW1: totalNonCurrentAssets | AX1: totalAssets | AY1: accountPayables | AZ1: shortTermDebt | BA1: longTermDebt | BB1: totalLiabilities | BC1: totalEquity | BD1: EBITDA | BE1: FCFsimple
A2: 2024 | B2: -0.041 | C2: -0.032 | D2: -0.266 | E2: -0.047 | F2: -0.113 | G2: -0.062 | H2: -3.151 | I2: -1.836 | J2: -0.013 | K2: 0.036 | L2: 0.345 | M2: -11.789 | N2: -0.233 | O2: -0.221 | P2: 0.006 | Q2: 0.22 | R2: -0.44 | S2: -2 | T2: 0.099 | U2: -0.078 | V2: -0.112 | W2: -1.093 | X2: -0.448 | Y2: 1.109 | Z2: -0.033 | AA2: -0.177 | AB2: -0.177 | AC2: -0.72 | AD2: -0.983 | AE2: -0.882 | AG2: 0.167 | AH2: 0.285 | AJ2: 0.012 | AK2: 0.997 | AL2: -0.027 | AM2: -0.818 | AN2: -0.063 | AO2: 0.013 | AP2: -1 | AQ2: 0.119 | AR2: -0.093 | AS2: -0.131 | AT2: 0.079 | AU2: -0.018 | AV2: -0.229 | AW2: 0.102 | AX2: -0.038 | AY2: -0.549 | AZ2: -0.211 | BA2: -0.282 | BB2: -0.108 | BC2: 0.105 | BD2: 1.866 | BE2: -1.049
A3: 2023 | B3: 0.399 | C3: 0.42 | D3: 0.391 | E3: 0.274 | F3: 0.306 | G3: 0.431 | H3: -1.528 | I3: -0.59 | J3: -0.202 | K3: 4.269 | L3: -0.22 | M3: -0.925 | N3: 0.03 | O3: 0.037 | P3: 0.455 | Q3: -0.629 | R3: -1.584 | S3: -2.305 | T3: 0.512 | U3: 0.302 | V3: -0.731 | W3: -0.558 | X3: -0.637 | Y3: -0.095 | Z3: 0.32 | AA3: -0.021 | AB3: -0.021 | AC3: 3.324 | AD3: 24.024 | AE3: 1.054 | AF3: -1 | AG3: 0.181 | AH3: 0.182 | AJ3: 0.28 | AK3: -1.213 | AL3: 0.278 | AM3: inf | AN3: 0.34 | AO3: 0.333 | AP3: 0.837 | AQ3: 0.618 | AR3: 0.348 | AS3: 0.56 | AT3: 0.149 | AU3: -0.032 | AV3: 0.67 | AW3: 0.314 | AX3: 0.338 | AY3: -0.225 | AZ3: 0.476 | BA3: 0.019 | BB3: 0.275 | BC3: 0.489 | BD3: -2.04 | BE3: -0.465
A4: 2022 | B4: 0.583 | C4: 0.578 | D4: 0.664 | E4: 0.449 | F4: 0.502 | G4: 0.569 | H4: 0.335 | I4: 0.129 | J4: 0.272 | K4: 24.004 | L4: -0.502 | M4: -0.168 | N4: 0.023 | O4: 0.03 | P4: 0.445 | Q4: 0.888 | R4: -29.837 | S4: -1.64 | T4: 0.437 | U4: 0.761 | V4: 1.967 | W4: -0.03 | X4: 0.451 | Y4: -0.339 | Z4: 0.563 | AA4: 0.969 | AB4: 0.969 | AC4: -0.785 | AD4: 0.215 | AE4: -0.322 | AF4: 0.018 | AG4: 2.566 | AH4: 0.467 | AJ4: -0.916 | AK4: 14.156 | AL4: 0.224 | AN4: 0.224 | AO4: 0.641 | AP4: 0.147 | AQ4: 0.223 | AR4: 0.284 | AS4: 0.57 | AT4: 0.392 | AU4: 0.358 | AV4: 1.827 | AW4: 0.479 | AX4: 0.334 | AY4: 3.765 | AZ4: 0.084 | BA4: -0.009 | BB4: 0.342 | BC4: 0.317 | BD4: -0.12 | BE4: 0.548
A5: 2021 | B5: 0.688 | C5: 0.707 | D5: 0.656 | E5: 0.553 | F5: 0.577 | G5: 0.774 | H5: -0.227 | I5: 0.25 | J5: 28.666 | K5: inf | L5: 26.247 | M5: 1.076 | N5: 0.051 | O5: 0.051 | P5: 0.669 | Q5: 3.18 | R5: -0.201 | S5: 0.82 | T5: 0.699 | U5: 1.098 | V5: 3.145 | W5: 0.661 | X5: 0.962 | Y5: 1.679 | Z5: 0.718 | AA5: 0.912 | AB5: 0.912 | AC5: 3.289 | AD5: -0.978 | AE5: 7.22 | AF5: 0 | AG5: -0.973 | AH5: 1.771 | AJ5: 11.058 | AK5: -2.155 | AL5: 1.15 | AM5: -1 | AN5: 0.806 | AO5: 0.585 | AP5: 0.742 | AQ5: 0.43 | AR5: 0.761 | AS5: 0.358 | AT5: 10.313 | AU5: 14.467 | AV5: 6.307 | AW5: 1.56 | AX5: 0.915 | AY5: 0.661 | AZ5: -0.59 | BA5: 28.841 | BB5: 1.651 | BC5: 0.159 | BD5: 0.031 | BE5: 0.437
A6: 2020 | B6: 0.859 | C6: 0.952 | D6: 0.444 | E6: 0.519 | F6: 0.5 | G6: 0.65 | H6: 1.274 | I6: -0.262 | J6: 1.205 | L6: 0.123 | M6: -0.295 | N6: 0.22 | O6: 0.22 | P6: -7.419 | Q6: -0.63 | R6: -2.005 | S6: -4.169 | T6: 0.673 | U6: 1.153 | V6: -1.191 | W6: 1.455 | X6: 0.137 | Y6: -0.521 | Z6: 5.208 | AA6: -0.295 | AB6: -0.295 | AC6: -12.711 | AD6: 1.698 | AE6: -0.129 | AF6: -inf | AG6: inf | AH6: inf | AJ6: -0.901 | AK6: 2.288 | AL6: 1.048 | AM6: 0.759 | AN6: 0.994 | AO6: 0.432 | AP6: 0.494 | AQ6: 1.102 | AR6: 0.879 | AS6: 0.774 | AT6: 2.404 | AU6: 4.345 | AV6: inf | AW6: 0.968 | AX6: 0.896 | AY6: 0.101 | AZ6: -0.576 | BA6: inf | BB6: 0.396 | BC6: 1.999 | BD6: -0.42 | BE6: -0.369
A7: 2019 | B7: 1.689 | C7: 2.108 | D7: 1.908 | E7: 1.044 | F7: 1.203 | G7: 0.907 | H7: 33.009 | I7: 0.305 | J7: 0.547 | K7: -1 | L7: 0.767 | M7: 0.229 | N7: 0.821 | O7: 0.821 | P7: -0.041 | Q7: 2.659 | R7: inf | S7: -inf | T7: 2.353 | U7: 2.553 | V7: 4.233 | W7: 10.549 | X7: 5.09 | Y7: -14.532 | Z7: -3.963 | AA7: 2.787 | AB7: 2.787 | AC7: 2.781 | AD7: 3.574 | AE7: 0.543 | AJ7: 55.191 | AK7: 1.011 | AL7: 19.5 | AM7: 0.526 | AN7: 5.277 | AO7: 2.225 | AP7: 142285999 | AQ7: 0.394 | AR7: 4.146 | AS7: 4.016 | AT7: 0.922 | AU7: -0.864 | AW7: 6.496 | AX7: 4.464 | AY7: 0.286 | AZ7: inf | BA7: -1 | BB7: 3.966 | BC7: 16.347 | BD7: 0.183 | BE7: 0.652
A8: 2018

Sheet Trailing Twelve Months (TTM)
A1: date | B1: revenue | C1: grossProfit | D1: generalAndAdministrativeExpenses | E1: sellingAndMarketingExpenses | F1: sellingGeneralAndAdministrativeExpenses | G1: researchAndDevelopmentExpenses | H1: otherExpenses | I1: operatingIncome | J1: interestExpense | K1: interestIncome | L1: incomeTaxExpense | M1: netIncome | N1: weightedAverageShsOut | O1: weightedAverageShsOutDil | P1: freeCashFlow | Q1: accountsReceivables | R1: accountsPayables | S1: inventory_x | T1: depreciationAndAmortization | U1: stockBasedCompensation | V1: deferredIncomeTax | W1: changeInWorkingCapital | X1: otherWorkingCapital | Y1: netChangeInCash | Z1: netCashProvidedByOperatingActivities | AA1: capitalExpenditure | AB1: investmentsInPropertyPlantAndEquipment | AC1: acquisitionsNet | AD1: purchasesOfInvestments | AE1: netCashUsedForInvestingActivites | AF1: debtRepayment | AG1: commonStockIssued | AH1: commonStockRepurchased | AI1: dividendsPaid | AJ1: netCashUsedProvidedByFinancingActivities | AK1: effectOfForexChangesOnCash | AL1: cashAndCashEquivalents | AM1: shortTermInvestments | AN1: cashAndShortTermInvestments | AO1: netReceivables | AP1: inventory_y | AQ1: otherCurrentAssets | AR1: totalCurrentAssets | AS1: propertyPlantEquipmentNet | AT1: goodwill | AU1: intangibleAssets | AV1: longTermInvestments | AW1: totalNonCurrentAssets | AX1: totalAssets | AY1: accountPayables | AZ1: shortTermDebt | BA1: longTermDebt | BB1: totalLiabilities | BC1: totalEquity | BD1: EBITDA | BE1: FCFsimple
A2: 2024-07-31 | B2: 3516257000 | C2: 2648645000 | D2: 418494000 | E2: 1282128000 | F2: 1697062000 | G2: 896227000 | H2: 9767000 | I2: 55356000 | J2: 20029000 | K2: 179147000 | L2: 41793000 | M2: 170197000 | N2: 966633000 | O2: 993164000 | P2: 1108515000 | Q2: -112357000 | R2: -15988000 | S2: -7559000 | T2: 182062000 | U2: 719888000 | V2: -4964000 | W2: -23979000 | X2: 49039000 | Y2: 873806000 | Z2: 1330403000 | AA2: -221888000 | AB2: -221888000 | AC2: -329911000 | AD2: -203869000 | AE2: -548929000 | AF2: 0 | AG2: 94076000 | AH2: 76375000 | AI2: 0 | AJ2: 89991000 | AK2: -165000 | AL2: 14084914000 | AM2: 297113000 | AN2: 14382027000 | AO2: 2778878000 | AP2: 209216001 | AQ2: 747322000 | AR2: 18117443000 | AS2: 2670711000 | AT2: 2719688000 | AU2: 461651000 | AV2: 232450000 | AW2: 8404592000 | AX2: 26522035000 | AY2: 127514000 | AZ2: 61631000 | BA2: 3009091000 | BB2: 16664727000 | BC2: 9857307999 | BD2: 237418000 | BE2: 15530000
A3: 2024-04-30 | B3: 3284011000 | C3: 2471831000 | D3: 465306000 | E3: 1158131000 | F3: 1621325000 | G3: 824681000 | H3: 9064000 | I3: 25825000 | J3: 19924000 | K3: 164259000 | L3: 35490000 | M3: 131656000 | N3: 960453000 | O3: 984043000 | P3: 1024435000 | Q3: -232539000 | R3: -26000 | S3: 0 | T3: 163355000 | U3: 683788000 | V3: -3387000 | W3: 3117000 | X3: 172796000 | Y3: 877146000 | Z3: 1248543000 | AA3: -224108000 | AB3: -224108000 | AC3: -432656000 | AD3: -205075000 | AE3: -457279000 | AF3: 0 | AG3: 83242000 | AH3: 76375000 | AI3: 0 | AJ3: 82232000 | AK3: 231000 | AL3: 13213593000 | AM3: 297113000 | AN3: 13510706000 | AO3: 2657296000 | AP3: 406327001 | AQ3: 663098000 | AR3: 17237427000 | AS3: 2584106000 | AT3: 2428389000 | AU3: 425104000 | AV3: 233745000 | AW3: 7602592000 | AX3: 24840019000 | AY3: 143520000 | AZ3: 60733000 | BA3: 3040291000 | BB3: 16003201000 | BC3: 8836817999 | BD3: 189180000 | BE3: -34928000
A4: 2024-01-31 | B4: 3055555000 | C4: 2299148000 | D4: 444206000 | E4: 1089124000 | F4: 1531218000 | G4: 768497000 | H4: 1638000 | I4: 30184000 | J4: 19800000 | K4: 148930000 | L4: 32232000 | M4: 89327000 | N4: 954478000 | O4: 974477000 | P4: 929095000 | Q4: -217699000 | R4: -18898000 | S4: 0 | T4: 145254000 | U4: 631519000 | V4: -3387000 | W4: 51526000 | X4: 225237000 | Y4: 924419000 | Z4: 1166207000 | AA4: -237112000 | AB4: -237112000 | AC4: -325878000 | AD4: -214220000 | AE4: -340650000 | AF4: 0 | AG4: 85070000 | AH4: 76375000 | AI4: 0 | AJ4: 93158000 | AK4: 1958000 | AL4: 12340833000 | AM4: 397113000 | AN4: 12737946000 | AO4: 2415532000 | AP4: 593228001 | AQ4: 602520000 | AR4: 16349226000 | AS4: 2482307000 | AT4: 2137171000 | AU4: 386295000 | AV4: 233203000 | AW4: 6786666000 | AX4: 23135892000 | AY4: 139121000 | AZ4: 60928000 | BA4: 3075576000 | BB4: 15233497000 | BC4: 7902395000 | BD4: 175438000 | BE4: -61674000
A5: 2023-10-31 | B5: 2847587000 | C5: 2124832000 | D5: 426448000 | E5: 1045206000 | F5: 1471654000 | G5: 746344000 | H5: -4760000 | I5: -62415000 | J5: 19730000 | K5: 134261000 | L5: 23937000 | M5: -13304000 | N5: 948649000 | O5: 961568000 | P5: 864019000 | Q5: -75011000 | R5: -38109000 | S5: 62886000 | T5: 130735000 | U5: 607594000 | V5: -3335000 | W5: 131949000 | X5: 182183000 | Y5: 507088000 | Z5: 1092484000 | AA5: -228465000 | AB5: -228465000 | AC5: -325482000 | AD5: -463086000 | AE5: -680185000 | AF5: 0 | AG5: 78843000 | AH5: 59419000 | AI5: 0 | AJ5: 86931000 | AK5: 2168000 | AL5: 11421133000 | AM5: 547522000 | AN5: 11968655000 | AO5: 2188608000 | AP5: 780083000 | AQ5: 541210000 | AR5: 15478556000 | AS5: 2346195000 | AT5: 1929775000 | AU5: 358666000 | AV5: 224229000 | AW5: 6037356000 | AX5: 21515912000 | AY5: 156313000 | AZ5: 59824000 | BA5: 3103654000 | BB5: 14463172000 | BC5: 7052740000 | BD5: 68320000 | BE5: -160145000
A6: 2023-07-31 | B6: 2642455000 | C6: 1956476000 | D6: 405007000 | E6: 998692000 | F6: 1403699000 | G6: 705528000 | H6: -3536000 | I6: -122000000 | J6: 25517000 | K6: 110420000 | L6: 23204000 | M6: -94600000 | N6: 943137000 | O6: 951554000 | P6: 798498000 | Q6: -120663000 | R6: -19239000 | S6: 7559000 | T6: 115932000 | U6: 588093000 | V6: -650000 | W6: 230376000 | X6: 362719000 | Y6: 850610000 | Z6: 1061817000 | AA6: -263319000 | AB6: -263319000 | AC6: -105197000 | AD6: -277100000 | AE6: -308768000 | AF6: -1591000 | AG6: 78267000 | AH6: 59419000 | AI6: 0 | AJ6: 84764000 | AK6: 3918000 | AL6: 10918812000 | AM6: 350000000 | AN6: 11268812000 | AO6: 2112049000 | AP6: 733127000 | AQ6: 489048000 | AR6: 14603036000 | AS6: 2169868000 | AT6: 1722382000 | AU6: 338743000 | AV6: 211083000 | AW6: 5551263000 | AX6: 20154299000 | AY6: 188634000 | AZ6: 55817000 | BA6: 3081778000 | BB6: 13824774000 | BC6: 6329525000 | BD6: -6068000 | BE6: -269387000
A7: 2023-04-30 | B7: 2445982000 | C7: 1802353000 | D7: 332024000 | E7: 991984000 | F7: 1324008000 | G7: 664030000 | H7: 1578000 | I7: -154934000 | J7: 25408000 | K7: 81509000 | L7: 23371000 | M7: -152357000 | N7: 937780000 | O7: 941964000 | P7: 745464000 | Q7: -91962000 | R7: 2372000 | S7: 0 | T7: 103964000 | U7: 554866000 | V7: -701000 | W7: 318081000 | X7: 425313000 | Y7: 678829000 | Z7: 1026942000 | AA7: -281478000 | AB7: -281478000 | AC7: -4946000 | AD7: -279850000 | AE7: -429677000 | AF7: -1591000 | AG7: 67619000 | AH7: 59419000 | AI7: 0 | AJ7: 73786000 | AK7: 787000 | AL7: 10070455000 | AM7: 350000000 | AN7: 10420455000 | AO7: 1991385000 | AP7: 536016001 | AQ7: 432649000 | AR7: 13528630000 | AS7: 1973577000 | AT7: 1707751000 | AU7: 349444000 | AV7: 187127000 | AW7: 5259447000 | AX7: 18788077000 | AY7: 205378000 | AZ7: 50000000 | BA7: 3068941000 | BB7: 13085305000 | BC7: 5702772000 | BD7: -50970000 | BE7: -332448000
A8: 2023-01-31 | B8: 2241236000 | C8: 1640005000 | D8: 317344000 | E8: 904409000 | F8: 1221753000 | G8: 608364000 | H8: 4560000 | I8: -190112000 | J8: 24773000 | K8: 52495000 | L8: 22402000 | M8: -183257000 | N8: 926530285 | O8: 932545000 | P8: 674570000 | Q8: -258109000 | R8: -15463000 | S8: 0 | T8: 93810000 | U8: 526504000 | V8: 1306000 | W8: 320441000 | X8: 611655000 | Y8: 460291000 | Z8: 941007000 | AA8: -266437000 | AB8: -266437000 | AC8: -14386000 | AD8: -271872000 | AE8: -556658000 | AF8: -1591000 | AG8: 68074000 | AH8: 59419000 | AI8: 0 | AJ8: 68984000 | AK8: -1495000 | AL8: 9393514000 | AM8: 250000000 | AN8: 9643514000 | AO8: 1899423000 | AP8: 484796001 | AQ8: 377060000 | AR8: 12552918000 | AS8: 1744407000 | AT8: 1693224000 | AU8: 360174000 | AV8: 157915000 | AW8: 4933136000 | AX8: 17486054000 | AY8: 199502000 | AZ8: 43752000 | BA8: 3052876000 | BB8: 12300644000 | BC8: 5185410000 | BD8: -96302000 | BE8: -362739000
A9: 2022-10-31 | B9: 2034879000 | C9: 1496632000 | D9: 306677000 | E9: 820564000 | F9: 1127241000 | G9: 521537000 | H9: 9021000 | I9: -152146000 | J9: 24723000 | K9: 25479000 | L9: 30670000 | M9: -176305000 | N9: 921165285 | O9: 927180000 | P9: 593996000 | Q9: -201950000 | R9: 65288000 | S9: -48172000 | T9: 86451000 | U9: 466794000 | V9: -12396000 | W9: 298794000 | X9: 501270000 | Y9: 560550000 | Z9: 827432000 | AA9: -233436000 | AB9: -233436000 | AC9: -75273000 | AD9: -18506000 | AE9: -331178000 | AF9: -1591000 | AG9: 66769000 | AH9: 50277000 | AI9: 0 | AJ9: 67929000 | AK9: -10185000 | AL9: 8934778000 | AM9: 0 | AN9: 8934778000 | AO9: 1641387000 | AP9: 424763001 | AQ9: 334550000 | AR9: 11483603000 | AS9: 1504448000 | AT9: 1679024000 | AU9: 370621000 | AV9: 134277000 | AW9: 4594292000 | AX9: 16077895000 | AY9: 201764000 | AZ9: 40526000 | BA9: 3047200000 | BB9: 11342276000 | BC9: 4735619000 | BD9: -65695000 | BE9: -299131000
A10: 2022-07-31 | B10: 1834048000 | C10: 1352365000 | D10: 278590000 | E10: 745852000 | F10: 1024442000 | G10: 463911000 | H10: 8961000 | I10: -135988000 | J10: 24792000 | K10: 10253000 | L10: 26273000 | M10: -172129000 | N10: 915673285 | O10: 921688000 | P10: 542742000 | Q10: -151825000 | R10: 28659000 | S10: -48172000 | T10: 80688000 | U10: 413347000 | V10: -13417000 | W10: 285247000 | X10: 461811000 | Y10: 533343000 | Z10: 743639000 | AA10: -200897000 | AB10: -200897000 | AC10: -52559000 | AD10: -16825000 | AE10: -278494000 | AF10: 0 | AG10: 68596000 | AH10: 50277000 | AI10: 0 | AJ10: 75597000 | AK10: -8861000 | AL10: 8375735000 | AM10: 0 | AN10: 8375735000 | AO10: 1439346000 | AP10: 371139001 | AQ10: 305731000 | AR10: 10640076000 | AS10: 1324914000 | AT10: 1622628000 | AU10: 363991000 | AV10: 110547000 | AW10: 4267993000 | AX10: 14908069000 | AY10: 119642000 | AZ10: 39809000 | BA10: 3055623000 | BB10: 10550512000 | BC10: 4357557000 | BD10: -55300000 | BE10: -256197000
A11: 2022-04-30 | B11: 1636585000 | C11: 1205037000 | D11: 248672000 | E11: 674947000 | F11: 923619000 | G11: 416502000 | H11: 6200000 | I11: -135084000 | J11: 24753000 | K11: 2526000 | L11: 25733000 | M11: -180162000 | N11: 909481285 | O11: 915496000 | P11: 480624000 | Q11: -157878000 | R11: 7379000 | S11: -48172000 | T11: 74867000 | U11: 358084000 | V11: -12964000 | W11: 265542000 | X11: 467742000 | Y11: 467739000 | Z11: 642208000 | AA11: -161584000 | AB11: -161584000 | AC11: -55399000 | AD11: -17825000 | AE11: -240520000 | AF11: 0 | AG11: 65527999 | AH11: 50277000 | AI11: 0 | AJ11: 73028000 | AK11: -8439000 | AL11: 7843928000 | AM11: 0 | AN11: 7843928000 | AO11: 1287087000 | AP11: 466609000 | AQ11: 318497000 | AR11: 9916121000 | AS11: 1164125000 | AT11: 1580872000 | AU11: 359731000 | AV11: 89127000 | AW11: 3973757000 | AX11: 13889878000 | AY11: 85467000 | AZ11: 38867000 | BA11: 3062172000 | BB11: 9864267000 | BC11: 4025611000 | BD11: -60217000 | BE11: -221801000
A12: 2022-01-31 | B12: 1451594000 | C12: 1068373000 | D12: 223092000 | E12: 616546000 | F12: 839638000 | G12: 371283000 | H12: 7756000 | I12: -142548000 | J12: 24684000 | K12: 1019000 | L12: 72355000 | M12: -234802000 | N12: 908470000 | O12: 908470000 | P12: 441095000 | Q12: -125354000 | R12: 33248000 | S12: -3470000 | T12: 68810000 | U12: 309952000 | V12: -18779000 | W12: 321723000 | X12: 420828000 | Y12: 78025000 | Z12: 574784000 | AA12: -133689000 | AB12: -133689000 | AC12: -410268000 | AD12: -16309000 | AE12: -564516000 | AF12: 0 | AG12: 66175999 | AH12: 50277000 | AI12: 0 | AJ12: 72531000 | AK12: -4774000 | AL12: 7376189000 | AM12: 0 | AN12: 7376189000 | AO12: 1129190000 | AP12: 416316000 | AQ12: 299371000 | AR12: 9221066000 | AS12: 1047108000 | AT12: 1539225000 | AU12: 354637000 | AV12: 68627000 | AW12: 3714148000 | AX12: 12935214000 | AY12: 77911000 | AZ12: 38233000 | BA12: 3069944000 | BB12: 9173203000 | BC12: 3762011000 | BD12: -73738000 | BE12: -207427000
A13: 2021-10-31 | B13: 1285513000 | C13: 948180000 | D13: 184261000 | E13: 566401000 | F13: 750662000 | G13: 332335000 | H13: 6759000 | I13: -134817000 | J13: 19431000 | K13: 1019000 | L13: 61605000 | M13: -211824000 | N13: 900508000 | O13: 900508000 | P13: 410975000 | Q13: -106967000 | R13: -2264000 | S13: 75313000 | T13: 60155000 | U13: 265029000 | V13: -4178000 | W13: 307949000 | X13: 345396000 | Y13: 847582000 | Z13: 529529000 | AA13: -118554000 | AB13: -118554000 | AC13: -349544000 | AD13: -15231000 | AE13: -488157000 | AF13: -1563000 | AG13: 18725999 | AH13: 34263000 | AI13: 0 | AJ13: 806882000 | AK13: -672000 | AL13: 7298164000 | AM13: 0 | AN13: 7298164000 | AO13: 1000244000 | AP13: 370344000 | AQ13: 273636000 | AR13: 8942388000 | AS13: 958294000 | AT13: 1206346000 | AU13: 272978000 | AV13: 47495000 | AW13: 3106978000 | AX13: 12049366000 | AY13: 42342000 | AZ13: 37390000 | BA13: 3075063000 | BB13: 8453124000 | BC13: 3596242000 | BD13: -74662000 | BE13: -193216000
... A24: 2019-01-31 | B24: 232840000 | C24: 145007000 | D24: 39861000 | E24: 166834000 | F24: 206695000 | G24: 81516000 | H24: 434000 | I24: -143204000 | J24: 192000 | K24: 190000 | L24: 1488000 | M24: -148917000 | N24: 556661020 | O24: 556661000 | P24: -40126000 | Q24: -34366000 | R24: 0 | S24: 0 | T24: 11079000 | U24: 19619000 | V24: 1155000 | W24: 36350000 | X24: 70716000 | Y24: -43837000 | Z24: -949000 | AA24: -39177000 | AB24: -39177000 | AC24: 3593000 | AD24: -119131000 | AE24: -54860000 | AF24: 0 | AG24: 0 | AH24: 0 | AI24: 0 | AJ24: 11750000 | AK24: 222000 | AL24: 169277000 | AM24: 345351000 | AN24: 514628000 | AO24: 229155000 | AP24: 46152001 | AQ24: 66404999 | AR24: 856340000 | AS24: 152994000 | AT24: 24250000 | AU24: 25267000 | AV24: 0 | AW24: 184136000 | AX24: 1040476000 | AY24: 24849000 | AZ24: 51825000 | BA24: 15971000 | BB24: 818408000 | BC24: 134299000 | BD24: -132125000 | BE24: -171302000
A25: 2018-10-31
A26: 2018-04-30
A27: 2018-01-31

Sheet TTM Margins
A1: date | B1: revenue | C1: grossProfit | D1: generalAndAdministrativeExpenses | E1: sellingAndMarketingExpenses | F1: sellingGeneralAndAdministrativeExpenses | G1: researchAndDevelopmentExpenses | H1: otherExpenses | I1: operatingIncome | J1: interestExpense | K1: interestIncome | L1: incomeTaxExpense | M1: netIncome | N1: weightedAverageShsOut | O1: weightedAverageShsOutDil | P1: freeCashFlow | Q1: accountsReceivables | R1: accountsPayables | S1: inventory_x | T1: depreciationAndAmortization | U1: stockBasedCompensation | V1: deferredIncomeTax | W1: changeInWorkingCapital | X1: otherWorkingCapital | Y1: netChangeInCash | Z1: netCashProvidedByOperatingActivities | AA1: capitalExpenditure | AB1: investmentsInPropertyPlantAndEquipment | AC1: acquisitionsNet | AD1: purchasesOfInvestments | AE1: netCashUsedForInvestingActivites | AF1: debtRepayment | AG1: commonStockIssued | AH1: commonStockRepurchased | AI1: dividendsPaid | AJ1: netCashUsedProvidedByFinancingActivities | AK1: effectOfForexChangesOnCash | AL1: cashAndCashEquivalents | AM1: shortTermInvestments | AN1: cashAndShortTermInvestments | AO1: netReceivables | AP1: inventory_y | AQ1: otherCurrentAssets | AR1: totalCurrentAssets | AS1: propertyPlantEquipmentNet | AT1: goodwill | AU1: intangibleAssets | AV1: longTermInvestments | AW1: totalNonCurrentAssets | AX1: totalAssets | AY1: accountPayables | AZ1: shortTermDebt | BA1: longTermDebt | BB1: totalLiabilities | BC1: totalEquity | BD1: EBITDA | BE1: FCFsimple
A2: 2024-07-31 | B2: 1 | C2: 0.753 | D2: 0.119 | E2: 0.365 | F2: 0.483 | G2: 0.255 | H2: 0.003 | I2: 0.016 | J2: 0.006 | K2: 0.051 | L2: 0.012 | M2: 0.048 | N2: 0.275 | O2: 0.282 | P2: 0.315 | Q2: -0.032 | R2: -0.005 | S2: -0.002 | T2: 0.052 | U2: 0.205 | V2: -0.001 | W2: -0.007 | X2: 0.014 | Y2: 0.249 | Z2: 0.378 | AA2: -0.063 | AB2: -0.063 | AC2: -0.094 | AD2: -0.058 | AE2: -0.156 | AF2: 0 | AG2: 0.027 | AH2: 0.022 | AI2: 0 | AJ2: 0.026 | AK2: 0 | AL2: 4.006 | AM2: 0.084 | AN2: 4.09 | AO2: 0.79 | AP2: 0.059 | AQ2: 0.213 | AR2: 5.152 | AS2: 0.76 | AT2: 0.773 | AU2: 0.131 | AV2: 0.066 | AW2: 2.39 | AX2: 7.543 | AY2: 0.036 | AZ2: 0.018 | BA2: 0.856 | BB2: 4.739 | BC2: 2.803 | BD2: 0.068 | BE2: 0.004
A3: 2024-04-30 | B3: 1 | C3: 0.753 | D3: 0.142 | E3: 0.353 | F3: 0.494 | G3: 0.251 | H3: 0.003 | I3: 0.008 | J3: 0.006 | K3: 0.05 | L3: 0.011 | M3: 0.04 | N3: 0.292 | O3: 0.3 | P3: 0.312 | Q3: -0.071 | R3: 0 | S3: 0 | T3: 0.05 | U3: 0.208 | V3: -0.001 | W3: 0.001 | X3: 0.053 | Y3: 0.267 | Z3: 0.38 | AA3: -0.068 | AB3: -0.068 | AC3: -0.132 | AD3: -0.062 | AE3: -0.139 | AF3: 0 | AG3: 0.025 | AH3: 0.023 | AI3: 0 | AJ3: 0.025 | AK3: 0 | AL3: 4.024 | AM3: 0.09 | AN3: 4.114 | AO3: 0.809 | AP3: 0.124 | AQ3: 0.202 | AR3: 5.249 | AS3: 0.787 | AT3: 0.739 | AU3: 0.129 | AV3: 0.071 | AW3: 2.315 | AX3: 7.564 | AY3: 0.044 | AZ3: 0.018 | BA3: 0.926 | BB3: 4.873 | BC3: 2.691 | BD3: 0.058 | BE3: -0.011
A4: 2024-01-31 | B4: 1 | C4: 0.752 | D4: 0.145 | E4: 0.356 | F4: 0.501 | G4: 0.252 | H4: 0.001 | I4: 0.01 | J4: 0.006 | K4: 0.049 | L4: 0.011 | M4: 0.029 | N4: 0.312 | O4: 0.319 | P4: 0.304 | Q4: -0.071 | R4: -0.006 | S4: 0 | T4: 0.048 | U4: 0.207 | V4: -0.001 | W4: 0.017 | X4: 0.074 | Y4: 0.303 | Z4: 0.382 | AA4: -0.078 | AB4: -0.078 | AC4: -0.107 | AD4: -0.07 | AE4: -0.111 | AF4: 0 | AG4: 0.028 | AH4: 0.025 | AI4: 0 | AJ4: 0.03 | AK4: 0.001 | AL4: 4.039 | AM4: 0.13 | AN4: 4.169 | AO4: 0.791 | AP4: 0.194 | AQ4: 0.197 | AR4: 5.351 | AS4: 0.812 | AT4: 0.699 | AU4: 0.126 | AV4: 0.076 | AW4: 2.221 | AX4: 7.572 | AY4: 0.046 | AZ4: 0.02 | BA4: 1.007 | BB4: 4.986 | BC4: 2.586 | BD4: 0.057 | BE4: -0.02
A5: 2023-10-31 | B5: 1 | C5: 0.746 | D5: 0.15 | E5: 0.367 | F5: 0.517 | G5: 0.262 | H5: -0.002 | I5: -0.022 | J5: 0.007 | K5: 0.047 | L5: 0.008 | M5: -0.005 | N5: 0.333 | O5: 0.338 | P5: 0.303 | Q5: -0.026 | R5: -0.013 | S5: 0.022 | T5: 0.046 | U5: 0.213 | V5: -0.001 | W5: 0.046 | X5: 0.064 | Y5: 0.178 | Z5: 0.384 | AA5: -0.08 | AB5: -0.08 | AC5: -0.114 | AD5: -0.163 | AE5: -0.239 | AF5: 0 | AG5: 0.028 | AH5: 0.021 | AI5: 0 | AJ5: 0.031 | AK5: 0.001 | AL5: 4.011 | AM5: 0.192 | AN5: 4.203 | AO5: 0.769 | AP5: 0.274 | AQ5: 0.19 | AR5: 5.436 | AS5: 0.824 | AT5: 0.678 | AU5: 0.126 | AV5: 0.079 | AW5: 2.12 | AX5: 7.556 | AY5: 0.055 | AZ5: 0.021 | BA5: 1.09 | BB5: 5.079 | BC5: 2.477 | BD5: 0.024 | BE5: -0.056
A6: 2023-07-31 | B6: 1 | C6: 0.74 | D6: 0.153 | E6: 0.378 | F6: 0.531 | G6: 0.267 | H6: -0.001 | I6: -0.046 | J6: 0.01 | K6: 0.042 | L6: 0.009 | M6: -0.036 | N6: 0.357 | O6: 0.36 | P6: 0.302 | Q6: -0.046 | R6: -0.007 | S6: 0.003 | T6: 0.044 | U6: 0.223 | V6: 0 | W6: 0.087 | X6: 0.137 | Y6: 0.322 | Z6: 0.402 | AA6: -0.1 | AB6: -0.1 | AC6: -0.04 | AD6: -0.105 | AE6: -0.117 | AF6: -0.001 | AG6: 0.03 | AH6: 0.022 | AI6: 0 | AJ6: 0.032 | AK6: 0.001 | AL6: 4.132 | AM6: 0.132 | AN6: 4.265 | AO6: 0.799 | AP6: 0.277 | AQ6: 0.185 | AR6: 5.526 | AS6: 0.821 | AT6: 0.652 | AU6: 0.128 | AV6: 0.08 | AW6: 2.101 | AX6: 7.627 | AY6: 0.071 | AZ6: 0.021 | BA6: 1.166 | BB6: 5.232 | BC6: 2.395 | BD6: -0.002 | BE6: -0.102
A7: 2023-04-30 | B7: 1 | C7: 0.737 | D7: 0.136 | E7: 0.406 | F7: 0.541 | G7: 0.271 | H7: 0.001 | I7: -0.063 | J7: 0.01 | K7: 0.033 | L7: 0.01 | M7: -0.062 | N7: 0.383 | O7: 0.385 | P7: 0.305 | Q7: -0.038 | R7: 0.001 | S7: 0 | T7: 0.043 | U7: 0.227 | V7: 0 | W7: 0.13 | X7: 0.174 | Y7: 0.278 | Z7: 0.42 | AA7: -0.115 | AB7: -0.115 | AC7: -0.002 | AD7: -0.114 | AE7: -0.176 | AF7: -0.001 | AG7: 0.028 | AH7: 0.024 | AI7: 0 | AJ7: 0.03 | AK7: 0 | AL7: 4.117 | AM7: 0.143 | AN7: 4.26 | AO7: 0.814 | AP7: 0.219 | AQ7: 0.177 | AR7: 5.531 | AS7: 0.807 | AT7: 0.698 | AU7: 0.143 | AV7: 0.077 | AW7: 2.15 | AX7: 7.681 | AY7: 0.084 | AZ7: 0.02 | BA7: 1.255 | BB7: 5.35 | BC7: 2.331 | BD7: -0.021 | BE7: -0.136
A8: 2023-01-31 | B8: 1 | C8: 0.732 | D8: 0.142 | E8: 0.404 | F8: 0.545 | G8: 0.271 | H8: 0.002 | I8: -0.085 | J8: 0.011 | K8: 0.023 | L8: 0.01 | M8: -0.082 | N8: 0.413 | O8: 0.416 | P8: 0.301 | Q8: -0.115 | R8: -0.007 | S8: 0 | T8: 0.042 | U8: 0.235 | V8: 0.001 | W8: 0.143 | X8: 0.273 | Y8: 0.205 | Z8: 0.42 | AA8: -0.119 | AB8: -0.119 | AC8: -0.006 | AD8: -0.121 | AE8: -0.248 | AF8: -0.001 | AG8: 0.03 | AH8: 0.027 | AI8: 0 | AJ8: 0.031 | AK8: -0.001 | AL8: 4.191 | AM8: 0.112 | AN8: 4.303 | AO8: 0.847 | AP8: 0.216 | AQ8: 0.168 | AR8: 5.601 | AS8: 0.778 | AT8: 0.755 | AU8: 0.161 | AV8: 0.07 | AW8: 2.201 | AX8: 7.802 | AY8: 0.089 | AZ8: 0.02 | BA8: 1.362 | BB8: 5.488 | BC8: 2.314 | BD8: -0.043 | BE8: -0.162
A9: 2022-10-31 | B9: 1 | C9: 0.735 | D9: 0.151 | E9: 0.403 | F9: 0.554 | G9: 0.256 | H9: 0.004 | I9: -0.075 | J9: 0.012 | K9: 0.013 | L9: 0.015 | M9: -0.087 | N9: 0.453 | O9: 0.456 | P9: 0.292 | Q9: -0.099 | R9: 0.032 | S9: -0.024 | T9: 0.042 | U9: 0.229 | V9: -0.006 | W9: 0.147 | X9: 0.246 | Y9: 0.275 | Z9: 0.407 | AA9: -0.115 | AB9: -0.115 | AC9: -0.037 | AD9: -0.009 | AE9: -0.163 | AF9: -0.001 | AG9: 0.033 | AH9: 0.025 | AI9: 0 | AJ9: 0.033 | AK9: -0.005 | AL9: 4.391 | AM9: 0 | AN9: 4.391 | AO9: 0.807 | AP9: 0.209 | AQ9: 0.164 | AR9: 5.643 | AS9: 0.739 | AT9: 0.825 | AU9: 0.182 | AV9: 0.066 | AW9: 2.258 | AX9: 7.901 | AY9: 0.099 | AZ9: 0.02 | BA9: 1.497 | BB9: 5.574 | BC9: 2.327 | BD9: -0.032 | BE9: -0.147
A10: 2022-07-31 | B10: 1 | C10: 0.737 | D10: 0.152 | E10: 0.407 | F10: 0.559 | G10: 0.253 | H10: 0.005 | I10: -0.074 | J10: 0.014 | K10: 0.006 | L10: 0.014 | M10: -0.094 | N10: 0.499 | O10: 0.503 | P10: 0.296 | Q10: -0.083 | R10: 0.016 | S10: -0.026 | T10: 0.044 | U10: 0.225 | V10: -0.007 | W10: 0.156 | X10: 0.252 | Y10: 0.291 | Z10: 0.405 | AA10: -0.11 | AB10: -0.11 | AC10: -0.029 | AD10: -0.009 | AE10: -0.152 | AF10: 0 | AG10: 0.037 | AH10: 0.027 | AI10: 0 | AJ10: 0.041 | AK10: -0.005 | AL10: 4.567 | AM10: 0 | AN10: 4.567 | AO10: 0.785 | AP10: 0.202 | AQ10: 0.167 | AR10: 5.801 | AS10: 0.722 | AT10: 0.885 | AU10: 0.198 | AV10: 0.06 | AW10: 2.327 | AX10: 8.129 | AY10: 0.065 | AZ10: 0.022 | BA10: 1.666 | BB10: 5.753 | BC10: 2.376 | BD10: -0.03 | BE10: -0.14
A11: 2022-04-30 | B11: 1 | C11: 0.736 | D11: 0.152 | E11: 0.412 | F11: 0.564 | G11: 0.254 | H11: 0.004 | I11: -0.083 | J11: 0.015 | K11: 0.002 | L11: 0.016 | M11: -0.11 | N11: 0.556 | O11: 0.559 | P11: 0.294 | Q11: -0.096 | R11: 0.005 | S11: -0.029 | T11: 0.046 | U11: 0.219 | V11: -0.008 | W11: 0.162 | X11: 0.286 | Y11: 0.286 | Z11: 0.392 | AA11: -0.099 | AB11: -0.099 | AC11: -0.034 | AD11: -0.011 | AE11: -0.147 | AF11: 0 | AG11: 0.04 | AH11: 0.031 | AI11: 0 | AJ11: 0.045 | AK11: -0.005 | AL11: 4.793 | AM11: 0 | AN11: 4.793 | AO11: 0.786 | AP11: 0.285 | AQ11: 0.195 | AR11: 6.059 | AS11: 0.711 | AT11: 0.966 | AU11: 0.22 | AV11: 0.054 | AW11: 2.428 | AX11: 8.487 | AY11: 0.052 | AZ11: 0.024 | BA11: 1.871 | BB11: 6.027 | BC11: 2.46 | BD11: -0.037 | BE11: -0.136
A12: 2022-01-31 | B12: 1 | C12: 0.736 | D12: 0.154 | E12: 0.425 | F12: 0.578 | G12: 0.256 | H12: 0.005 | I12: -0.098 | J12: 0.017 | K12: 0.001 | L12: 0.05 | M12: -0.162 | N12: 0.626 | O12: 0.626 | P12: 0.304 | Q12: -0.086 | R12: 0.023 | S12: -0.002 | T12: 0.047 | U12: 0.214 | V12: -0.013 | W12: 0.222 | X12: 0.29 | Y12: 0.054 | Z12: 0.396 | AA12: -0.092 | AB12: -0.092 | AC12: -0.283 | AD12: -0.011 | AE12: -0.389 | AF12: 0 | AG12: 0.046 | AH12: 0.035 | AI12: 0 | AJ12: 0.05 | AK12: -0.003 | AL12: 5.081 | AM12: 0 | AN12: 5.081 | AO12: 0.778 | AP12: 0.287 | AQ12: 0.206 | AR12: 6.352 | AS12: 0.721 | AT12: 1.06 | AU12: 0.244 | AV12: 0.047 | AW12: 2.559 | AX12: 8.911 | AY12: 0.054 | AZ12: 0.026 | BA12: 2.115 | BB12: 6.319 | BC12: 2.592 | BD12: -0.051 | BE12: -0.143
A13: 2021-10-31 | B13: 1 | C13: 0.738 | D13: 0.143 | E13: 0.441 | F13: 0.584 | G13: 0.259 | H13: 0.005 | I13: -0.105 | J13: 0.015 | K13: 0.001 | L13: 0.048 | M13: -0.165 | N13: 0.701 | O13: 0.701 | P13: 0.32 | Q13: -0.083 | R13: -0.002 | S13: 0.059 | T13: 0.047 | U13: 0.206 | V13: -0.003 | W13: 0.24 | X13: 0.269 | Y13: 0.659 | Z13: 0.412 | AA13: -0.092 | AB13: -0.092 | AC13: -0.272 | AD13: -0.012 | AE13: -0.38 | AF13: -0.001 | AG13: 0.015 | AH13: 0.027 | AI13: 0 | AJ13: 0.628 | AK13: -0.001 | AL13: 5.677 | AM13: 0 | AN13: 5.677 | AO13: 0.778 | AP13: 0.288 | AQ13: 0.213 | AR13: 6.956 | AS13: 0.745 | AT13: 0.938 | AU13: 0.212 | AV13: 0.037 | AW13: 2.417 | AX13: 9.373 | AY13: 0.033 | AZ13: 0.029 | BA13: 2.392 | BB13: 6.576 | BC13: 2.798 | BD13: -0.058 | BE13: -0.15
... A24: 2019-01-31 | B24: 1 | C24: 0.623 | D24: 0.171 | E24: 0.717 | F24: 0.888 | G24: 0.35 | H24: 0.002 | I24: -0.615 | J24: 0.001 | K24: 0.001 | L24: 0.006 | M24: -0.64 | N24: 2.391 | O24: 2.391 | P24: -0.172 | Q24: -0.148 | R24: 0 | S24: 0 | T24: 0.048 | U24: 0.084 | V24: 0.005 | W24: 0.156 | X24: 0.304 | Y24: -0.188 | Z24: -0.004 | AA24: -0.168 | AB24: -0.168 | AC24: 0.015 | AD24: -0.512 | AE24: -0.236 | AF24: 0 | AG24: 0 | AH24: 0 | AI24: 0 | AJ24: 0.05 | AK24: 0.001 | AL24: 0.727 | AM24: 1.483 | AN24: 2.21 | AO24: 0.984 | AP24: 0.198 | AQ24: 0.285 | AR24: 3.678 | AS24: 0.657 | AT24: 0.104 | AU24: 0.109 | AV24: 0 | AW24: 0.791 | AX24: 4.469 | AY24: 0.107 | AZ24: 0.223 | BA24: 0.069 | BB24: 3.515 | BC24: 0.577 | BD24: -0.567 | BE24: -0.736
A25: 2018-10-31
A26: 2018-04-30
A27: 2018-01-31

Sheet TTM Quarterly % Change
A1: date | B1: revenue | C1: grossProfit | D1: generalAndAdministrativeExpenses | E1: sellingAndMarketingExpenses | F1: sellingGeneralAndAdministrativeExpenses | G1: researchAndDevelopmentExpenses | H1: otherExpenses | I1: operatingIncome | J1: interestExpense | K1: interestIncome | L1: incomeTaxExpense | M1: netIncome | N1: weightedAverageShsOut | O1: weightedAverageShsOutDil | P1: freeCashFlow | Q1: accountsReceivables | R1: accountsPayables | S1: inventory_x | T1: depreciationAndAmortization | U1: stockBasedCompensation | V1: deferredIncomeTax | W1: changeInWorkingCapital | X1: otherWorkingCapital | Y1: netChangeInCash | Z1: netCashProvidedByOperatingActivities | AA1: capitalExpenditure | AB1: investmentsInPropertyPlantAndEquipment | AC1: acquisitionsNet | AD1: purchasesOfInvestments | AE1: netCashUsedForInvestingActivites | AF1: debtRepayment | AG1: commonStockIssued | AH1: commonStockRepurchased | AI1: dividendsPaid | AJ1: netCashUsedProvidedByFinancingActivities | AK1: effectOfForexChangesOnCash | AL1: cashAndCashEquivalents | AM1: shortTermInvestments | AN1: cashAndShortTermInvestments | AO1: netReceivables | AP1: inventory_y | AQ1: otherCurrentAssets | AR1: totalCurrentAssets | AS1: propertyPlantEquipmentNet | AT1: goodwill | AU1: intangibleAssets | AV1: longTermInvestments | AW1: totalNonCurrentAssets | AX1: totalAssets | AY1: accountPayables | AZ1: shortTermDebt | BA1: longTermDebt | BB1: totalLiabilities | BC1: totalEquity | BD1: EBITDA | BE1: FCFsimple
A2: 2024-07-31 | B2: 0.071 | C2: 0.072 | D2: -0.101 | E2: 0.107 | F2: 0.047 | G2: 0.087 | H2: 0.078 | I2: 1.144 | J2: 0.005 | K2: 0.091 | L2: 0.178 | M2: 0.293 | N2: 0.006 | O2: 0.009 | P2: 0.082 | Q2: -0.517 | R2: 613.923 | S2: -inf | T2: 0.115 | U2: 0.053 | V2: 0.466 | W2: -8.693 | X2: -0.716 | Y2: -0.004 | Z2: 0.066 | AA2: -0.01 | AB2: -0.01 | AC2: -0.237 | AD2: -0.006 | AE2: 0.2 | AG2: 0.13 | AH2: 0 | AJ2: 0.094 | AK2: -1.714 | AL2: 0.066 | AM2: 0 | AN2: 0.064 | AO2: 0.046 | AP2: -0.485 | AQ2: 0.127 | AR2: 0.051 | AS2: 0.034 | AT2: 0.12 | AU2: 0.086 | AV2: -0.006 | AW2: 0.105 | AX2: 0.068 | AY2: -0.112 | AZ2: 0.015 | BA2: -0.01 | BB2: 0.041 | BC2: 0.115 | BD2: 0.255 | BE2: -1.445
A3: 2024-04-30 | B3: 0.075 | C3: 0.075 | D3: 0.048 | E3: 0.063 | F3: 0.059 | G3: 0.073 | H3: 4.534 | I3: -0.144 | J3: 0.006 | K3: 0.103 | L3: 0.101 | M3: 0.474 | N3: 0.006 | O3: 0.01 | P3: 0.103 | Q3: 0.068 | R3: -0.999 | T3: 0.125 | U3: 0.083 | V3: 0 | W3: -0.94 | X3: -0.233 | Y3: -0.051 | Z3: 0.071 | AA3: -0.055 | AB3: -0.055 | AC3: 0.328 | AD3: -0.043 | AE3: 0.342 | AG3: -0.021 | AH3: 0 | AJ3: -0.117 | AK3: -0.882 | AL3: 0.071 | AM3: -0.252 | AN3: 0.061 | AO3: 0.1 | AP3: -0.315 | AQ3: 0.101 | AR3: 0.054 | AS3: 0.041 | AT3: 0.136 | AU3: 0.1 | AV3: 0.002 | AW3: 0.12 | AX3: 0.074 | AY3: 0.032 | AZ3: -0.003 | BA3: -0.011 | BB3: 0.051 | BC3: 0.118 | BD3: 0.078 | BE3: -0.434
A4: 2024-01-31 | B4: 0.073 | C4: 0.082 | D4: 0.042 | E4: 0.042 | F4: 0.04 | G4: 0.03 | H4: -1.344 | I4: -1.484 | J4: 0.004 | K4: 0.109 | L4: 0.347 | M4: -7.714 | N4: 0.006 | O4: 0.013 | P4: 0.075 | Q4: 1.902 | R4: -0.504 | S4: -1 | T4: 0.111 | U4: 0.039 | V4: 0.016 | W4: -0.61 | X4: 0.236 | Y4: 0.823 | Z4: 0.067 | AA4: 0.038 | AB4: 0.038 | AC4: 0.001 | AD4: -0.537 | AE4: -0.499 | AG4: 0.079 | AH4: 0.285 | AJ4: 0.072 | AK4: -0.097 | AL4: 0.081 | AM4: -0.275 | AN4: 0.064 | AO4: 0.104 | AP4: -0.24 | AQ4: 0.113 | AR4: 0.056 | AS4: 0.058 | AT4: 0.107 | AU4: 0.077 | AV4: 0.04 | AW4: 0.124 | AX4: 0.075 | AY4: -0.11 | AZ4: 0.018 | BA4: -0.009 | BB4: 0.053 | BC4: 0.12 | BD4: 1.568 | BE4: -0.615
A5: 2023-10-31 | B5: 0.078 | C5: 0.086 | D5: 0.053 | E5: 0.047 | F5: 0.048 | G5: 0.058 | H5: 0.346 | I5: -0.488 | J5: -0.227 | K5: 0.216 | L5: 0.032 | M5: -0.859 | N5: 0.006 | O5: 0.011 | P5: 0.082 | Q5: -0.378 | R5: 0.981 | S5: 7.319 | T5: 0.128 | U5: 0.033 | V5: 4.131 | W5: -0.427 | X5: -0.498 | Y5: -0.404 | Z5: 0.029 | AA5: -0.132 | AB5: -0.132 | AC5: 2.094 | AD5: 0.671 | AE5: 1.203 | AF5: -1 | AG5: 0.007 | AH5: 0 | AJ5: 0.026 | AK5: -0.447 | AL5: 0.046 | AM5: 0.564 | AN5: 0.062 | AO5: 0.036 | AP5: 0.064 | AQ5: 0.107 | AR5: 0.06 | AS5: 0.081 | AT5: 0.12 | AU5: 0.059 | AV5: 0.062 | AW5: 0.088 | AX5: 0.068 | AY5: -0.171 | AZ5: 0.072 | BA5: 0.007 | BB5: 0.046 | BC5: 0.114 | BD5: -12.259 | BE5: -0.406
A6: 2023-07-31 | B6: 0.08 | C6: 0.086 | D6: 0.22 | E6: 0.007 | F6: 0.06 | G6: 0.062 | H6: -3.241 | I6: -0.213 | J6: 0.004 | K6: 0.355 | L6: -0.007 | M6: -0.379 | N6: 0.006 | O6: 0.01 | P6: 0.071 | Q6: 0.312 | R6: -9.111 | S6: inf | T6: 0.115 | U6: 0.06 | V6: -0.073 | W6: -0.276 | X6: -0.147 | Y6: 0.253 | Z6: 0.034 | AA6: -0.065 | AB6: -0.065 | AC6: 20.269 | AD6: -0.01 | AE6: -0.281 | AF6: 0 | AG6: 0.157 | AH6: 0 | AJ6: 0.149 | AK6: 3.978 | AL6: 0.084 | AM6: 0 | AN6: 0.081 | AO6: 0.061 | AP6: 0.368 | AQ6: 0.13 | AR6: 0.079 | AS6: 0.099 | AT6: 0.009 | AU6: -0.031 | AV6: 0.128 | AW6: 0.055 | AX6: 0.073 | AY6: -0.082 | AZ6: 0.116 | BA6: 0.004 | BB6: 0.057 | BC6: 0.11 | BD6: -0.881 | BE6: -0.19
A7: 2023-04-30 | B7: 0.091 | C7: 0.099 | D7: 0.046 | E7: 0.097 | F7: 0.084 | G7: 0.092 | H7: -0.654 | I7: -0.185 | J7: 0.026 | K7: 0.553 | L7: 0.043 | M7: -0.169 | N7: 0.012 | O7: 0.01 | P7: 0.105 | Q7: -0.644 | R7: -1.153 | T7: 0.108 | U7: 0.054 | V7: -1.537 | W7: -0.007 | X7: -0.305 | Y7: 0.475 | Z7: 0.091 | AA7: 0.056 | AB7: 0.056 | AC7: -0.656 | AD7: 0.029 | AE7: -0.228 | AF7: 0 | AG7: -0.007 | AH7: 0 | AJ7: 0.07 | AK7: -1.526 | AL7: 0.072 | AM7: 0.4 | AN7: 0.081 | AO7: 0.048 | AP7: 0.106 | AQ7: 0.147 | AR7: 0.078 | AS7: 0.131 | AT7: 0.009 | AU7: -0.03 | AV7: 0.185 | AW7: 0.066 | AX7: 0.074 | AY7: 0.029 | AZ7: 0.143 | BA7: 0.005 | BB7: 0.064 | BC7: 0.1 | BD7: -0.471 | BE7: -0.084
A8: 2023-01-31 | B8: 0.101 | C8: 0.096 | D8: 0.035 | E8: 0.102 | F8: 0.084 | G8: 0.166 | H8: -0.495 | I8: 0.25 | J8: 0.002 | K8: 1.06 | L8: -0.27 | M8: 0.039 | N8: 0.006 | O8: 0.006 | P8: 0.136 | Q8: 0.278 | R8: -1.237 | S8: -1 | T8: 0.085 | U8: 0.128 | V8: -1.105 | W8: 0.072 | X8: 0.22 | Y8: -0.179 | Z8: 0.137 | AA8: 0.141 | AB8: 0.141 | AC8: -0.809 | AD8: 13.691 | AE8: 0.681 | AF8: 0 | AG8: 0.02 | AH8: 0.182 | AJ8: 0.016 | AK8: -0.853 | AL8: 0.051 | AM8: inf | AN8: 0.079 | AO8: 0.157 | AP8: 0.141 | AQ8: 0.127 | AR8: 0.093 | AS8: 0.159 | AT8: 0.008 | AU8: -0.028 | AV8: 0.176 | AW8: 0.074 | AX8: 0.088 | AY8: -0.011 | AZ8: 0.08 | BA8: 0.002 | BB8: 0.084 | BC8: 0.095 | BD8: 0.466 | BE8: 0.213
A9: 2022-10-31 | B9: 0.11 | C9: 0.107 | D9: 0.101 | E9: 0.1 | F9: 0.1 | G9: 0.124 | H9: 0.007 | I9: 0.119 | J9: -0.003 | K9: 1.485 | L9: 0.167 | M9: 0.024 | N9: 0.006 | O9: 0.006 | P9: 0.094 | Q9: 0.33 | R9: 1.278 | S9: 0 | T9: 0.071 | U9: 0.129 | V9: -0.076 | W9: 0.047 | X9: 0.085 | Y9: 0.051 | Z9: 0.113 | AA9: 0.162 | AB9: 0.162 | AC9: 0.432 | AD9: 0.1 | AE9: 0.189 | AF9: -inf | AG9: -0.027 | AH9: 0 | AJ9: -0.101 | AK9: 0.149 | AL9: 0.067 | AN9: 0.067 | AO9: 0.14 | AP9: 0.144 | AQ9: 0.094 | AR9: 0.079 | AS9: 0.136 | AT9: 0.035 | AU9: 0.018 | AV9: 0.215 | AW9: 0.076 | AX9: 0.078 | AY9: 0.686 | AZ9: 0.018 | BA9: -0.003 | BB9: 0.075 | BC9: 0.087 | BD9: 0.188 | BE9: 0.168
A10: 2022-07-31 | B10: 0.121 | C10: 0.122 | D10: 0.12 | E10: 0.105 | F10: 0.109 | G10: 0.114 | H10: 0.445 | I10: 0.007 | J10: 0.002 | K10: 3.059 | L10: 0.021 | M10: -0.045 | N10: 0.007 | O10: 0.007 | P10: 0.129 | Q10: -0.038 | R10: 2.884 | S10: 0 | T10: 0.078 | U10: 0.154 | V10: 0.035 | W10: 0.074 | X10: -0.013 | Y10: 0.14 | Z10: 0.158 | AA10: 0.243 | AB10: 0.243 | AC10: -0.051 | AD10: -0.056 | AE10: 0.158 | AG10: 0.047 | AH10: 0 | AJ10: 0.035 | AK10: 0.05 | AL10: 0.068 | AN10: 0.068 | AO10: 0.118 | AP10: -0.205 | AQ10: -0.04 | AR10: 0.073 | AS10: 0.138 | AT10: 0.026 | AU10: 0.012 | AV10: 0.24 | AW10: 0.074 | AX10: 0.073 | AY10: 0.4 | AZ10: 0.024 | BA10: -0.002 | BB10: 0.07 | BC10: 0.082 | BD10: -0.082 | BE10: 0.155
A11: 2022-04-30 | B11: 0.127 | C11: 0.128 | D11: 0.115 | E11: 0.095 | F11: 0.1 | G11: 0.122 | H11: -0.201 | I11: -0.052 | J11: 0.003 | K11: 1.479 | L11: -0.644 | M11: -0.233 | N11: 0.001 | O11: 0.008 | P11: 0.09 | Q11: 0.259 | R11: -0.778 | S11: 12.882 | T11: 0.088 | U11: 0.155 | V11: -0.31 | W11: -0.175 | X11: 0.111 | Y11: 4.995 | Z11: 0.117 | AA11: 0.209 | AB11: 0.209 | AC11: -0.865 | AD11: 0.093 | AE11: -0.574 | AG11: -0.01 | AH11: 0 | AJ11: 0.007 | AK11: 0.768 | AL11: 0.063 | AN11: 0.063 | AO11: 0.14 | AP11: 0.121 | AQ11: 0.064 | AR11: 0.075 | AS11: 0.112 | AT11: 0.027 | AU11: 0.014 | AV11: 0.299 | AW11: 0.07 | AX11: 0.074 | AY11: 0.097 | AZ11: 0.017 | BA11: -0.003 | BB11: 0.075 | BC11: 0.07 | BD11: -0.183 | BE11: 0.069
A12: 2022-01-31 | B12: 0.129 | C12: 0.127 | D12: 0.211 | E12: 0.089 | F12: 0.119 | G12: 0.117 | H12: 0.148 | I12: 0.057 | J12: 0.27 | K12: 0 | L12: 0.174 | M12: 0.108 | N12: 0.009 | O12: 0.009 | P12: 0.073 | Q12: 0.172 | R12: -15.686 | S12: -1.046 | T12: 0.144 | U12: 0.17 | V12: 3.495 | W12: 0.045 | X12: 0.218 | Y12: -0.908 | Z12: 0.085 | AA12: 0.128 | AB12: 0.128 | AC12: 0.174 | AD12: 0.071 | AE12: 0.156 | AF12: -1 | AG12: 2.534 | AH12: 0.467 | AJ12: -0.91 | AK12: 6.104 | AL12: 0.011 | AN12: 0.011 | AO12: 0.129 | AP12: 0.124 | AQ12: 0.094 | AR12: 0.031 | AS12: 0.093 | AT12: 0.276 | AU12: 0.299 | AV12: 0.445 | AW12: 0.195 | AX12: 0.074 | AY12: 0.84 | AZ12: 0.023 | BA12: -0.002 | BB12: 0.085 | BC12: 0.046 | BD12: -0.012 | BE12: 0.074
A13: 2021-10-31 | B13: 0.13 | C13: 0.128 | D13: 0.151 | E13: 0.117 | F13: 0.125 | G13: 0.137 | H13: 0.066 | I13: 0.136 | J13: 0.47 | K13: inf | L13: 0.07 | M13: 0.139 | N13: 0.01 | O13: 0.01 | P13: 0.128 | Q13: -0.051 | R13: -1.32 | S13: -0.302 | T13: 0.14 | U13: 0.21 | V13: 0.04 | W13: 0.111 | X13: 0.187 | Y13: 0.173 | Z13: 0.154 | AA13: 0.252 | AB13: 0.252 | AC13: -0.204 | AD13: 1.106 | AE13: -0.099 | AF13: -0.5 | AG13: -0.493 | AH13: 0 | AJ13: 0.003 | AK13: -2.045 | AL13: 0.131 | AM13: -1 | AN13: 0.131 | AO13: 0.124 | AP13: 0.143 | AQ13: 0.058 | AR13: 0.129 | AS13: 0.085 | AT13: 0.318 | AU13: 0.322 | AV13: 0.738 | AW13: 0.206 | AX13: 0.148 | AY13: -0.008 | AZ13: 0.029 | BA13: 0.313 | BB13: 0.199 | BC13: 0.042 | BD13: 0.132 | BE13: 0.203
A14: 2021-07-31 | B14: 0.139 | C14: 0.139 | D14: 0.154 | E14: 0.131 | F14: 0.136 | G14: 0.158 | H14: -0.018 | I14: 0.172 | J14: 0.862 | L14: 0.071 | M14: 0.173 | N14: 0.011 | O14: 0.011 | P14: 0.128 | Q14: 0.829 | R14: -2.781 | S14: 0.071 | T14: 0.142 | U14: 0.214 | V14: -0.152 | W14: 0.093 | X14: 0.332 | Y14: 0.062 | Z14: 0.132 | AA14: 0.148 | AB14: 0.148 | AC14: 0.001 | AD14: 2.241 | AE14: 0.034 | AF14: 0 | AG14: 8.841 | AH14: 0 | AJ14: 0.011 | AK14: -0.775 | AL14: 0.126 | AM14: 0 | AN14: 0.126 | AO14: 0.152 | AP14: 0.147 | AQ14: 0.269 | AR14: 0.134 | AS14: 0.069 | AT14: 0.666 | AU14: 0.703 | AV14: 0.802 | AW14: 0.293 | AX14: 0.169 | AY14: 0.287 | AZ14: 0.021 | BA14: 0.455 | BB14: 0.248 | BC14: 0.036 | BD14: 0.197 | BE14: 0.168
A15: 2021-04-30 | B15: 0.143 | C15: 0.144 | D15: 0.143 | E15: 0.117 | F15: 0.123 | G15: 0.175 | H15: 0.038 | I15: 0.095 | J15: 3.554 | L15: 10.3 | M15: 0.711 | N15: 0.013 | O15: 0.013 | P15: 0.104 | Q15: -0.149 | R15: -1.351 | S15: 0.708 | T15: 0.151 | U15: 0.205 | V15: 2.653 | W15: 0.366 | X15: 0.164 | Y15: -0.589 | Z15: 0.137 | AA15: 0.292 | AB15: 0.292 | AC15: 4.248 | AD15: -0.974 | AE15: -2.058 | AF15: 0 | AG15: inf | AH15: 0 | AJ15: -0.005 | AK15: 0.702 | AL15: 0.135 | AM15: 0 | AN15: 0.135 | AO15: 0.095 | AP15: 0.128 | AQ15: 0.054 | AR15: 0.127 | AS15: 0.069 | AT15: 2.011 | AU15: 2.696 | AV15: 0.896 | AW15: 0.403 | AX15: 0.179 | AY15: -0.085 | AZ15: 0.081 | BA15: 0.844 | BB15: 0.288 | BC15: 0.031 | BD15: 0.052 | BE15: 0.184
A16: 2021-01-31 | B16: 0.148 | C16: 0.161 | D16: 0.091 | E16: 0.1 | F16: 0.098 | G16: 0.146 | H16: -0.288 | I16: -0.142 | J16: 1.38 | L16: 1.105 | M16: -0.092 | N16: 0.016 | O16: 0.016 | P16: 0.189 | Q16: 1.832 | R16: -4.999 | S16: 0.424 | T16: 0.134 | U16: 0.185 | V16: 0.288 | W16: 0.001 | X16: 0.067 | Y16: 4.228 | Z16: 0.157 | AA16: 0.029 | AB16: 0.029 | AC16: 0.026 | AD16: -0.874 | AE16: -9.342 | AF16: 1 | AG16: -1 | AH16: 1.771 | AJ16: 10.957 | AK16: 1.89 | AL16: 0.487 | AM16: -0.996 | AN16: 0.249 | AO16: 0.118 | AP16: 0.178 | AQ16: 0.01 | AR16: 0.221 | AS16: 0.096 | AT16: 0.711 | AU16: 0.858 | AV16: 0.231 | AW16: 0.171 | AX16: 0.211 | AY16: 0.421 | AZ16: -0.639 | BA16: 7.472 | BB16: 0.376 | BC16: 0.042 | BD16: -0.277 | BE16: -0.136
A17: 2020-10-31 | B17: 0.164 | C17: 0.176 | D17: 0.102 | E17: 0.113 | F17: 0.11 | G17: 0.13 | H17: -0.275 | I17: -0.117 | J17: 0.103 | L17: 0.008 | M17: -0.097 | N17: 0.018 | O17: 0.018 | P17: 0.39 | Q17: -0.253 | R17: -12.512 | S17: 3.678 | T17: 0.147 | U17: 0.173 | V17: 0.274 | W17: 0.03 | X17: -0.157 | Y17: -0.047 | Z17: 0.193 | AA17: -0.236 | AB17: -0.236 | AC17: -14.907 | AD17: -0.093 | AE17: -6.065 | AF17: -inf | AG17: 0.032 | AH17: 0 | AJ17: 0.101 | AK17: -0.461 | AL17: 0.103 | AM17: -0.119 | AN17: 0.059 | AO17: 0.045 | AP17: 0.142 | AQ17: 0.042 | AR17: 0.06 | AS17: 0.112 | AT17: 2.407 | AU17: 8.145 | AV17: 0.625 | AW17: 0.204 | AX17: 0.085 | AY17: 0.097 | AZ17: -0.388 | BA17: 0.493 | BB17: 0.142 | BC17: 0.033 | BD17: -0.207 | BE17: -0.221
A18: 2020-07-31 | B18: 0.161 | C18: 0.168 | D18: -0.013 | E18: 0.1 | F18: 0.071 | G18: 0.128 | H18: 0.109 | I18: -0.145 | J18: 0.017 | L18: -0.08 | M18: -0.163 | N18: 0.115 | O18: 0.115 | P18: 0.533 | Q18: -0.407 | R18: -1.053 | S18: -0.448 | T18: 0.152 | U18: 0.079 | V18: -1.183 | W18: 0.148 | X18: 0.009 | Y18: -0.636 | Z18: 0.311 | AA18: -0.004 | AB18: -0.004 | AC18: -0.184 | AD18: -0.08 | AE18: 11.448 | AG18: 0 | AH18: 0 | AJ18: -0.915 | AK18: 32.719 | AL18: 0.121 | AM18: -0.113 | AN18: 0.067 | AO18: 0.06 | AP18: 0.119 | AQ18: 0.114 | AR18: 0.069 | AS18: 0.156 | AT18: 0.011 | AU18: -0.168 | AV18: 1 | AW18: 0.154 | AX18: 0.083 | AY18: 0.631 | AZ18: -0.228 | BA18: 1.098 | BB18: 0.158 | BC18: 0.022 | BD18: -0.213 | BE18: -0.127
A19: 2020-04-30 | B19: 0.17 | C19: 0.189 | D19: 0.148 | E19: 0.117 | F19: 0.125 | G19: 0.128 | H19: 0.615 | I19: -0.022 | J19: 0.321 | L19: 0.221 | M19: -0.048 | N19: 0.022 | O19: 0.022 | P19: 8.278 | Q19: -0.209 | R19: -0.292 | S19: inf | T19: 0.14 | U19: 0.249 | V19: -0.191 | W19: 0.608 | X19: 0.144 | Y19: 4.17 | Z19: 0.972 | AA19: -0.068 | AB19: -0.068 | AC19: -0.014 | AD19: 0.042 | AE19: -1.001 | AG19: 0 | AH19: 0 | AJ19: 0.011 | AK19: -1.485 | AL19: 0.497 | AM19: -0.09 | AN19: 0.302 | AO19: 0.111 | AP19: 0.196 | AQ19: 0.164 | AR19: 0.265 | AS19: 0.192 | AT19: -0.005 | AU19: -0.165 | AV19: 1 | AW19: 0.167 | AX19: 0.248 | AY19: -0.192 | AZ19: -0.162 | BA19: inf | BB19: -0.068 | BC19: 0.727 | BD19: -0.053 | BE19: -0.059
A20: 2020-01-31 | B20: 0.175 | C20: 0.194 | D20: 0.155 | E20: 0.11 | F20: 0.121 | G20: 0.147 | H20: 0.75 | I20: -0.001 | J20: 0.488 | L20: -0.008 | M20: -0.02 | N20: 0.052 | O20: 0.052 | P20: -1.325 | Q20: 0.057 | R20: -3.331 | S20: -1 | T20: 0.111 | U20: 0.362 | V20: 0.012 | W20: 0.291 | X20: 0.167 | Y20: -0.733 | Z20: 1.013 | AA20: -0.006 | AB20: -0.006 | AC20: 0.047 | AD20: 2.101 | AE20: 8.234 | AG20: inf | AH20: inf | AJ20: 0.041 | AK20: -1.373 | AL20: 0.106 | AM20: 1.473 | AN20: 0.355 | AO20: 0.165 | AP20: -0.022 | AQ20: 0.555 | AR20: 0.311 | AS20: 0.157 | AT20: -0.007 | AU20: -0.158 | AV20: inf | AW20: 0.213 | AX20: 0.293 | AY20: -0.238 | AZ20: 0.071 | BB20: 0.133 | BC20: 0.646 | BD20: -0.02 | BE20: -0.014
A21: 2019-10-31 | B21: 0.167 | C21: 0.181 | D21: 0.116 | E21: 0.101 | F21: 0.105 | G21: 0.097 | H21: 5.778 | I21: -0.024 | J21: 0.8 | L21: -0.048 | M21: -0.045 | N21: 0.049 | O21: 0.049 | P21: -0.344 | Q21: 0.185 | R21: 0 | S21: 0 | T21: 0.11 | U21: 0.17 | V21: -0.145 | W21: 0.463 | X21: 0.288 | Y21: 0.069 | Z21: 5.736 | AA21: 0.336 | AB21: 0.336 | AC21: 0.008 | AD21: 0.064 | AE21: -0.119 | AJ21: -0.013 | AK21: -1.691 | AL21: 0.662 | AM21: -0.046 | AN21: 0.464 | AO21: 0.184 | AP21: 0.338 | AQ21: 0.009 | AR21: 0.383 | AS21: 0.256 | AT21: -0.003 | AU21: -0.783 | AW21: 0.239 | AX21: 0.353 | AY21: -0.021 | AZ21: 0.447 | BB21: 0.16 | BC21: 1.498 | BD21: -0.043 | BE21: 0.084
A22: 2019-07-31 | B22: 0.21 | C22: 0.253 | D22: 0.515 | E22: 0.151 | F22: 0.222 | G22: 0.157 | H22: -0.315 | I22: 0.133 | J22: -0.145 | L22: 0.321 | M22: 0.137 | N22: -0.058 | O22: -0.058 | P22: 0.269 | Q22: 5.16 | R22: 0 | S22: 0 | T22: 0.138 | U22: 1.277 | V22: 2.962 | W22: -0.272 | X22: 0.327 | Y22: -17.998 | Z22: 0.025 | AA22: 0.236 | AB22: 0.236 | AC22: 0.238 | AD22: 0.385 | AE22: 0.525 | AJ22: 92.726 | AK22: 2.821 | AL22: 4.011 | AM22: -0.088 | AN22: 1.22 | AO22: 0.449 | AP22: 0.47 | AQ22: 0.483 | AR22: 0.927 | AS22: 0.518 | AT22: 0.329 | AU22: 0.051 | AW22: 0.871 | AX22: 0.915 | AY22: 0.05 | AZ22: 0.55 | BB22: 0.291 | BC22: -2.246 | BD22: 0.132 | BE22: 0.165
A23: 2019-04-30 | B23: 0.246 | C23: 0.326 | D23: 0.144 | E23: 0.135 | F23: 0.137 | G23: 0.097 | H23: 0.908 | I23: -0.077 | J23: 0.005 | K23: -1 | L23: 0.075 | M23: -0.106 | N23: 0.276 | O23: 0.276 | P23: 0.148 | Q23: -0.724 | R23: inf | S23: -inf | T23: 0.514 | U23: 0.123 | V23: 0.346 | W23: 0.95 | X23: 0.281 | Y23: -0.172 | Z23: -8.577 | AA23: 0.359 | AB23: 0.359 | AC23: 0.552 | AD23: 0.435 | AE23: -0.074 | AJ23: -0.376 | AK23: -1.302 | AL23: 0.176 | AM23: 0.23 | AN23: 0.212 | AO23: 0.121 | AP23: 0.568 | AQ23: -0.084 | AR23: 0.184 | AS23: 0.363 | AT23: -0.025 | AU23: -0.426 | AW23: 0.445 | AX23: 0.23 | AY23: -0.094 | AZ23: 0.846 | BA23: -1 | BB23: 0.863 | BC23: -3.475 | BD23: -0.126 | BE23: -0.015
A24: 2019-01-31
A25: 2018-10-31
A26: 2018-04-30
A27: 2018-01-31

Sheet TTM Yearly % Change
A1: date | B1: revenue | C1: grossProfit | D1: generalAndAdministrativeExpenses | E1: sellingAndMarketingExpenses | F1: sellingGeneralAndAdministrativeExpenses | G1: researchAndDevelopmentExpenses | H1: otherExpenses | I1: operatingIncome | J1: interestExpense | K1: interestIncome | L1: incomeTaxExpense | M1: netIncome | N1: weightedAverageShsOut | O1: weightedAverageShsOutDil | P1: freeCashFlow | Q1: accountsReceivables | R1: accountsPayables | S1: inventory_x | T1: depreciationAndAmortization | U1: stockBasedCompensation | V1: deferredIncomeTax | W1: changeInWorkingCapital | X1: otherWorkingCapital | Y1: netChangeInCash | Z1: netCashProvidedByOperatingActivities | AA1: capitalExpenditure | AB1: investmentsInPropertyPlantAndEquipment | AC1: acquisitionsNet | AD1: purchasesOfInvestments | AE1: netCashUsedForInvestingActivites | AF1: debtRepayment | AG1: commonStockIssued | AH1: commonStockRepurchased | AI1: dividendsPaid | AJ1: netCashUsedProvidedByFinancingActivities | AK1: effectOfForexChangesOnCash | AL1: cashAndCashEquivalents | AM1: shortTermInvestments | AN1: cashAndShortTermInvestments | AO1: netReceivables | AP1: inventory_y | AQ1: otherCurrentAssets | AR1: totalCurrentAssets | AS1: propertyPlantEquipmentNet | AT1: goodwill | AU1: intangibleAssets | AV1: longTermInvestments | AW1: totalNonCurrentAssets | AX1: totalAssets | AY1: accountPayables | AZ1: shortTermDebt | BA1: longTermDebt | BB1: totalLiabilities | BC1: totalEquity | BD1: EBITDA | BE1: FCFsimple
A2: 2024-07-31 | B2: 0.331 | C2: 0.354 | D2: 0.033 | E2: 0.284 | F2: 0.209 | G2: 0.27 | H2: -3.762 | I2: -1.454 | J2: -0.215 | K2: 0.622 | L2: 0.801 | M2: -2.799 | N2: 0.025 | O2: 0.044 | P2: 0.388 | Q2: -0.069 | R2: -0.169 | S2: -2 | T2: 0.57 | U2: 0.224 | V2: 6.637 | W2: -1.104 | X2: -0.865 | Y2: 0.027 | Z2: 0.253 | AA2: -0.157 | AB2: -0.157 | AC2: 2.136 | AD2: -0.264 | AE2: 0.778 | AF2: -1 | AG2: 0.202 | AH2: 0.285 | AJ2: 0.062 | AK2: -1.042 | AL2: 0.29 | AM2: -0.151 | AN2: 0.276 | AO2: 0.316 | AP2: -0.715 | AQ2: 0.528 | AR2: 0.241 | AS2: 0.231 | AT2: 0.579 | AU2: 0.363 | AV2: 0.101 | AW2: 0.514 | AX2: 0.316 | AY2: -0.324 | AZ2: 0.104 | BA2: -0.024 | BB2: 0.205 | BC2: 0.557 | BD2: -40.126 | BE2: -1.058
A3: 2024-04-30 | B3: 0.343 | C3: 0.371 | D3: 0.401 | E3: 0.167 | F3: 0.225 | G3: 0.242 | H3: 4.744 | I3: -1.167 | J3: -0.216 | K3: 1.015 | L3: 0.519 | M3: -1.864 | N3: 0.024 | O3: 0.045 | P3: 0.374 | Q3: 1.529 | R3: -1.011 | T3: 0.571 | U3: 0.232 | V3: 3.832 | W3: -0.99 | X3: -0.594 | Y3: 0.292 | Z3: 0.216 | AA3: -0.204 | AB3: -0.204 | AC3: 86.476 | AD3: -0.267 | AE3: 0.064 | AF3: -1 | AG3: 0.231 | AH3: 0.285 | AJ3: 0.114 | AK3: -0.706 | AL3: 0.312 | AM3: -0.151 | AN3: 0.297 | AO3: 0.334 | AP3: -0.242 | AQ3: 0.533 | AR3: 0.274 | AS3: 0.309 | AT3: 0.422 | AU3: 0.217 | AV3: 0.249 | AW3: 0.446 | AX3: 0.322 | AY3: -0.301 | AZ3: 0.215 | BA3: -0.009 | BB3: 0.223 | BC3: 0.55 | BD3: -4.712 | BE3: -0.895
A4: 2024-01-31 | B4: 0.363 | C4: 0.402 | D4: 0.4 | E4: 0.204 | F4: 0.253 | G4: 0.263 | H4: -0.641 | I4: -1.159 | J4: -0.201 | K4: 1.837 | L4: 0.439 | M4: -1.487 | N4: 0.03 | O4: 0.045 | P4: 0.377 | Q4: -0.157 | R4: 0.222 | T4: 0.548 | U4: 0.199 | V4: -3.593 | W4: -0.839 | X4: -0.632 | Y4: 1.008 | Z4: 0.239 | AA4: -0.11 | AB4: -0.11 | AC4: 21.652 | AD4: -0.212 | AE4: -0.388 | AF4: -1 | AG4: 0.25 | AH4: 0.285 | AJ4: 0.35 | AK4: -2.31 | AL4: 0.314 | AM4: 0.588 | AN4: 0.321 | AO4: 0.272 | AP4: 0.224 | AQ4: 0.598 | AR4: 0.302 | AS4: 0.423 | AT4: 0.262 | AU4: 0.073 | AV4: 0.477 | AW4: 0.376 | AX4: 0.323 | AY4: -0.303 | AZ4: 0.393 | BA4: 0.007 | BB4: 0.238 | BC4: 0.524 | BD4: -2.822 | BE4: -0.83
A5: 2023-10-31 | B5: 0.399 | C5: 0.42 | D5: 0.391 | E5: 0.274 | F5: 0.306 | G5: 0.431 | H5: -1.528 | I5: -0.59 | J5: -0.202 | K5: 4.269 | L5: -0.22 | M5: -0.925 | N5: 0.03 | O5: 0.037 | P5: 0.455 | Q5: -0.629 | R5: -1.584 | S5: -2.305 | T5: 0.512 | U5: 0.302 | V5: -0.731 | W5: -0.558 | X5: -0.637 | Y5: -0.095 | Z5: 0.32 | AA5: -0.021 | AB5: -0.021 | AC5: 3.324 | AD5: 24.024 | AE5: 1.054 | AF5: -1 | AG5: 0.181 | AH5: 0.182 | AJ5: 0.28 | AK5: -1.213 | AL5: 0.278 | AM5: inf | AN5: 0.34 | AO5: 0.333 | AP5: 0.837 | AQ5: 0.618 | AR5: 0.348 | AS5: 0.56 | AT5: 0.149 | AU5: -0.032 | AV5: 0.67 | AW5: 0.314 | AX5: 0.338 | AY5: -0.225 | AZ5: 0.476 | BA5: 0.019 | BB5: 0.275 | BC5: 0.489 | BD5: -2.04 | BE5: -0.465
A6: 2023-07-31 | B6: 0.441 | C6: 0.447 | D6: 0.454 | E6: 0.339 | F6: 0.37 | G6: 0.521 | H6: -1.395 | I6: -0.103 | J6: 0.029 | K6: 9.77 | L6: -0.117 | M6: -0.45 | N6: 0.03 | O6: 0.032 | P6: 0.471 | Q6: -0.205 | R6: -1.671 | S6: -1.157 | T6: 0.437 | U6: 0.423 | V6: -0.952 | W6: -0.192 | X6: -0.215 | Y6: 0.595 | Z6: 0.428 | AA6: 0.311 | AB6: 0.311 | AC6: 1.002 | AD6: 15.47 | AE6: 0.109 | AF6: -inf | AG6: 0.141 | AH6: 0.182 | AJ6: 0.121 | AK6: -1.442 | AL6: 0.304 | AM6: inf | AN6: 0.345 | AO6: 0.467 | AP6: 0.975 | AQ6: 0.6 | AR6: 0.372 | AS6: 0.638 | AT6: 0.061 | AU6: -0.069 | AV6: 0.909 | AW6: 0.301 | AX6: 0.352 | AY6: 0.577 | AZ6: 0.402 | BA6: 0.009 | BB6: 0.31 | BC6: 0.453 | BD6: -0.89 | BE6: 0.051
A7: 2023-04-30 | B7: 0.495 | C7: 0.496 | D7: 0.335 | E7: 0.47 | F7: 0.434 | G7: 0.594 | H7: -0.745 | I7: 0.147 | J7: 0.026 | K7: 31.268 | L7: -0.092 | M7: -0.154 | N7: 0.031 | O7: 0.029 | P7: 0.551 | Q7: -0.418 | R7: -0.679 | S7: -1 | T7: 0.389 | U7: 0.55 | V7: -0.946 | W7: 0.198 | X7: -0.091 | Y7: 0.451 | Z7: 0.599 | AA7: 0.742 | AB7: 0.742 | AC7: -0.911 | AD7: 14.7 | AE7: 0.786 | AF7: -inf | AG7: 0.032 | AH7: 0.182 | AJ7: 0.01 | AK7: -1.093 | AL7: 0.284 | AM7: inf | AN7: 0.328 | AO7: 0.547 | AP7: 0.149 | AQ7: 0.358 | AR7: 0.364 | AS7: 0.695 | AT7: 0.08 | AU7: -0.029 | AV7: 1.1 | AW7: 0.324 | AX7: 0.353 | AY7: 1.403 | AZ7: 0.286 | BA7: 0.002 | BB7: 0.327 | BC7: 0.417 | BD7: -0.154 | BE7: 0.499
A8: 2023-01-31 | B8: 0.544 | C8: 0.535 | D8: 0.422 | E8: 0.467 | F8: 0.455 | G8: 0.639 | H8: -0.412 | I8: 0.334 | J8: 0.004 | K8: 50.516 | L8: -0.69 | M8: -0.22 | N8: 0.02 | O8: 0.027 | P8: 0.529 | Q8: 1.059 | R8: -1.465 | S8: -1 | T8: 0.363 | U8: 0.699 | V8: -1.07 | W8: -0.004 | X8: 0.453 | Y8: 4.899 | Z8: 0.637 | AA8: 0.993 | AB8: 0.993 | AC8: -0.965 | AD8: 15.67 | AE8: -0.014 | AF8: -inf | AG8: 0.029 | AH8: 0.182 | AJ8: -0.049 | AK8: -0.687 | AL8: 0.273 | AM8: inf | AN8: 0.307 | AO8: 0.682 | AP8: 0.164 | AQ8: 0.26 | AR8: 0.361 | AS8: 0.666 | AT8: 0.1 | AU8: 0.016 | AV8: 1.301 | AW8: 0.328 | AX8: 0.352 | AY8: 1.561 | AZ8: 0.144 | BA8: -0.006 | BB8: 0.341 | BC8: 0.378 | BD8: 0.306 | BE8: 0.749
A9: 2022-10-31 | B9: 0.583 | C9: 0.578 | D9: 0.664 | E9: 0.449 | F9: 0.502 | G9: 0.569 | H9: 0.335 | I9: 0.129 | J9: 0.272 | K9: 24.004 | L9: -0.502 | M9: -0.168 | N9: 0.023 | O9: 0.03 | P9: 0.445 | Q9: 0.888 | R9: -29.837 | S9: -1.64 | T9: 0.437 | U9: 0.761 | V9: 1.967 | W9: -0.03 | X9: 0.451 | Y9: -0.339 | Z9: 0.563 | AA9: 0.969 | AB9: 0.969 | AC9: -0.785 | AD9: 0.215 | AE9: -0.322 | AF9: 0.018 | AG9: 2.566 | AH9: 0.467 | AJ9: -0.916 | AK9: 14.156 | AL9: 0.224 | AN9: 0.224 | AO9: 0.641 | AP9: 0.147 | AQ9: 0.223 | AR9: 0.284 | AS9: 0.57 | AT9: 0.392 | AU9: 0.358 | AV9: 1.827 | AW9: 0.479 | AX9: 0.334 | AY9: 3.765 | AZ9: 0.084 | BA9: -0.009 | BB9: 0.342 | BC9: 0.317 | BD9: -0.12 | BE9: 0.548
A10: 2022-07-31 | B10: 0.612 | C10: 0.609 | D10: 0.74 | E10: 0.471 | F10: 0.535 | G10: 0.587 | H10: 0.413 | I10: 0.146 | J10: 0.875 | K10: inf | L10: -0.544 | M10: -0.074 | N10: 0.027 | O10: 0.034 | P10: 0.49 | Q10: 0.347 | R10: 3.051 | S10: -1.447 | T10: 0.529 | U10: 0.888 | V10: 2.339 | W10: 0.029 | X10: 0.587 | Y10: -0.262 | Z10: 0.62 | AA10: 1.121 | AB10: 1.121 | AC10: -0.88 | AD10: 1.327 | AE10: -0.486 | AF10: -1 | AG10: 0.857 | AH10: 0.467 | AJ10: -0.906 | AK10: -14.781 | AL10: 0.298 | AM10: -1 | AN10: 0.298 | AO10: 0.618 | AP10: 0.145 | AQ10: 0.182 | AR10: 0.343 | AS10: 0.501 | AT10: 0.772 | AU10: 0.763 | AV10: 3.045 | AW10: 0.657 | AX10: 0.42 | AY10: 1.804 | AZ10: 0.096 | BA10: 0.305 | BB10: 0.497 | BC10: 0.263 | BD10: -0.161 | BE10: 0.595
A11: 2022-04-30 | B11: 0.638 | C11: 0.633 | D11: 0.792 | E11: 0.506 | F11: 0.573 | G11: 0.651 | H11: -0.039 | I11: 0.334 | J11: 2.487 | K11: inf | L11: -0.522 | M11: 0.137 | N11: 0.031 | O11: 0.038 | P11: 0.488 | Q11: 1.56 | R11: -2.857 | S11: -1.478 | T11: 0.62 | U11: 0.985 | V11: 1.734 | W11: 0.047 | X11: 1.14 | Y11: -0.312 | Z11: 0.584 | AA11: 0.959 | AB11: 0.959 | AC11: -0.874 | AD11: 6.99 | AE11: -0.541 | AF11: -1 | AG11: 16.456 | AH11: 0.467 | AJ11: -0.908 | AK11: -3.948 | AL11: 0.369 | AM11: -1 | AN11: 0.369 | AO11: 0.666 | AP11: 0.652 | AQ11: 0.562 | AR11: 0.419 | AS11: 0.409 | AT11: 1.877 | AU11: 1.967 | AV11: 4.877 | AW11: 0.994 | AX11: 0.547 | AY11: 1.579 | AZ11: 0.092 | BA11: 0.902 | BB11: 0.746 | BC11: 0.208 | BD11: 0.093 | BE11: 0.612
A12: 2022-01-31 | B12: 0.66 | C12: 0.657 | D12: 0.837 | E12: 0.536 | F12: 0.606 | G12: 0.73 | H12: 0.247 | I12: 0.541 | J12: 14.833 | K12: inf | L12: 14.201 | M12: 1.535 | N12: 0.043 | O12: 0.043 | P12: 0.507 | Q12: 0.73 | R12: 1.936 | S12: -1.059 | T12: 0.714 | U12: 1.071 | V12: 13.468 | W12: 0.733 | X12: 1.24 | Y12: -0.953 | Z12: 0.612 | AA12: 1.094 | AB12: 1.094 | AC12: 3.905 | AD12: -0.81 | AE12: -2.139 | AF12: -1 | AG12: inf | AH12: 0.467 | AJ12: -0.909 | AK12: -3.838 | AL12: 0.461 | AM12: -1 | AN12: 0.461 | AO12: 0.601 | AP12: 0.662 | AQ12: 0.548 | AR12: 0.488 | AS12: 0.355 | AT12: 7.435 | AU12: 9.812 | AV12: 7.578 | AW12: 1.614 | AX12: 0.698 | AY12: 1.152 | AZ12: 0.161 | BA12: 2.516 | BB12: 1.091 | BC12: 0.164 | BD12: 0.408 | BE12: 0.785
A13: 2021-10-31 | B13: 0.688 | C13: 0.707 | D13: 0.656 | E13: 0.553 | F13: 0.577 | G13: 0.774 | H13: -0.227 | I13: 0.25 | J13: 28.666 | K13: inf | L13: 26.247 | M13: 1.076 | N13: 0.051 | O13: 0.051 | P13: 0.669 | Q13: 3.18 | R13: -0.201 | S13: 0.82 | T13: 0.699 | U13: 1.098 | V13: 3.145 | W13: 0.661 | X13: 0.962 | Y13: 1.679 | Z13: 0.718 | AA13: 0.912 | AB13: 0.912 | AC13: 3.289 | AD13: -0.978 | AE13: 7.22 | AF13: 0 | AG13: -0.973 | AH13: 1.771 | AJ13: 11.058 | AK13: -2.155 | AL13: 1.15 | AM13: -1 | AN13: 0.806 | AO13: 0.585 | AP13: 0.742 | AQ13: 0.43 | AR13: 0.761 | AS13: 0.358 | AT13: 10.313 | AU13: 14.467 | AV13: 6.307 | AW13: 1.56 | AX13: 0.915 | AY13: 0.661 | AZ13: -0.59 | BA13: 28.841 | BB13: 1.651 | BC13: 0.159 | BD13: 0.031 | BE13: 0.437
A14: 2021-07-31 | B14: 0.739 | C14: 0.78 | D14: 0.586 | E14: 0.547 | F14: 0.556 | G14: 0.763 | H14: -0.474 | I14: -0.029 | J14: 21.258 | L14: 24.661 | M14: 0.645 | N14: 0.06 | O14: 0.06 | P14: 1.056 | Q14: 2.293 | R14: 27.756 | S14: 11.192 | T14: 0.71 | U14: 1.034 | V14: 4.08 | W14: 0.541 | X14: 0.394 | Y14: 1.176 | Z14: 0.777 | AA14: 0.167 | AB14: 0.167 | AC14: -75.947 | AD14: -0.99 | AE14: -47.205 | AF14: -inf | AG14: -0.944 | AH14: 1.771 | AJ14: 12.237 | AK14: -0.404 | AL14: 1.096 | AM14: -0.997 | AN14: 0.691 | AO14: 0.473 | AP14: 0.741 | AQ14: 0.409 | AR14: 0.654 | AS14: 0.392 | AT14: 28.253 | AU14: 105.976 | AV14: 5.832 | AW14: 1.556 | AX14: 0.811 | AY14: 0.836 | AZ14: -0.756 | BA14: 32.922 | BB14: 1.524 | BC14: 0.149 | BD14: -0.278 | BE14: -0.069
A15: 2021-04-30 | B15: 0.773 | C15: 0.826 | D15: 0.357 | E15: 0.505 | F15: 0.467 | G15: 0.717 | H15: -0.406 | I15: -0.291 | J15: 11.156 | L15: 21.062 | M15: 0.174 | N15: 0.168 | O15: 0.168 | P15: 1.795 | Q15: 0.067 | R15: -0.146 | S15: 5.285 | T15: 0.724 | U15: 0.807 | V15: -2.1 | W15: 0.618 | X15: 0.057 | Y15: -0.254 | Z15: 1.057 | AA15: 0.012 | AB15: 0.012 | AC15: -62.072 | AD15: -0.997 | AE15: -557.507 | AF15: -inf | AG15: -0.994 | AH15: 1.771 | AJ15: 0.115 | AK15: 88.469 | AL15: 1.086 | AM15: -0.997 | AN15: 0.601 | AO15: 0.355 | AP15: 0.698 | AQ15: 0.237 | AR15: 0.56 | AS15: 0.506 | AT15: 16.753 | AU15: 51.232 | AV15: 6.582 | AW15: 1.283 | AX15: 0.678 | AY15: 1.327 | AZ15: -0.815 | BA15: 47.926 | BB15: 1.343 | BC15: 0.133 | BD15: -0.525 | BE15: -0.304
A16: 2021-01-31 | B16: 0.816 | C16: 0.898 | D16: 0.363 | E16: 0.505 | F16: 0.47 | G16: 0.649 | H16: -0.075 | I16: -0.367 | J16: 2.527 | L16: 1.384 | M16: -0.347 | N16: 0.179 | O16: 0.179 | P16: 22.501 | Q16: -0.008 | R16: -2.724 | S16: inf | T16: 0.707 | U16: 0.872 | V16: -1.243 | W16: 0.904 | X16: 0.039 | Y16: 8.376 | Z16: 2.568 | AA16: -0.27 | AB16: -0.27 | AC16: -12.474 | AD16: -0.89 | AE16: -1.787 | AF16: -inf | AG16: -1 | AH16: 1.771 | AJ16: 0.133 | AK16: -26.485 | AL16: 1.752 | AM16: -0.997 | AN16: 0.837 | AO16: 0.374 | AP16: 0.801 | AQ16: 0.366 | AR16: 0.75 | AS16: 0.68 | AT16: 4.867 | AU16: 10.794 | AV16: 7 | AW16: 0.899 | AX16: 0.776 | AY16: 1.054 | AZ16: -0.857 | BA16: inf | BB16: 0.695 | BC16: 0.898 | BD16: -0.573 | BE16: -0.447
A17: 2020-10-31 | B17: 0.859 | C17: 0.952 | D17: 0.444 | E17: 0.519 | F17: 0.5 | G17: 0.65 | H17: 1.274 | I17: -0.262 | J17: 1.205 | L17: 0.123 | M17: -0.295 | N17: 0.22 | O17: 0.22 | P17: -7.419 | Q17: -0.63 | R17: -2.005 | S17: -4.169 | T17: 0.673 | U17: 1.153 | V17: -1.191 | W17: 1.455 | X17: 0.137 | Y17: -0.521 | Z17: 5.208 | AA17: -0.295 | AB17: -0.295 | AC17: -12.711 | AD17: 1.698 | AE17: -0.129 | AF17: -inf | AG17: inf | AH17: inf | AJ17: -0.901 | AK17: 2.288 | AL17: 1.048 | AM17: 0.759 | AN17: 0.994 | AO17: 0.432 | AP17: 0.494 | AQ17: 1.102 | AR17: 0.879 | AS17: 0.774 | AT17: 2.404 | AU17: 4.345 | AV17: inf | AW17: 0.968 | AX17: 0.896 | AY17: 0.101 | AZ17: -0.576 | BA17: inf | BB17: 0.396 | BC17: 1.999 | BD17: -0.42 | BE17: -0.369
A18: 2020-07-31 | B18: 0.864 | C18: 0.96 | D18: 0.461 | E18: 0.503 | F18: 0.493 | G18: 0.602 | H18: 20.247 | I18: -0.184 | J18: 2.6 | L18: 0.061 | M18: -0.254 | N18: 0.257 | O18: 0.257 | P18: -4.029 | Q18: -0.413 | R18: -0.913 | S18: -1.677 | T18: 0.618 | U18: 1.146 | V18: -1.128 | W18: 2.487 | X18: 0.737 | Y18: -0.462 | Z18: 34.053 | AA18: 0.233 | AB18: 0.233 | AC18: -0.151 | AD18: 2.164 | AE18: -1.151 | AG18: inf | AH18: inf | AJ18: -0.912 | AK18: -5.215 | AL18: 2.085 | AM18: 0.904 | AN18: 1.755 | AO18: 0.623 | AP18: 0.75 | AQ18: 1.036 | AR18: 1.451 | AS18: 1.004 | AT18: -0.004 | AU18: -0.873 | AV18: inf | AW18: 1.024 | AX18: 1.365 | AY18: -0.017 | AZ18: 0.004 | BA18: inf | BB18: 0.419 | BC18: 6.256 | BD18: -0.301 | BE18: -0.122
A19: 2020-04-30 | B19: 0.941 | C19: 1.102 | D19: 1.242 | E19: 0.573 | F19: 0.703 | G19: 0.642 | H19: 12.121 | I19: 0.081 | J19: 2.026 | L19: 0.524 | M19: 0.014 | N19: 0.063 | O19: 0.063 | P19: -3.509 | Q19: 5.103 | R19: -2.651 | S19: -2.227 | T19: 0.598 | U19: 3.531 | V19: 1.772 | W19: 1.211 | X19: 1.283 | Y19: -26.114 | Z19: 26.41 | AA19: 0.531 | AB19: 0.531 | AC19: 0.289 | AD19: 3.761 | AE19: -1.019 | AG19: inf | AH19: inf | AJ19: 96.317 | AK19: -1.478 | AL19: 12.794 | AM19: 0.957 | AN19: 4.734 | AO19: 1.219 | AP19: 1.299 | AQ19: 1.709 | AR19: 3.417 | AS19: 1.63 | AT19: 0.309 | AU19: -0.84 | AV19: inf | AW19: 2.281 | AX19: 3.181 | AY19: -0.367 | AZ19: 1.015 | BA19: inf | BB19: 0.581 | BC19: -9.847 | BD19: 0.005 | BE19: 0.171
A20: 2020-01-31 | B20: 1.068 | C20: 1.343 | D20: 1.234 | E20: 0.598 | F20: 0.721 | G20: 0.597 | H20: 14.495 | I20: 0.02 | J20: 1.302 | K20: -1 | L20: 0.342 | M20: -0.048 | N20: 0.327 | O20: 0.327 | P20: -1.31 | Q20: 1.126 | R20: -inf | T20: 1.122 | U20: 3.075 | V20: 3.616 | W20: 1.681 | X20: 1.556 | Y20: -5.024 | Z20: -106.314 | AA20: 1.233 | AB20: 1.233 | AC20: 1.029 | AD20: 5.553 | AE20: 10.477 | AG20: inf | AH20: inf | AJ20: 59.097 | AK20: -1.297 | AL20: 9.836 | AM20: 1.645 | AN20: 4.339 | AO20: 1.24 | AP20: 2.014 | AQ20: 1.131 | AR20: 3.136 | AS20: 2.006 | AT20: 0.283 | AU20: -0.89 | AV20: inf | AW20: 3.064 | AX20: 3.123 | AY20: -0.291 | AZ20: 3.438 | BA20: -1 | BB20: 2.161 | BC20: 11.677 | BD20: -0.072 | BE20: 0.226
A21: 2019-10-31
A22: 2019-07-31
A23: 2019-04-30
A24: 2019-01-31
A25: 2018-10-31
A26: 2018-04-30
A27: 2018-01-31

Sheet Earnings Reports
A1: date | B1: eps | C1: epsEstimated | D1: time | E1: revenue | F1: revenueEstimated | G1: updatedFromDate | H1: fiscalDateEnding
A2: 2025-08-26 | D2: amc | G2: 2024-10-01 | H2: 2025-07-31
A3: 2025-06-02 | D3: amc | G3: 2024-10-01 | H3: 2025-04-30
A4: 2025-03-03 | D4: amc | G4: 2024-10-01 | H4: 2025-01-31
A5: 2024-11-26 | C5: 0.83 | D5: amc | F5: 982360000 | G5: 2024-10-01 | H5: 2024-10-31
A6: 2024-08-28 | B6: 1.04 | C6: 0.988 | D6: amc | E6: 963872000 | F6: 960027920 | G6: 2024-10-01 | H6: 2024-07-31
A7: 2024-06-04 | B7: 0.93 | C7: 0.895 | D7: amc | E7: 921036000 | F7: 904562868 | G7: 2024-09-16 | H7: 2024-04-30
A8: 2024-03-05 | B8: 0.95 | C8: 0.823 | D8: amc | E8: 845335000 | F8: 839125165 | G8: 2024-09-16 | H8: 2024-01-31
A9: 2023-11-28 | B9: 0.82 | C9: 0.74 | D9: amc | E9: 786014000 | F9: 838820000 | G9: 2024-09-16 | H9: 2023-10-31
A10: 2023-08-30 | B10: 0.74 | C10: 0.56 | D10: amc | E10: 731626000 | F10: 724130000 | G10: 2024-09-16 | H10: 2023-07-31
A11: 2023-05-31 | B11: 0.57 | C11: 0.5 | D11: amc | E11: 692580000 | F11: 677370000 | G11: 2024-09-16 | H11: 2023-04-30
A12: 2023-03-07 | B12: 0.47 | C12: 0.43 | D12: amc | E12: 637367000 | F12: 624920000 | G12: 2024-09-16 | H12: 2023-01-31
A13: 2022-11-29 | B13: 0.4 | C13: 0.32 | D13: amc | E13: 580882000 | G13: 2024-09-16 | H13: 2022-10-31
A14: 2022-08-30 | B14: 0.36 | C14: 0.28 | D14: amc | E14: 535153000 | G14: 2024-09-16 | H14: 2022-07-31
A15: 2022-06-02 | B15: 0.31 | C15: 0.23 | D15: amc | E15: 487834000 | F15: 477228912 | G15: 2024-09-16 | H15: 2022-04-30
A16: 2022-03-09 | B16: 0.3 | C16: 0.2 | D16: amc | E16: 431010000 | F16: 410860000 | G16: 2024-09-16 | H16: 2022-01-31
A17: 2021-12-01 | B17: 0.17 | C17: 0.1 | D17: amc | E17: 380051000 | F17: 282187865 | G17: 2024-09-16 | H17: 2021-10-31
A18: 2021-08-31 | B18: 0.11 | C18: 0.09 | D18: amc | E18: 337690000 | F18: 278594250 | G18: 2024-09-16 | H18: 2021-07-31
A19: 2021-06-03 | B19: 0.1 | C19: 0.06 | D19: amc | E19: 302843000 | F19: 249845474 | G19: 2024-09-16 | H19: 2021-04-30
A20: 2021-03-16 | B20: 0.13 | C20: 0.09 | D20: amc | E20: 264929000 | F20: 245887227 | G20: 2024-09-16 | H20: 2021-01-31
A21: 2020-12-02 | B21: 0.08 | D21: amc | E21: 232460000 | G21: 2024-09-16 | H21: 2020-10-31
A22: 2020-09-02 | B22: 0.03 | C22: 0.00499 | D22: amc | E22: 198971000 | F22: 66323666 | G22: 2024-09-16 | H22: 2020-07-31
A23: 2020-06-02 | B23: 0.02 | C23: -0.06 | D23: amc | E23: 178078000 | F23: 534234000 | G23: 2024-09-16 | H23: 2020-04-30
A24: 2020-03-19 | B24: -0.02 | C24: -0.08 | D24: amc | E24: 152109000 | F24: 608436000 | G24: 2024-09-16 | H24: 2020-01-31
A25: 2019-12-05 | B25: -0.07 | C25: -0.12 | D25: amc | E25: 125119000 | F25: 214489714 | G25: 2024-09-16 | H25: 2019-10-31
A26: 2019-09-05 | B26: -0.18 | C26: -0.22 | D26: amc | E26: 108108000 | F26: 138138000 | G26: 2024-09-16 | H26: 2019-07-31
A27: 2019-04-29 | B27: -0.13207 | D27: amc | E27: 96077000 | G27: 2024-09-16 | H27: 2019-04-30
A28: 2019-01-31 | B28: -0.18259 | D28: amc | E28: 80455000 | G28: 2024-09-16 | H28: 2019-01-31
A29: 2018-10-31 | B29: -0.24721 | D29: amc | E29: 66379000 | G29: 2024-09-16 | H29: 2018-10-31
A30: 2018-07-31 | B30: -0.19204 | D30: amc | E30: 55701000 | G30: 2024-09-16 | H30: 2018-07-31
A31: 2018-04-30 | B31: -0.19636 | D31: amc | E31: 47289000 | G31: 2024-09-16 | H31: 2018-04-30
A32: 2018-01-31 | B32: -0.96892 | D32: amc | E32: 38717000 | G32: 2024-09-16 | H32: 2018-01-31

Sheet Employees
A1: periodOfReport | B1: filingDate | C1: acceptanceTime | D1: formType | E1: cik | F1: employeeCount
A2: 2024-01-31 | B2: 2024-03-07 | C2: 2024-03-06 21:07:39 | D2: 10-K | E2: 0001535527 | F2: 7925
A3: 2023-01-31 | B3: 2023-03-09 | C3: 2023-03-08 19:41:08 | D3: 10-K | E3: 0001535527 | F3: 7273
A4: 2022-01-31 | B4: 2022-03-16 | C4: 2022-03-16 16:08:17 | D4: 10-K | E4: 0001535527 | F4: 4965
A5: 2021-01-31 | B5: 2021-03-18 | C5: 2021-03-18 17:02:10 | D5: 10-K | E5: 0001535527 | F5: 3394
A6: 2020-01-31 | B6: 2020-03-23 | C6: 2020-03-23 16:06:34 | D6: 10-K | E6: 0001535527 | F6: 2309

Sheet Revenue Product Seg.
A1: Date | B1: Professional Services | C1: Subscription and Circulation
A2: 2024-07-31 | B2: 45615000 | C2: 918257000
A3: 2024-04-30 | B3: 48864000 | C3: 872172000
A4: 2024-01-31 | B4: 49388000 | C4: 795947000
A5: 2023-10-31 | B5: 52551000 | C5: 733463000
A6: 2023-07-31 | B6: 41654000 | C6: 689972000
A7: 2023-04-30 | B7: 41405000 | C7: 651175000
A8: 2023-01-31 | B8: 39104000 | C8: 598263000
A9: 2022-10-31 | B9: 33506000 | C9: 547376000
A10: 2022-07-31 | B10: 28954000 | C10: 506199000
A11: 2022-04-30 | B11: 28012000 | C11: 459822000
A12: 2022-01-31 | B12: 25567000 | C12: 405443000
A13: 2021-10-31 | B13: 23021000 | C13: 357030000
... A21: 2019-10-31 | B21: 10898000 | C21: 114221000
A22: 2019-07-31 | B22: 10533000
A23: 2019-04-30 | B23: 10087000

Sheet Revenue Geographic Seg.
A1: Date | B1: Asia Pacific | C1: EMEA | D1: Other Countries | E1: UNITED STATES
A2: 2024-07-31 | B2: 98274000 | C2: 148851000 | D2: 61746000 | E2: 655001000
A3: 2024-04-30 | B3: 93462000 | C3: 141612000 | D3: 55936000 | E3: 630026000
A4: 2024-01-31 | B4: 86648000 | C4: 132309000 | D4: 51893000 | E4: 574485000
A5: 2023-10-31 | B5: 81459000 | C5: 119158000 | D5: 47517000 | E5: 537880000
A6: 2023-07-31 | B6: 75198000 | C6: 111909000 | D6: 43655000 | E6: 500864000
A7: 2023-04-30 | B7: 72219000 | C7: 104552000 | D7: 40984000 | E7: 474825000
A8: 2023-01-31 | B8: 65411000 | C8: 94543000 | D8: 36999000 | E8: 440414000
A9: 2022-10-31 | B9: 60011000 | C9: 85665000 | D9: 31904000 | E9: 403302000
A10: 2022-07-31 | B10: 54623000 | C10: 77096000 | D10: 29176000 | E10: 374258000
A11: 2022-04-30 | B11: 48079000 | C11: 70625000 | D11: 23537000 | E11: 345593000
A12: 2022-01-31 | B12: 43423000 | C12: 61278000 | D12: 21003000 | E12: 305306000
A13: 2021-10-31 | B13: 37265000 | C13: 50721000 | D13: 15367000 | E13: 276698000
... A21: 2019-10-31 | B21: 9985000 | C21: 17609000 | D21: 4923000 | E21: 92602000
A22: 2019-07-31 | B22: 8613000 | D22: 4343000
A23: 2019-04-30 | B23: 6230000 | D23: 4126000

Sheet Market Caps
A1: date | B1: marketCap | C1: dateValue
A2: 2019-06-12 | B2: 7545278000 | C2: =A2 -> 2019-06-12
A3: 2019-06-13 | B3: 8788947960 | C3: =A3 -> 2019-06-13
A4: 2019-06-14 | B4: 8346638560 | C4: =A4 -> 2019-06-14
A5: 2019-06-17 | B5: 9107670910 | C5: =A5 -> 2019-06-17
A6: 2019-06-18 | B6: 9951961500 | C6: =A6 -> 2019-06-18
A7: 2019-06-19 | B7: 10045627020 | C7: =A7 -> 2019-06-19
A8: 2019-06-20 | B8: 9737311350 | C8: =A8 -> 2019-06-20
A9: 2019-06-21 | B9: 9396472930 | C9: =A9 -> 2019-06-21
A10: 2019-06-24 | B10: 8842285270 | C10: =A10 -> 2019-06-24
A11: 2019-06-25 | B11: 8003198320 | C11: =A11 -> 2019-06-25
A12: 2019-06-26 | B12: 8150201150 | C12: =A12 -> 2019-06-26
A13: 2019-06-27 | B13: 8232158480 | C13: =A13 -> 2019-06-27
... A1336: 2024-09-30 | B1336: 68460202770 | C1336: =A1336 -> 2024-09-30

Sheet Daily Prices
B1: open | C1: high | D1: low | E1: close | F1: volume | G1: marketCap | H1: Implied Shares | I1: dateValue
A2: 43628 | B2: 63.5 | C2: 67 | D2: 56 | E2: 58 | F2: 19449200 | I2: =A2 -> 43628
A3: 43629 | B3: 63.860001 | C3: 69.669998 | D3: 61.599998 | E3: 67.559998 | F3: 10923900 | I3: =A3 -> 43629
A4: 43630 | B4: 69.779999 | C4: 70.790001 | D4: 63.02 | E4: 64.160004 | F4: 6264200 | I4: =A4 -> 43630
A5: 43633 | B5: 64.75 | C5: 70.010002 | D5: 62 | E5: 70.010002 | F5: 3247500 | I5: =A5 -> 43633
A6: 43634 | B6: 73 | C6: 78.699997 | D6: 71.5 | E6: 76.5 | F6: 6612600 | I6: =A6 -> 43634
A7: 43635 | B7: 78.75 | C7: 79.790001 | D7: 73.555 | E7: 77.220001 | F7: 3319100 | I7: =A7 -> 43635
A8: 43636 | B8: 78 | C8: 78.220001 | D8: 70.690002 | E8: 74.849998 | F8: 3429600 | I8: =A8 -> 43636
A9: 43637 | B9: 72.459999 | C9: 73.928001 | D9: 68.300003 | E9: 72.230003 | F9: 2657500 | I9: =A9 -> 43637
A10: 43640 | B10: 71.050003 | C10: 72.389999 | D10: 65.080002 | E10: 67.970001 | F10: 2448000 | I10: =A10 -> 43640
A11: 43641 | B11: 67.099998 | C11: 68.989998 | D11: 61.169998 | E11: 61.52 | F11: 2480200 | I11: =A11 -> 43641
A12: 43642 | B12: 63.299999 | C12: 64.919998 | D12: 62.005001 | E12: 62.650002 | F12: 1625500 | I12: =A12 -> 43642
A13: 43643 | B13: 63.389999 | C13: 64.995003 | D13: 62.570999 | E13: 63.279999 | F13: 914500 | I13: =A13 -> 43643
... A28: 43665 | B28: 85.160004 | C28: 85.849998 | D28: 80.75 | E28: 83.519997 | F28: 13669000 | I28: =A28 -> 43665
A29: 43668 | B29: 82.269997 | C29: 88.5 | D29: 82.080002 | E29: 87.68 | F29: 5357700 | G29: 11406378880 | H29: 130091000 | I29: =A29 -> 43668
A30: 43669 | B30: 88.32 | C30: 89.440002 | D30: 84.489998 | E30: 86.739998 | F30: 2529800 | G30: 11284093340 | H30: 130091003 | I30: =A30 -> 43669
A31: 43670 | B31: 86.790001 | C31: 87.849998 | D31: 85.5 | E31: 87.459999 | F31: 1250700 | G31: 11377758860 | H31: 130091001 | I31: =A31 -> 43670
A32: 43671 | B32: 87.5 | C32: 93.338997 | D32: 87 | E32: 92.279999 | F32: 3270400 | G32: 12004797480 | H32: 130091002 | I32: =A32 -> 43671
A33: 43672 | B33: 93.040001 | C33: 95.5 | D33: 91.910004 | E33: 92.879997 | F33: 2053000 | G33: 12082852080 | H33: 130091004 | I33: =A33 -> 43672
A34: 43675 | B34: 93.690002 | C34: 93.900002 | D34: 82.650002 | E34: 87.230003 | F34: 3317800 | G34: 11347837930 | H34: 130090995 | I34: =A34 -> 43675
A35: 43676 | B35: 86 | C35: 96.190002 | D35: 84 | E35: 94 | F35: 3127200 | G35: 12228554000 | H35: 130091000 | I35: =A35 -> 43676
A36: 43677 | B36: 93.949997 | C36: 94.801003 | D36: 86.817001 | E36: 89.07 | F36: 2476000 | G36: 18178830720 | H36: 204096001 | I36: =A36 -> 43677
A37: 43678 | B37: 90.07 | C37: 94.32 | D37: 89.439003 | E37: 91.529999 | F37: 2238200 | G37: 18680906880 | H37: 204096003 | I37: =A37 -> 43678
A38: 43679 | B38: 91.540001 | C38: 92.779999 | D38: 86.910004 | E38: 88.010002 | F38: 1801000 | G38: 17962488960 | H38: 204095995 | I38: =A38 -> 43679
A39: 43682 | B39: 83.339996 | C39: 86.919998 | D39: 82.25 | E39: 85.480003 | F39: 2196400 | G39: 17446126080 | H39: 204095992 | I39: =A39 -> 43682
A40: 43683 | B40: 87.199997 | C40: 89.760002 | D40: 82.709999 | E40: 85.239998 | F40: 1357400 | G40: 17397143040 | H40: 204096005 | I40: =A40 -> 43683
... A1335: 45562 | B1335: 283.79999 | C1335: 286.45001 | D1335: 281.14999 | E1335: 285.85999 | F1335: 2896400 | G1335: 69775853260 | H1335: 244091013 | I1335: =A1335 -> 45562

Sheet Relative Valuations
B1: date | C1: marketCap | D1: fiscalDateEnding | E1: time | F1: revenue | G1: EBITDA | H1: freeCashFlow | I1: FCFsimple | J1: operatingIncome | K1: netIncome | L1: P/S | M1: P/EBITDA | N1: P/FCF | O1: P/FCFsimple | P1: P/OpIncome | Q1: P/E
A2: 0 | B2: 43628 | C2: 7545278000 | D2: 43585 | E2: amc | F2: 290200000 | G2: -115443000 | H2: -46066000 | I2: -168700000 | J2: -132212000 | K2: -133177000 | L2: 26.000269 | M2: -65.359338 | N2: -163.79278 | O2: -44.726011 | P2: -57.06954 | Q2: -56.656014
A3: 1 | B3: 43629 | C3: 8788947960 | D3: 43585 | E3: amc | F3: 290200000 | G3: -115443000 | H3: -46066000 | I3: -168700000 | J3: -132212000 | K3: -133177000 | L3: 30.28583 | M3: -76.132359 | N3: -190.79034 | O3: -52.098091 | P3: -66.476174 | Q3: -65.994488
A4: 2 | B4: 43630 | C4: 8346638560 | D4: 43585 | E4: amc | F4: 290200000 | G4: -115443000 | H4: -46066000 | I4: -168700000 | J4: -132212000 | K4: -133177000 | L4: 28.761677 | M4: -72.30095 | N4: -181.1887 | O4: -49.476221 | P4: -63.130719 | Q4: -62.673274
A5: 3 | B5: 43633 | C5: 9107670910 | D5: 43585 | E5: amc | F5: 290200000 | G5: -115443000 | H5: -46066000 | I5: -168700000 | J5: -132212000 | K5: -133177000 | L5: 31.384118 | M5: -78.893228 | N5: -197.70918 | O5: -53.987379 | P5: -68.88687 | Q5: -68.387716
A6: 4 | B6: 43634 | C6: 9951961500 | D6: 43585 | E6: amc | F6: 290200000 | G6: -115443000 | H6: -46066000 | I6: -168700000 | J6: -132212000 | K6: -133177000 | L6: 34.293458 | M6: -86.206712 | N6: -216.03702 | O6: -58.992066 | P6: -75.272755 | Q6: -74.727329
A7: 5 | B7: 43635 | C7: 10045627020 | D7: 43585 | E7: amc | F7: 290200000 | G7: -115443000 | H7: -46066000 | I7: -168700000 | J7: -132212000 | K7: -133177000 | L7: 34.61622 | M7: -87.01807 | N7: -218.07031 | O7: -59.547285 | P7: -75.981205 | Q7: -75.430645
A8: 6 | B8: 43636 | C8: 9737311350 | D8: 43585 | E8: amc | F8: 290200000 | G8: -115443000 | H8: -46066000 | I8: -168700000 | J8: -132212000 | K8: -133177000 | L8: 33.553795 | M8: -84.347352 | N8: -211.3774 | O8: -57.719688 | P8: -73.649225 | Q8: -73.115563
A9: 7 | B9: 43637 | C9: 9396472930 | D9: 43585 | E9: amc | F9: 290200000 | G9: -115443000 | H9: -46066000 | I9: -168700000 | J9: -132212000 | K9: -133177000 | L9: 32.3793 | M9: -81.394913 | N9: -203.97849 | O9: -55.699306 | P9: -71.071256 | Q9: -70.556274
A10: 8 | B10: 43640 | C10: 8842285270 | D10: 43585 | E10: amc | F10: 290200000 | G10: -115443000 | H10: -46066000 | I10: -168700000 | J10: -132212000 | K10: -133177000 | L10: 30.469625 | M10: -76.594382 | N10: -191.94819 | O10: -52.414258 | P10: -66.879597 | Q10: -66.394988
A11: 9 | B11: 43641 | C11: 8003198320 | D11: 43585 | E11: amc | F11: 290200000 | G11: -115443000 | H11: -46066000 | I11: -168700000 | J11: -132212000 | K11: -133177000 | L11: 27.578216 | M11: -69.325973 | N11: -173.7333 | O11: -47.440417 | P11: -60.533071 | Q11: -60.094448
A12: 10 | B12: 43642 | C12: 8150201150 | D12: 43585 | E12: amc | F12: 290200000 | G12: -115443000 | H12: -46066000 | I12: -168700000 | J12: -132212000 | K12: -133177000 | L12: 28.084773 | M12: -70.599353 | N12: -176.92444 | O12: -48.311803 | P12: -61.644943 | Q12: -61.198264
A13: 11 | B13: 43643 | C13: 8232158480 | D13: 43585 | E13: amc | F13: 290200000 | G13: -115443000 | H13: -46066000 | I13: -168700000 | J13: -132212000 | K13: -133177000 | L13: 28.36719 | M13: -71.309291 | N13: -178.70357 | O13: -48.79762 | P13: -62.264836 | Q13: -61.813665
... A1336: 1334 | B1336: 45565 | C1336: 68460202770 | D1336: 45504 | E1336: amc | F1336: 3516257000 | G1336: 237418000 | H1336: 1108515000 | I1336: 15530000 | J1336: 55356000 | K1336: 170197000 | L1336: 19.469624 | M1336: 288.35304 | N1336: 61.758481 | O1336: 4408.2552 | P1336: 1236.726 | Q1336: 402.24095

Sheet CAPM
B1: CRWD
A2: Total Liabilities | B2: 4311884000
A3: Long-Term Debt | B3: 743238000
A4: % Debt | B4: 0.20453307
A5: Cost of Debt | B5: 0.026948299
A6: Tax Rate | B6: 0.21
A7: Total Equity | B7: 2890590000
A8: % Equity | B8: 0.79546693
A9: CAPM | B9: 0.12261449
A10: Risk-Free Rate | B10: 0.03737
A11: Beta | B11: 1.1736816
A12: Market Risk Premium | B12: 0.07263
A13: WACC | B13: 0.48378218

Sheet Beta Analysis
B1: Years | C1: Timing Standard | D1: Beta | E1: CAPM
A2: 0 | B2: 3 | C2: M | D2: 0.8909862 | E2: 0.10208233
A3: 1 | B3: 3 | C3: W | D3: 1.7106002 | E3: 0.16161089
A4: 2 | B4: 3 | C4: D | D4: 1.670814 | E4: 0.15872122
A5: 3 | B5: 5 | C5: M | D5: 1.108589 | E5: 0.11788682
A6: 4 | B6: 5 | C6: W | D6: 1.0860606 | E6: 0.11625058
A7: 5 | B7: 5 | C7: D | D7: 1.1736816 | E7: 0.12261449
A8: 6 | B8: Mean | D8: 1.2734553 | E8: 0.12986106
A9: 7 | B9: Median | D9: 1.1411353 | E9: 0.12025065

Sheet Recons
B1: date | C1: marketCap | D1: dateValue | E1: Daily Prices marketCap | I1: Market Caps | L1: Daily Prices and Relative Valuations are reconciled
A2: 0 | B2: 43628 | C2: 7545278000 | D2: =B2 -> 43628 | E2: =INDEX('Daily Prices'!$A$1:$I$1335,MATCH(Recons!$D2,'Daily Prices'!$I$1:$I$1335,0),MATCH(Recons!C$1,'Daily Prices'!$A$1:$I$1,0)) -> 0 | G2: 7545278000 | H2: =C2-G2 -> 0 | I2: =INDEX('Market Caps'!$A$1:$C$1336,MATCH(Recons!$D2,'Market Caps'!$C$1:$C$1336,0),MATCH(Recons!C$1,'Market Caps'!$A$1:$C$1,0)) -> #N/A
A3: 1 | B3: 43629 | C3: 8788947960 | D3: =B3 -> 43629 | E3: =INDEX('Daily Prices'!$A$1:$I$1335,MATCH(Recons!$D3,'Daily Prices'!$I$1:$I$1335,0),MATCH(Recons!C$1,'Daily Prices'!$A$1:$I$1,0)) -> 0 | G3: 8788947960 | H3: =C3-G3 -> 0 | I3: =INDEX('Market Caps'!$A$1:$B$1336,MATCH(Recons!$D3,'Market Caps'!$A$1:$A$1336,0),MATCH(Recons!C$1,'Market Caps'!$A$1:$B$1,0)) -> #N/A
A4: 2 | B4: 43630 | C4: 8346638560 | D4: =B4 -> 43630 | E4: =INDEX('Daily Prices'!$A$1:$I$1335,MATCH(Recons!$D4,'Daily Prices'!$I$1:$I$1335,0),MATCH(Recons!C$1,'Daily Prices'!$A$1:$I$1,0)) -> 0 | G4: 8346638560 | H4: =C4-G4 -> 0 | I4: =INDEX('Market Caps'!$A$1:$B$1336,MATCH(Recons!$D4,'Market Caps'!$A$1:$A$1336,0),MATCH(Recons!C$1,'Market Caps'!$A$1:$B$1,0)) -> #N/A | L4: weightedAverageShsOut | M4: weightedAverageShsOutDil
A5: 3 | B5: 43633 | C5: 9107670910 | D5: =B5 -> 43633 | E5: =INDEX('Daily Prices'!$A$1:$I$1335,MATCH(Recons!$D5,'Daily Prices'!$I$1:$I$1335,0),MATCH(Recons!C$1,'Daily Prices'!$A$1:$I$1,0)) -> 0 | G5: 9107670910 | H5: =C5-G5 -> 0 | I5: =INDEX('Market Caps'!$A$1:$B$1336,MATCH(Recons!$D5,'Market Caps'!$A$1:$A$1336,0),MATCH(Recons!C$1,'Market Caps'!$A$1:$B$1,0)) -> #N/A | L5: 244091000 | M5: 251265000
A6: 4 | B6: 43634 | C6: 9951961500 | D6: =B6 -> 43634 | E6: =INDEX('Daily Prices'!$A$1:$I$1335,MATCH(Recons!$D6,'Daily Prices'!$I$1:$I$1335,0),MATCH(Recons!C$1,'Daily Prices'!$A$1:$I$1,0)) -> 0 | G6: 9951961500 | H6: =C6-G6 -> 0
A7: 5 | B7: 43635 | C7: 10045627020 | D7: =B7 -> 43635 | E7: =INDEX('Daily Prices'!$A$1:$I$1335,MATCH(Recons!$D7,'Daily Prices'!$I$1:$I$1335,0),MATCH(Recons!C$1,'Daily Prices'!$A$1:$I$1,0)) -> 0 | G7: 10045627020 | H7: =C7-G7 -> 0
A8: 6 | B8: 43636 | C8: 9737311350 | D8: =B8 -> 43636 | E8: =INDEX('Daily Prices'!$A$1:$I$1335,MATCH(Recons!$D8,'Daily Prices'!$I$1:$I$1335,0),MATCH(Recons!C$1,'Daily Prices'!$A$1:$I$1,0)) -> 0 | G8: 9737311350 | H8: =C8-G8 -> 0
A9: 7 | B9: 43637 | C9: 9396472930 | D9: =B9 -> 43637 | E9: =INDEX('Daily Prices'!$A$1:$I$1335,MATCH(Recons!$D9,'Daily Prices'!$I$1:$I$1335,0),MATCH(Recons!C$1,'Daily Prices'!$A$1:$I$1,0)) -> 0 | G9: 9396472930 | H9: =C9-G9 -> 0
A10: 8 | B10: 43640 | C10: 8842285270 | D10: =B10 -> 43640 | E10: =INDEX('Daily Prices'!$A$1:$I$1335,MATCH(Recons!$D10,'Daily Prices'!$I$1:$I$1335,0),MATCH(Recons!C$1,'Daily Prices'!$A$1:$I$1,0)) -> 0 | G10: 8842285270 | H10: =C10-G10 -> 0
A11: 9 | B11: 43641 | C11: 8003198320 | D11: =B11 -> 43641 | E11: =INDEX('Daily Prices'!$A$1:$I$1335,MATCH(Recons!$D11,'Daily Prices'!$I$1:$I$1335,0),MATCH(Recons!C$1,'Daily Prices'!$A$1:$I$1,0)) -> 0 | G11: 8003198320 | H11: =C11-G11 -> 0
A12: 10 | B12: 43642 | C12: 8150201150 | D12: =B12 -> 43642 | E12: =INDEX('Daily Prices'!$A$1:$I$1335,MATCH(Recons!$D12,'Daily Prices'!$I$1:$I$1335,0),MATCH(Recons!C$1,'Daily Prices'!$A$1:$I$1,0)) -> 0 | G12: 8150201150 | H12: =C12-G12 -> 0
A13: 11 | B13: 43643 | C13: 8232158480 | D13: =B13 -> 43643 | E13: =INDEX('Daily Prices'!$A$1:$I$1335,MATCH(Recons!$D13,'Daily Prices'!$I$1:$I$1335,0),MATCH(Recons!C$1,'Daily Prices'!$A$1:$I$1,0)) -> 0 | G13: 8232158480 | H13: =C13-G13 -> 0
A14: 12 | B14: 43644 | C14: 8883914390 | D14: =B14 -> 43644 | E14: =INDEX('Daily Prices'!$A$1:$I$1335,MATCH(Recons!$D14,'Daily Prices'!$I$1:$I$1335,0),MATCH(Recons!C$1,'Daily Prices'!$A$1:$I$1,0)) -> 0 | G14: 8883914390 | H14: =C14-G14 -> 0
A15: 13 | B15: 43647 | C15: 8221751200 | D15: =B15 -> 43647 | E15: =INDEX('Daily Prices'!$A$1:$I$1335,MATCH(Recons!$D15,'Daily Prices'!$I$1:$I$1335,0),MATCH(Recons!C$1,'Daily Prices'!$A$1:$I$1,0)) -> 0 | G15: 8221751200 | H15: =C15-G15 -> 0
A16: 14 | B16: 43648 | C16: 8393471319 | D16: =B16 -> 43648 | E16: =INDEX('Daily Prices'!$A$1:$I$1335,MATCH(Recons!$D16,'Daily Prices'!$I$1:$I$1335,0),MATCH(Recons!C$1,'Daily Prices'!$A$1:$I$1,0)) -> 0 | G16: 8393471319 | H16: =C16-G16 -> 0
A17: 15 | B17: 43649 | C17: 8747318840 | D17: =B17 -> 43649 | E17: =INDEX('Daily Prices'!$A$1:$I$1335,MATCH(Recons!$D17,'Daily Prices'!$I$1:$I$1335,0),MATCH(Recons!C$1,'Daily Prices'!$A$1:$I$1,0)) -> 0 | G17: 8747318840 | H17: =C17-G17 -> 0
... A28: 26 | B28: 43665 | C28: 10865200320 | D28: =B28 -> 43665 | E28: =INDEX('Daily Prices'!$A$1:$I$1335,MATCH(Recons!$D28,'Daily Prices'!$I$1:$I$1335,0),MATCH(Recons!C$1,'Daily Prices'!$A$1:$I$1,0)) -> 0 | G28: 10865200320 | H28: =C28-G28 -> 0
A29: 27 | B29: 43668 | C29: 11406378880 | D29: =B29 -> 43668 | E29: =INDEX('Daily Prices'!$A$1:$I$1335,MATCH(Recons!$D29,'Daily Prices'!$I$1:$I$1335,0),MATCH(Recons!C$1,'Daily Prices'!$A$1:$I$1,0)) -> 11406378880 | F29: =C29-E29 -> 0 | G29: 11406378880 | H29: =C29-G29 -> 0
A30: 28 | B30: 43669 | C30: 11284093340 | D30: =B30 -> 43669 | E30: =INDEX('Daily Prices'!$A$1:$I$1335,MATCH(Recons!$D30,'Daily Prices'!$I$1:$I$1335,0),MATCH(Recons!C$1,'Daily Prices'!$A$1:$I$1,0)) -> 11284093340 | F30: =C30-E30 -> 0 | G30: 11284093340 | H30: =C30-G30 -> 0
A31: 29 | B31: 43670 | C31: 11377758860 | D31: =B31 -> 43670 | E31: =INDEX('Daily Prices'!$A$1:$I$1335,MATCH(Recons!$D31,'Daily Prices'!$I$1:$I$1335,0),MATCH(Recons!C$1,'Daily Prices'!$A$1:$I$1,0)) -> 11377758860 | F31: =C31-E31 -> 0 | G31: 11377758860 | H31: =C31-G31 -> 0
A32: 30 | B32: 43671 | C32: 12004797480 | D32: =B32 -> 43671 | E32: =INDEX('Daily Prices'!$A$1:$I$1335,MATCH(Recons!$D32,'Daily Prices'!$I$1:$I$1335,0),MATCH(Recons!C$1,'Daily Prices'!$A$1:$I$1,0)) -> 12004797480 | F32: =C32-E32 -> 0 | G32: 12004797480 | H32: =C32-G32 -> 0
A33: 31 | B33: 43672 | C33: 12082852080 | D33: =B33 -> 43672 | E33: =INDEX('Daily Prices'!$A$1:$I$1335,MATCH(Recons!$D33,'Daily Prices'!$I$1:$I$1335,0),MATCH(Recons!C$1,'Daily Prices'!$A$1:$I$1,0)) -> 12082852080 | F33: =C33-E33 -> 0 | G33: 12082852080 | H33: =C33-G33 -> 0
A34: 32 | B34: 43675 | C34: 11347837930 | D34: =B34 -> 43675 | E34: =INDEX('Daily Prices'!$A$1:$I$1335,MATCH(Recons!$D34,'Daily Prices'!$I$1:$I$1335,0),MATCH(Recons!C$1,'Daily Prices'!$A$1:$I$1,0)) -> 11347837930 | F34: =C34-E34 -> 0 | G34: 11347837930 | H34: =C34-G34 -> 0
A35: 33 | B35: 43676 | C35: 12228554000 | D35: =B35 -> 43676 | E35: =INDEX('Daily Prices'!$A$1:$I$1335,MATCH(Recons!$D35,'Daily Prices'!$I$1:$I$1335,0),MATCH(Recons!C$1,'Daily Prices'!$A$1:$I$1,0)) -> 12228554000 | F35: =C35-E35 -> 0 | G35: 12228554000 | H35: =C35-G35 -> 0
A36: 34 | B36: 43677 | C36: 18178830720 | D36: =B36 -> 43677 | E36: =INDEX('Daily Prices'!$A$1:$I$1335,MATCH(Recons!$D36,'Daily Prices'!$I$1:$I$1335,0),MATCH(Recons!C$1,'Daily Prices'!$A$1:$I$1,0)) -> 18178830720 | F36: =C36-E36 -> 0 | G36: 18178830720 | H36: =C36-G36 -> 0
A37: 35 | B37: 43678 | C37: 18680906880 | D37: =B37 -> 43678 | E37: =INDEX('Daily Prices'!$A$1:$I$1335,MATCH(Recons!$D37,'Daily Prices'!$I$1:$I$1335,0),MATCH(Recons!C$1,'Daily Prices'!$A$1:$I$1,0)) -> 18680906880 | F37: =C37-E37 -> 0 | G37: 18680906880 | H37: =C37-G37 -> 0
A38: 36 | B38: 43679 | C38: 17962488960 | D38: =B38 -> 43679 | E38: =INDEX('Daily Prices'!$A$1:$I$1335,MATCH(Recons!$D38,'Daily Prices'!$I$1:$I$1335,0),MATCH(Recons!C$1,'Daily Prices'!$A$1:$I$1,0)) -> 17962488960 | F38: =C38-E38 -> 0 | G38: 17962488960 | H38: =C38-G38 -> 0
A39: 37 | B39: 43682 | C39: 17446126080 | D39: =B39 -> 43682 | E39: =INDEX('Daily Prices'!$A$1:$I$1335,MATCH(Recons!$D39,'Daily Prices'!$I$1:$I$1335,0),MATCH(Recons!C$1,'Daily Prices'!$A$1:$I$1,0)) -> 17446126080 | F39: =C39-E39 -> 0 | G39: 17446126080 | H39: =C39-G39 -> 0
A40: 38 | B40: 43683 | C40: 17397143040 | D40: =B40 -> 43683 | E40: =INDEX('Daily Prices'!$A$1:$I$1335,MATCH(Recons!$D40,'Daily Prices'!$I$1:$I$1335,0),MATCH(Recons!C$1,'Daily Prices'!$A$1:$I$1,0)) -> 17397143040 | F40: =C40-E40 -> 0 | G40: 17397143040 | H40: =C40-G40 -> 0
... A1335: 1333 | B1335: 45562 | C1335: 69775853260 | D1335: =B1335 -> 45562 | E1335: =INDEX('Daily Prices'!$A$1:$I$1335,MATCH(Recons!$D1335,'Daily Prices'!$I$1:$I$1335,0),MATCH(Recons!C$1,'Daily Prices'!$A$1:$I$1,0)) -> 69775853260 | F1335: =C1335-E1335 -> 0 | G1335: 69775853260 | H1335: =C1335-G1335 -> 0
A1336: 1334 | B1336: 45565 | C1336: 68460202770 | D1336: =B1336 -> 45565 | E1336: =INDEX('Daily Prices'!$A$1:$I$1335,MATCH(Recons!$D1336,'Daily Prices'!$I$1:$I$1335,0),MATCH(Recons!C$1,'Daily Prices'!$A$1:$I$1,0)) -> #N/A | F1336: =C1336-E1336 -> #N/A | G1336: 68460202770 | H1336: =C1336-G1336 -> 0 | J1336: 280.24 | K1336: =J1336*L5 -> 68404061840 | L1336: =J1336*M5 -> 70414503600 | M1336: =J1336*((L5+M5)/2) -> 69409282720
