Workbook

Sheet __FDSCACHE__
B1: This sheet contains FactSet XML data for use with this workbook's =FDS codes. Modifying the worksheet's contents may damage the workbook's =FDS functionality.

Sheet WACC
B1: MDB
A2: Total Liabilities | B2: 1768183000
A3: Long-Term Debt | B3: 1144977000
A4: % Debt | B4: 0.45652554
A5: Cost of Debt | B5: 0.0040472429
A6: Tax Rate | B6: 0.21
A7: Total Equity | B7: 1363047000
A8: % Equity | B8: 0.54347446
A9: CAPM | B9: 0.14059346
A10: Risk-Free Rate | B10: 0.04073
A11: Beta | B11: 1.4416552
A12: Market Risk Premium | B12: 0.06927
A13: Terminal Growth Rate | B13: 0.02
A14: WACC | B14: 0.077868613

Sheet DCF_Simple
D1: =Python!A31 -> 2017-07-31 | E1: =Python!A27 -> 2018-07-31 | F1: =Python!A23 -> 2019-07-31 | G1: =Python!A19 -> 2020-07-31 | H1: =Python!A15 -> 2021-07-31 | I1: =Python!A11 -> 2022-07-31 | J1: =Python!A7 -> 2023-07-31 | K1: =Python!A3 -> 2024-07-31 | L1: =EDATE(K1, 12) -> 45869 | M1: =EDATE(L1, 12) -> 46234 | N1: =EDATE(M1, 12) -> 46599 | O1: =EDATE(N1, 12) -> 46965 | P1: =EDATE(O1, 12) -> 47330 | Q1: =EDATE(P1, 12) -> 47695 | R1: =EDATE(Q1, 12) -> 48060 | S1: =EDATE(R1, 12) -> 48426 | ... U1: =EDATE(T1, 12) -> 49156
B3: Figures in millions | D3: =YEAR(D1) -> 2017 | E3: =YEAR(E1) -> 2018 | F3: =YEAR(F1) -> 2019 | G3: =YEAR(G1) -> 2020 | H3: =YEAR(H1) -> 2021 | I3: =YEAR(I1) -> 2022 | J3: =YEAR(J1) -> 2023 | K3: =YEAR(K1) -> 2024 | ... U3: =YEAR(U1) -> 2034 | V3: Terminal
B4: Revenue | D4: =IFERROR(INDEX(Python!$1:$1048576,MATCH(DCF_Simple!D$1,Python!$A:$A,0),MATCH(DCF_Simple!$B4,Python!$1:$1,0))/1000000,0) -> 124.229 | E4: =IFERROR(INDEX(Python!$1:$1048576,MATCH(DCF_Simple!E$1,Python!$A:$A,0),MATCH(DCF_Simple!$B4,Python!$1:$1,0))/1000000,0) -> 192.241 | F4: =IFERROR(INDEX(Python!$1:$1048576,MATCH(DCF_Simple!F$1,Python!$A:$A,0),MATCH(DCF_Simple!$B4,Python!$1:$1,0))/1000000,0) -> 339.225 | G4: =IFERROR(INDEX(Python!$1:$1048576,MATCH(DCF_Simple!G$1,Python!$A:$A,0),MATCH(DCF_Simple!$B4,Python!$1:$1,0))/1000000,0) -> 501.574 | H4: =IFERROR(INDEX(Python!$1:$1048576,MATCH(DCF_Simple!H$1,Python!$A:$A,0),MATCH(DCF_Simple!$B4,Python!$1:$1,0))/1000000,0) -> 702.165 | I4: =IFERROR(INDEX(Python!$1:$1048576,MATCH(DCF_Simple!I$1,Python!$A:$A,0),MATCH(DCF_Simple!$B4,Python!$1:$1,0))/1000000,0) -> 1082.494 | J4: =IFERROR(INDEX(Python!$1:$1048576,MATCH(DCF_Simple!J$1,Python!$A:$A,0),MATCH(DCF_Simple!$B4,Python!$1:$1,0))/1000000,0) -> 1487.004 | K4: =IFERROR(INDEX(Python!$1:$1048576,MATCH(DCF_Simple!K$1,Python!$A:$A,0),MATCH(DCF_Simple!$B4,Python!$1:$1,0))/1000000,0) -> 1819.61 | L4: =K4*(1+L5) -> 2092.0526 | M4: =L4*(1+M5) -> 2405.2869 | N4: =M4*(1+N5) -> 2765.4205 | O4: =N4*(1+O5) -> 3179.4754 | P4: =O4*(1+P5) -> 3655.5249 | Q4: =P4*(1+Q5) -> 4202.8514 | R4: =Q4*(1+R5) -> 4832.1268 | S4: =R4*(1+S5) -> 5555.621 | ... U4: =T4*(1+U5) -> 7343.8059 | V4: =U4 -> 7343.8059
B5: Growth (y/y) | E5: =IFERROR(E4/D4-1,"") -> 0.54747281 | F5: =IFERROR(F4/E4-1,"") -> 0.76458196 | G5: =IFERROR(G4/F4-1,"") -> 0.47858796 | H5: =IFERROR(H4/G4-1,"") -> 0.39992304 | I5: =IFERROR(I4/H4-1,"") -> 0.54165189 | J5: =IFERROR(J4/I4-1,"") -> 0.37368336 | K5: =IFERROR(K4/J4-1,"") -> 0.22367526 | L5: =Python!F2 -> 0.14972583 | M5: =L5 -> 0.14972583 | N5: =M5 -> 0.14972583 | O5: =N5 -> 0.14972583 | P5: =O5 -> 0.14972583 | Q5: =P5 -> 0.14972583 | R5: =Q5 -> 0.14972583 | S5: =R5 -> 0.14972583 | T5: =S5 -> 0.14972583 | U5: =T5 -> 0.14972583
B7: Free Cash Flow (FCF) | D7: =IFERROR(INDEX(Python!$1:$1048576,MATCH(DCF_Simple!D$1,Python!$A:$A,0),MATCH(DCF_Simple!$B7,Python!$1:$1,0))/1000000,0) -> -45.301 | E7: =IFERROR(INDEX(Python!$1:$1048576,MATCH(DCF_Simple!E$1,Python!$A:$A,0),MATCH(DCF_Simple!$B7,Python!$1:$1,0))/1000000,0) -> -44.983 | F7: =IFERROR(INDEX(Python!$1:$1048576,MATCH(DCF_Simple!F$1,Python!$A:$A,0),MATCH(DCF_Simple!$B7,Python!$1:$1,0))/1000000,0) -> -33.35 | G7: =IFERROR(INDEX(Python!$1:$1048576,MATCH(DCF_Simple!G$1,Python!$A:$A,0),MATCH(DCF_Simple!$B7,Python!$1:$1,0))/1000000,0) -> -43.333 | H7: =IFERROR(INDEX(Python!$1:$1048576,MATCH(DCF_Simple!H$1,Python!$A:$A,0),MATCH(DCF_Simple!$B7,Python!$1:$1,0))/1000000,0) -> -45.115 | I7: =IFERROR(INDEX(Python!$1:$1048576,MATCH(DCF_Simple!I$1,Python!$A:$A,0),MATCH(DCF_Simple!$B7,Python!$1:$1,0))/1000000,0) -> -27.468 | J7: =IFERROR(INDEX(Python!$1:$1048576,MATCH(DCF_Simple!J$1,Python!$A:$A,0),MATCH(DCF_Simple!$B7,Python!$1:$1,0))/1000000,0) -> 45.205 | K7: =IFERROR(INDEX(Python!$1:$1048576,MATCH(DCF_Simple!K$1,Python!$A:$A,0),MATCH(DCF_Simple!$B7,Python!$1:$1,0))/1000000,0) -> 148.858 | L7: =L8*L4 -> 117.3722 | M7: =M8*M4 -> 134.94585 | N7: =N8*N4 -> 155.15073 | O7: =O8*O4 -> 178.3808 | P7: =P8*P4 -> 205.08901 | Q7: =Q8*Q4 -> 235.79613 | R7: =R8*R4 -> 271.1009 | S7: =S8*S4 -> 311.69171 | ... U7: =U8*U4 -> 412.01576 | V7: =U7 -> 412.01576
B8: FCF Margin | D8: =IFERROR(D7/D$4,"") -> -0.36465721 | E8: =IFERROR(E7/E$4,"") -> -0.23399275 | F8: =IFERROR(F7/F$4,"") -> -0.09831233 | G8: =IFERROR(G7/G$4,"") -> -0.086394032 | H8: =IFERROR(H7/H$4,"") -> -0.06425128 | I8: =IFERROR(I7/I$4,"") -> -0.025374736 | J8: =IFERROR(J7/J$4,"") -> 0.030400053 | K8: =IFERROR(K7/K$4,"") -> 0.08180764 | L8: =AVERAGE(J8:K8) -> 0.056103846 | M8: =L8 -> 0.056103846 | N8: =M8 -> 0.056103846 | O8: =N8 -> 0.056103846 | P8: =O8 -> 0.056103846 | Q8: =P8 -> 0.056103846 | R8: =Q8 -> 0.056103846 | S8: =R8 -> 0.056103846 | T8: =S8 -> 0.056103846 | U8: =T8 -> 0.056103846
B10: Shares Outstanding, Diluted | D10: =IFERROR(INDEX(Python!$1:$1048576,MATCH(DCF_Simple!D$1,Python!$A:$A,0),MATCH(DCF_Simple!$B10,Python!$1:$1,0))/1000000,0) -> 48.968305 | E10: =IFERROR(INDEX(Python!$1:$1048576,MATCH(DCF_Simple!E$1,Python!$A:$A,0),MATCH(DCF_Simple!$B10,Python!$1:$1,0))/1000000,0) -> 51.185258 | F10: =IFERROR(INDEX(Python!$1:$1048576,MATCH(DCF_Simple!F$1,Python!$A:$A,0),MATCH(DCF_Simple!$B10,Python!$1:$1,0))/1000000,0) -> 55.647707 | G10: =IFERROR(INDEX(Python!$1:$1048576,MATCH(DCF_Simple!G$1,Python!$A:$A,0),MATCH(DCF_Simple!$B10,Python!$1:$1,0))/1000000,0) -> 58.393894 | H10: =IFERROR(INDEX(Python!$1:$1048576,MATCH(DCF_Simple!H$1,Python!$A:$A,0),MATCH(DCF_Simple!$B10,Python!$1:$1,0))/1000000,0) -> 63.426694 | I10: =IFERROR(INDEX(Python!$1:$1048576,MATCH(DCF_Simple!I$1,Python!$A:$A,0),MATCH(DCF_Simple!$B10,Python!$1:$1,0))/1000000,0) -> 68.334464 | J10: =IFERROR(INDEX(Python!$1:$1048576,MATCH(DCF_Simple!J$1,Python!$A:$A,0),MATCH(DCF_Simple!$B10,Python!$1:$1,0))/1000000,0) -> 70.874117 | K10: =IFERROR(INDEX(Python!$1:$1048576,MATCH(DCF_Simple!K$1,Python!$A:$A,0),MATCH(DCF_Simple!$B10,Python!$1:$1,0))/1000000,0) -> 73.543427 | L10: =K10*(1+L11) -> 76.31327 | M10: =L10*(1+M11) -> 79.187434 | N10: =M10*(1+N11) -> 82.169845 | O10: =N10*(1+O11) -> 85.264583 | P10: =O10*(1+P11) -> 88.475877 | Q10: =P10*(1+Q11) -> 91.808116 | R10: =Q10*(1+R11) -> 95.265857 | S10: =R10*(1+S11) -> 98.853826 | ... U10: =T10*(1+U11) -> 106.44025 | V10: =U10 -> 106.44025
B11: Change (y/y) | E11: =IFERROR(E10/D10-1,"") -> 0.045273223 | F11: =IFERROR(F10/E10-1,"") -> 0.087182309 | G11: =IFERROR(G10/F10-1,"") -> 0.049349509 | H11: =IFERROR(H10/G10-1,"") -> 0.086187093 | I11: =IFERROR(I10/H10-1,"") -> 0.077377043 | J11: =IFERROR(J10/I10-1,"") -> 0.037165039 | K11: =IFERROR(K10/J10-1,"") -> 0.037662691 | L11: =K11 -> 0.037662691 | M11: =L11 -> 0.037662691 | N11: =M11 -> 0.037662691 | O11: =N11 -> 0.037662691 | P11: =O11 -> 0.037662691 | Q11: =P11 -> 0.037662691 | R11: =Q11 -> 0.037662691 | S11: =R11 -> 0.037662691 | ... U11: =T11 -> 0.037662691
B13: FCF per share | D13: =IFERROR(D7/D10,0) -> -0.9251086 | E13: =IFERROR(E7/E10,0) -> -0.87882726 | F13: =IFERROR(F7/F10,0) -> -0.59930592 | G13: =IFERROR(G7/G10,0) -> -0.74208101 | H13: =IFERROR(H7/H10,0) -> -0.71129358 | I13: =IFERROR(I7/I10,0) -> -0.40196408 | J13: =IFERROR(J7/J10,0) -> 0.637821 | K13: =IFERROR(K7/K10,0) -> 2.024083 | L13: =L7/L10 -> 1.5380313 | M13: =M7/M10 -> 1.7041321 | N13: =N7/N10 -> 1.8881711 | O13: =O7/O10 -> 2.0920855 | P13: =P7/P10 -> 2.3180218 | Q13: =Q7/Q10 -> 2.5683582 | R13: =R7/R10 -> 2.8457299 | S13: =S7/S10 -> 3.1530566 | ... U13: =U7/U10 -> 3.8708642 | V13: =U13*(1+WACC!$B$13)/(WACC!$B$14-WACC!$B$13) -> 68.228377
B14: Discounted FCF per share | L14: =L13/((1+WACC!$B$14)^(L3-$K$3)) -> 1.4269191 | M14: =M13/((1+WACC!$B$14)^(M3-$K$3)) -> 1.4668024 | N14: =N13/((1+WACC!$B$14)^(N3-$K$3)) -> 1.5078004 | O14: =O13/((1+WACC!$B$14)^(O3-$K$3)) -> 1.5499444 | P14: =P13/((1+WACC!$B$14)^(P3-$K$3)) -> 1.5932664 | Q14: =Q13/((1+WACC!$B$14)^(Q3-$K$3)) -> 1.6377992 | R14: =R13/((1+WACC!$B$14)^(R3-$K$3)) -> 1.6835767 | S14: =S13/((1+WACC!$B$14)^(S3-$K$3)) -> 1.7306337 | ... U14: =U13/((1+WACC!$B$14)^(U3-$K$3)) -> 1.8287304 | V14: =V13/((1+WACC!$B$14)^(U3-$K$3)) -> 32.233449
B17: Terminal Value (TV) | C17: =V14 -> 32.233449 | L17: =C17/$C$19 -> 0.66545888
B18: Total Discounted FCF | C18: =SUM(14:14)-V14 -> 16.204479 | L18: =C18/$C$19 -> 0.33454112
B19: Enterprise Value | C19: =C17+C18 -> 48.437928
B20: Cash and Equivalents | C20: =Python!E3/1000000/K10 -> 30.795872
B21: Debt | C21: =WACC!B3/1000000/K10 -> 15.56872
B22: Equity Value | C22: =C19+C20-C21 -> 63.665081

Sheet Python
A1: fiscalDateEnding | B1: Revenue | C1: Free Cash Flow (FCF) | D1: Shares Outstanding, Diluted | E1: Cash and Equivalents | F1: estimatedRevGrowth_yearly
A2: 2024-10-31 | F2: 0.14972583
A3: 2024-07-31 | B3: 1819610000 | C3: 148858000 | D3: 73543427 | E3: 2264834000 | F3: 0.097305674
A4: 2024-04-30 | B4: 1765292000 | C4: 125370000 | D4: 72990141 | E4: 2073996000 | F4: 0.19865617
A5: 2024-01-31 | B5: 1683011000 | C5: 115403000 | D5: 72349350 | E5: 2015407000 | F5: 0.21000167
A6: 2023-10-31 | B6: 1586321000 | C6: 88674000 | D6: 71560023 | E6: 1924711000 | F6: 0.20990585
A7: 2023-07-31 | B7: 1487004000 | C7: 45205000 | D7: 70874117 | E7: 1901101000 | F7: 0.28502272
A8: 2023-04-30 | B8: 1366873000 | C8: 23857000 | D8: 70177499 | E8: 1903428000 | F8: 0.21616272
A9: 2023-01-31 | B9: 1284040000 | C9: -20214000 | D9: 69525238 | E9: 1836630000 | F9: 0.26704541
A10: 2022-10-31 | B10: 1189222000 | C10: -26619000 | D10: 68916813 | E10: 1787532000
A11: 2022-07-31 | B11: 1082494000 | C11: -27468000 | D11: 68334464 | E11: 1795612000
A12: 2022-04-30 | B12: 977581000 | C12: -1646000 | D12: 67706502 | E12: 1828695000 | F12: 4.9714316
A13: 2022-01-31 | B13: 873782000 | C13: -1092000 | D13: 66972991 | E13: 1825923000 | F13: 0.55375178
A14: 2021-10-31 | B14: 778287000 | C14: -39323000 | D14: 66386379 | E14: 1802886000 | F14: 0.60349139
A15: 2021-07-31 | B15: 702165000 | C15: -45115000 | D15: 63426694 | E15: 1814825000 | F15: 0.54158695
A16: 2021-04-30 | B16: 641699000 | C16: -37473000 | D16: 61361670 | E16: 935043000 | F16: 0.30063148
A17: 2021-01-31 | B17: 590380000 | C17: -54446000 | D17: 60497810 | E17: 957742000 | F17: 0.27077548
A18: 2020-10-31 | B18: 542904000 | C18: -44802000 | D18: 59368167 | E18: 966301000 | F18: 0.78467829
A19: 2020-07-31 | B19: 501574000 | C19: -43333000 | D19: 58393894 | E19: 974896000 | F19: 1.466936
A20: 2020-04-30 | B20: 462661000 | C20: -43312000 | D20: 57649524 | E20: 977017000 | F20: 1.803874
A21: 2020-01-31 | B21: 421720000 | C21: -33104000 | D21: 56943622 | E21: 986518000 | F21: 0.61838192
A22: 2019-10-31 | B22: 383681000 | C22: -35902000 | D22: 56411779 | E22: 425867000 | F22: 0.81364219
A23: 2019-07-31 | B23: 339225000 | C23: -33350000 | D23: 55647707 | E23: 436053000 | F23: 0.86139663
... A29: 2018-01-31 | B29: 154519000 | C29: -47016000 | D29: 50287162 | E29: 278974000 | F29: 0.61752773
A30: 2017-10-31 | B30: 139412000 | C30: -49230000 | D30: 17421642 | E30: 288555000
A31: 2017-07-31 | B31: 124229000 | C31: -45301000 | D31: 48968305 | E31: 92451000
A32: 2017-04-30 | B32: 112239000 | C32: -41813000 | D32: 40296208 | E32: 108769000
A33: 2017-01-31 | B33: 101358000 | C33: -39761000 | D33: 40296208 | E33: 116500000
A34: 2016-10-31 | D34: 40296208
A35: 2016-07-31 | D35: 11763244
A36: 2016-04-30 | D36: 11596586

Sheet Sheet3
A1: date | B1: revenue | C1: Deriv1 | D1: Static1 | F1: revenue | G1: Deriv1 | H1: Static1 | J1: grossProfit_margin | K1: Deriv1 | L1: Static1 | N1: FCF_margin | O1: Deriv1 | P1: Static1 | R1: 2025 | S1: =R1+1 -> 2026 | T1: =S1+1 -> 2027 | U1: =T1+1 -> 2028 | V1: =U1+1 -> 2029 | W1: =V1+1 -> 2030 | X1: =W1+1 -> 2031 | Y1: =X1+1 -> 2032 | Z1: =Y1+1 -> 2033 | ... AT1: =AS1+1 -> 2053
A2: 45596 | B2: 0.24979962 | C2: =B2/B3-1 -> -0.21198857 | D2: =B2-B3 -> -0.067200378 | F2: 0.24979962 | G2: =F2/F6-1 -> -0.29235235 | H2: =F2-F6 -> -0.10320038 | R2: =F2 -> 0.24979962 | S2: =R2*(1+$G$32) -> 0.2064695 | T2: =S2*(1+$G$32) -> 0.17065541 | U2: =T2*(1+$G$32) -> 0.14105361 | V2: =U2*(1+$G$32) -> 0.11658652 | W2: =V2*(1+$G$32) -> 0.096363479 | X2: =W2*(1+$G$32) -> 0.079648318 | Y2: =X2*(1+$G$32) -> 0.06583256 | Z2: =Y2*(1+$G$32) -> 0.054413277 | ... AT2: =AS2*(1+$G$32) -> 0.0012050017
A3: 2024-07-31 | B3: 0.317 | C3: =B3/B4-1 -> -0.039393939 | D3: =B3-B4 -> -0.013 | F3: 0.317 | G3: =F3/F7-1 -> -0.13623978 | H3: =F3-F7 -> -0.05 | J3: 0.753 | K3: =J3/J7-1 -> 0.017567568 | L3: =J3-J7 -> 0.013 | N3: 0.315 | O3: =N3/N7-1 -> 0.043046358 | P3: =N3-N7 -> 0.013 | R3: =J3 -> 0.753 | S3: =R3*(1+($K$32/2)) -> 0.75961419 | T3: =S3*(1+($K$32/2)) -> 0.76628648 | U3: =T3*(1+($K$32/2)) -> 0.77301737 | V3: =U3*(1+($K$32/2)) -> 0.77980739 | W3: =V3*(1+($K$32/2)) -> 0.78665705 | X3: =W3*(1+($K$32/2)) -> 0.79356687 | Y3: =X3*(1+($K$32/2)) -> 0.80053739 | Z3: =Y3*(1+($K$32/2)) -> 0.80756914 | ... AT3: =AS3*(1+($K$32/2)) -> 0.96192577
A4: 2024-04-30 | B4: 0.33 | C4: =B4/B5-1 -> 0.012269939 | D4: =B4-B5 -> 0.004 | F4: 0.33 | G4: =F4/F8-1 -> -0.21428571 | H4: =F4-F8 -> -0.09 | J4: 0.753 | K4: =J4/J8-1 -> 0.021709634 | L4: =J4-J8 -> 0.016 | N4: 0.312 | O4: =N4/N8-1 -> 0.02295082 | P4: =N4-N8 -> 0.007
A5: 2024-01-31 | B5: 0.326 | C5: =B5/B6-1 -> -0.076487252 | D5: =B5-B6 -> -0.027 | F5: 0.326 | G5: =F5/F9-1 -> -0.31941545 | H5: =F5-F9 -> -0.153 | J5: 0.752 | K5: =J5/J9-1 -> 0.027322404 | L5: =J5-J9 -> 0.02 | N5: 0.304 | O5: =N5/N9-1 -> 0.0099667774 | P5: =N5-N9 -> 0.003
A6: 2023-10-31 | B6: 0.353 | C6: =B6/B7-1 -> -0.038147139 | D6: =B6-B7 -> -0.014 | F6: 0.353 | G6: =F6/F10-1 -> -0.33143939 | H6: =F6-F10 -> -0.175 | J6: 0.746 | K6: =J6/J10-1 -> 0.014965986 | L6: =J6-J10 -> 0.011 | N6: 0.303 | O6: =N6/N10-1 -> 0.037671233 | P6: =N6-N10 -> 0.011 | R6: # Get a mathematical function written to get the first derivative. Maybe start with a graph, and go from there?
A7: 2023-07-31 | B7: 0.367 | C7: =B7/B8-1 -> -0.12619048 | D7: =B7-B8 -> -0.053 | F7: 0.367 | G7: =F7/F11-1 -> -0.37264957 | H7: =F7-F11 -> -0.218 | J7: 0.74 | K7: =J7/J11-1 -> 0.0040705563 | L7: =J7-J11 -> 0.003 | N7: 0.302 | O7: =N7/N11-1 -> 0.02027027 | P7: =N7-N11 -> 0.006 | S7: calculus functions in python/r, to start, do a static program maybe, just to get a foundation going. Might be a little bit of a detour for now
A8: 2023-04-30 | B8: 0.42 | C8: =B8/B9-1 -> -0.12317328 | D8: =B8-B9 -> -0.059 | F8: 0.42 | G8: =F8/F12-1 -> -0.31260229 | H8: =F8-F12 -> -0.191 | J8: 0.737 | K8: =J8/J12-1 -> 0.0013586957 | L8: =J8-J12 -> 0.001 | N8: 0.305 | O8: =N8/N12-1 -> 0.037414966 | P8: =N8-N12 -> 0.011
A9: 2023-01-31 | B9: 0.479 | C9: =B9/B10-1 -> -0.09280303 | D9: =B9-B10 -> -0.049 | F9: 0.479 | G9: =F9/F13-1 -> -0.23604466 | H9: =F9-F13 -> -0.148 | J9: 0.732 | K9: =J9/J13-1 -> -0.0054347826 | L9: =J9-J13 -> -0.004 | N9: 0.301 | O9: =N9/N13-1 -> -0.0098684211 | P9: =N9-N13 -> -0.003 | R9: I am leaving off by trying to determine a systematic way to project revenue growth. Keep it as simple as can be, for now
A10: 2022-10-31 | B10: 0.528 | C10: =B10/B11-1 -> -0.097435897 | D10: =B10-B11 -> -0.057 | F10: 0.528 | G10: =F10/F14-1 -> -0.16850394 | H10: =F10-F14 -> -0.107 | J10: 0.735 | K10: =J10/J14-1 -> -0.0040650407 | L10: =J10-J14 -> -0.003 | N10: 0.292 | O10: =N10/N14-1 -> -0.0875 | P10: =N10-N14 -> -0.028 | R10: Current figures are quarterly. I need annual
A11: 2022-07-31 | B11: 0.585 | C11: =B11/B12-1 -> -0.042553191 | D11: =B11-B12 -> -0.026 | F11: 0.585 | G11: =F11/F15-1 -> -0.16068867 | H11: =F11-F15 -> -0.112 | J11: 0.737 | K11: =J11/J15-1 -> -0.0027063599 | L11: =J11-J15 -> -0.002 | N11: 0.296 | O11: =N11/N15-1 -> -0.075 | P11: =N11-N15 -> -0.024
A12: 2022-04-30 | B12: 0.611 | C12: =B12/B13-1 -> -0.025518341 | D12: =B12-B13 -> -0.016 | F12: 0.611 | G12: =F12/F16-1 -> -0.12838802 | H12: =F12-F16 -> -0.09 | J12: 0.736 | K12: =J12/J16-1 -> -0.0040595399 | L12: =J12-J16 -> -0.003 | N12: 0.294 | O12: =N12/N16-1 -> -0.089783282 | P12: =N12-N16 -> -0.029
A13: 2022-01-31 | B13: 0.627 | C13: =B13/B14-1 -> -0.012598425 | D13: =B13-B14 -> -0.008 | F13: 0.627 | G13: =F13/F17-1 -> -0.15498652 | H13: =F13-F17 -> -0.115 | J13: 0.736 | K13: =J13/J17-1 -> -0.0013568521 | L13: =J13-J17 -> -0.001 | N13: 0.304 | O13: =N13/N17-1 -> -0.092537313 | P13: =N13-N17 -> -0.031
A14: 2021-10-31 | B14: 0.635 | C14: =B14/B15-1 -> -0.088952654 | D14: =B14-B15 -> -0.062 | F14: 0.635 | G14: =F14/F18-1 -> -0.25990676 | H14: =F14-F18 -> -0.223 | J14: 0.738 | K14: =J14/J18-1 -> 0.012345679 | L14: =J14-J18 -> 0.009 | N14: 0.32 | O14: =N14/N18-1 -> -0.0092879257 | P14: =N14-N18 -> -0.003 | R14: add more to show the return, and also the market cap valuations
A15: 2021-07-31 | B15: 0.697 | C15: =B15/B16-1 -> -0.0057061341 | D15: =B15-B16 -> -0.004 | F15: 0.697 | G15: =F15/F19-1 -> -0.1702381 | H15: =F15-F19 -> -0.143 | J15: 0.739 | K15: =J15/J19-1 -> 0.023545706 | L15: =J15-J19 -> 0.017 | N15: 0.32 | O15: =N15/N19-1 -> 0.18081181 | P15: =N15-N19 -> 0.049
A16: 2021-04-30 | B16: 0.701 | C16: =B16/B17-1 -> -0.055256065 | D16: =B16-B17 -> -0.041 | F16: 0.701 | G16: =F16/F20-1 -> -0.17819461 | H16: =F16-F20 -> -0.152 | J16: 0.739 | K16: =J16/J20-1 -> 0.030683403 | L16: =J16-J20 -> 0.022 | N16: 0.323 | O16: =N16/N20-1 -> 0.57560976 | P16: =N16-N20 -> 0.118
A17: 2021-01-31 | B17: 0.742 | C17: =B17/B18-1 -> -0.13519814 | D17: =B17-B18 -> -0.116 | F17: 0.742 | G17: =F17/F21-1 -> -0.16722783 | H17: =F17-F21 -> -0.149 | J17: 0.737 | K17: =J17/J21-1 -> 0.043909348 | L17: =J17-J21 -> 0.031 | N17: 0.335 | O17: =N17/N21-1 -> 11.884615 | P17: =N17-N21 -> 0.309
A18: 2020-10-31 | B18: 0.858 | C18: =B18/B19-1 -> 0.021428571 | D18: =B18-B19 -> 0.018 | F18: 0.858 | G18: =F18/F22-1 -> -0.030508475 | H18: =F18-F22 -> -0.027 | J18: 0.729 | K18: =J18/J22-1 -> 0.050432277 | L18: =J18-J22 -> 0.035 | N18: 0.323 | O18: =N18/N22-1 -> -4.4361702 | P18: =N18-N22 -> 0.417
A19: 2020-07-31 | B19: 0.84 | C19: =B19/B20-1 -> -0.015240328 | D19: =B19-B20 -> -0.013 | F19: 0.84 | G19: =F19/F23-1 -> -0.10733262 | H19: =F19-F23 -> -0.101 | J19: 0.722 | K19: =J19/J23-1 -> 0.052478134 | L19: =J19-J23 -> 0.036 | N19: 0.271 | O19: =N19/N23-1 -> -2.6227545 | P19: =N19-N23 -> 0.438
A20: 2020-04-30 | B20: 0.853 | C20: =B20/B21-1 -> -0.042648709 | D20: =B20-B21 -> -0.038 | F20: 0.853 | G20: =F20/F24-1 -> -0.17344961 | H20: =F20-F24 -> -0.179 | J20: 0.717 | K20: =J20/J24-1 -> 0.062222222 | L20: =J20-J24 -> 0.042 | N20: 0.205 | O20: =N20/N24-1 -> -1.940367 | P20: =N20-N24 -> 0.423
A21: 2020-01-31 | B21: 0.891 | C21: =B21/B22-1 -> 0.006779661 | D21: =B21-B22 -> 0.006 | F21: 0.891 | G21: =F21/F25-1 -> -0.17346939 | H21: =F21-F25 -> -0.187 | J21: 0.706 | K21: =J21/J25-1 -> 0.084485407 | L21: =J21-J25 -> 0.055 | N21: 0.026 | O21: =N21/N25-1 -> -1.0988593 | P21: =N21-N25 -> 0.289
A22: 2019-10-31 | B22: 0.885 | C22: =B22/B23-1 -> -0.059511158 | D22: =B22-B23 -> -0.056 | F22: 0.885 | J22: 0.694 | N22: -0.094
A23: 2019-07-31 | B23: 0.941 | C23: =B23/B24-1 -> -0.088178295 | D23: =B23-B24 -> -0.091 | F23: 0.941 | J23: 0.686 | N23: -0.167
A24: 2019-04-30 | B24: 1.032 | C24: =B24/B25-1 -> -0.042671614 | D24: =B24-B25 -> -0.046 | F24: 1.032 | J24: 0.675 | N24: -0.218
A25: 2019-01-31 | B25: 1.078 | F25: 1.078 | J25: 0.651 | N25: -0.263
A26: 2018-10-31 | J26: 0.618 | N26: -0.364
A27: 2018-07-31
A28: 2018-04-30
A29: 2018-01-31
A31: Mean | C31: =AVERAGE(C2:C24) -> -0.059964107 | G31: =AVERAGE(G2:G24) -> -0.20439619 | K31: =AVERAGE(K2:K24) -> 0.022603918 | O31: =AVERAGE(O2:O8) -> 0.028553404
A32: Median | C32: =MEDIAN(C2:C24) -> -0.042671614 | G32: =MEDIAN(G2:G24) -> -0.1734595 | K32: =MEDIAN(K2:K24) -> 0.017567568 | O32: =MEDIAN(O2:O8) -> 0.030182893

Sheet Beta
B1: Years | C1: Timing Standard | D1: Beta | E1: CAPM
A2: 0 | B2: 3 | C2: M | D2: 1.2145369 | E2: 0.12486097
A3: 1 | B3: 3 | C3: W | D3: 2.1625874 | E3: 0.19053243
A4: 2 | B4: 3 | C4: D | D4: 2.2895553 | E4: 0.1993275
A5: 3 | B5: 5 | C5: M | D5: 1.15248 | E5: 0.12056229
A6: 4 | B6: 5 | C6: W | D6: 1.3793959 | E6: 0.13628076
A7: 5 | B7: 5 | C7: D | D7: 1.5039145 | E7: 0.14490616
A8: 6 | B8: Mean | D8: 1.6170784 | E8: 0.15274502
A9: 7 | B9: Median | D9: 1.4416552 | E9: 0.14059346
