Workbook

Sheet __FDSCACHE__
B1: This sheet contains FactSet XML data for use with this workbook's =FDS codes. Modifying the worksheet's contents may damage the workbook's =FDS functionality.

Sheet WACC
B1: CRWD
A2: Total Liabilities | B2: 4311884000
A3: Long-Term Debt | B3: 743238000
A4: % Debt | B4: 0.20453307
A5: Cost of Debt | B5: 0.026948299
A6: Tax Rate | B6: 0.21
A7: Total Equity | B7: 2890590000
A8: % Equity | B8: 0.79546693
A9: CAPM | B9: 0.11972161
A10: Risk-Free Rate | B10: 0.04098
A11: Beta | B11: 1.1408521
A12: Market Risk Premium | B12: 0.06902
A13: Terminal Growth Rate | B13: 0.02
A14: WACC | B14: 0.09958892

Sheet DCF_Simple
D1: =Python!A31 | E1: =Python!A27 | F1: =Python!A23 | G1: =Python!A19 | H1: =Python!A15 | I1: =Python!A11 | J1: =Python!A7 | K1: =Python!A3 | L1: =EDATE(K1, 12) | M1: =EDATE(L1, 12) | N1: =EDATE(M1, 12) | O1: =EDATE(N1, 12) | P1: =EDATE(O1, 12) | Q1: =EDATE(P1, 12) | R1: =EDATE(Q1, 12) | S1: =EDATE(R1, 12) | ... U1: =EDATE(T1, 12)
B3: Figures in millions | D3: =YEAR(D1) | E3: =YEAR(E1) | F3: =YEAR(F1) | G3: =YEAR(G1) | H3: =YEAR(H1) | I3: =YEAR(I1) | J3: =YEAR(J1) | K3: =YEAR(K1) | ... U3: =YEAR(U1) | V3: Terminal
B4: Revenue | D4: =IFERROR(INDEX(Python!$1:$1048576,MATCH(DCF_Simple!D$1,Python!$A:$A,0),MATCH(DCF_Simple!$B4,Python!$1:$1,0))/1000000,0) | E4: =IFERROR(INDEX(Python!$1:$1048576,MATCH(DCF_Simple!E$1,Python!$A:$A,0),MATCH(DCF_Simple!$B4,Python!$1:$1,0))/1000000,0) | F4: =IFERROR(INDEX(Python!$1:$1048576,MATCH(DCF_Simple!F$1,Python!$A:$A,0),MATCH(DCF_Simple!$B4,Python!$1:$1,0))/1000000,0) | G4: =IFERROR(INDEX(Python!$1:$1048576,MATCH(DCF_Simple!G$1,Python!$A:$A,0),MATCH(DCF_Simple!$B4,Python!$1:$1,0))/1000000,0) | H4: =IFERROR(INDEX(Python!$1:$1048576,MATCH(DCF_Simple!H$1,Python!$A:$A,0),MATCH(DCF_Simple!$B4,Python!$1:$1,0))/1000000,0) | I4: =IFERROR(INDEX(Python!$1:$1048576,MATCH(DCF_Simple!I$1,Python!$A:$A,0),MATCH(DCF_Simple!$B4,Python!$1:$1,0))/1000000,0) | J4: =IFERROR(INDEX(Python!$1:$1048576,MATCH(DCF_Simple!J$1,Python!$A:$A,0),MATCH(DCF_Simple!$B4,Python!$1:$1,0))/1000000,0) | K4: =IFERROR(INDEX(Python!$1:$1048576,MATCH(DCF_Simple!K$1,Python!$A:$A,0),MATCH(DCF_Simple!$B4,Python!$1:$1,0))/1000000,0) | L4: =K4*(1+L5) | M4: =L4*(1+M5) | N4: =M4*(1+N5) | O4: =N4*(1+O5) | P4: =O4*(1+P5) | Q4: =P4*(1+Q5) | R4: =Q4*(1+R5) | S4: =R4*(1+S5) | ... U4: =T4*(1+U5) | V4: =U4
B5: Growth (y/y) | E5: =IFERROR(E4/D4-1,"") | F5: =IFERROR(F4/E4-1,"") | G5: =IFERROR(G4/F4-1,"") | H5: =IFERROR(H4/G4-1,"") | I5: =IFERROR(I4/H4-1,"") | J5: =IFERROR(J4/I4-1,"") | K5: =IFERROR(K4/J4-1,"") | L5: =Python!F2 | M5: =L5/2 | N5: =M5 | O5: =N5 | P5: =O5 | Q5: =P5 | R5: =Q5 | S5: =R5 | T5: =S5 | U5: =T5
B7: Free Cash Flow (FCF) | D7: =IFERROR(INDEX(Python!$1:$1048576,MATCH(DCF_Simple!D$1,Python!$A:$A,0),MATCH(DCF_Simple!$B7,Python!$1:$1,0))/1000000,0) | E7: =IFERROR(INDEX(Python!$1:$1048576,MATCH(DCF_Simple!E$1,Python!$A:$A,0),MATCH(DCF_Simple!$B7,Python!$1:$1,0))/1000000,0) | F7: =IFERROR(INDEX(Python!$1:$1048576,MATCH(DCF_Simple!F$1,Python!$A:$A,0),MATCH(DCF_Simple!$B7,Python!$1:$1,0))/1000000,0) | G7: =IFERROR(INDEX(Python!$1:$1048576,MATCH(DCF_Simple!G$1,Python!$A:$A,0),MATCH(DCF_Simple!$B7,Python!$1:$1,0))/1000000,0) | H7: =IFERROR(INDEX(Python!$1:$1048576,MATCH(DCF_Simple!H$1,Python!$A:$A,0),MATCH(DCF_Simple!$B7,Python!$1:$1,0))/1000000,0) | I7: =IFERROR(INDEX(Python!$1:$1048576,MATCH(DCF_Simple!I$1,Python!$A:$A,0),MATCH(DCF_Simple!$B7,Python!$1:$1,0))/1000000,0) | J7: =IFERROR(INDEX(Python!$1:$1048576,MATCH(DCF_Simple!J$1,Python!$A:$A,0),MATCH(DCF_Simple!$B7,Python!$1:$1,0))/1000000,0) | K7: =IFERROR(INDEX(Python!$1:$1048576,MATCH(DCF_Simple!K$1,Python!$A:$A,0),MATCH(DCF_Simple!$B7,Python!$1:$1,0))/1000000,0) | L7: =L8*L4 | M7: =M8*M4 | N7: =N8*N4 | O7: =O8*O4 | P7: =P8*P4 | Q7: =Q8*Q4 | R7: =R8*R4 | S7: =S8*S4 | ... U7: =U8*U4 | V7: =U7
B8: FCF Margin | D8: =IFERROR(D7/D$4,"") | E8: =IFERROR(E7/E$4,"") | F8: =IFERROR(F7/F$4,"") | G8: =IFERROR(G7/G$4,"") | H8: =IFERROR(H7/H$4,"") | I8: =IFERROR(I7/I$4,"") | J8: =IFERROR(J7/J$4,"") | K8: =IFERROR(K7/K$4,"") | L8: =AVERAGE(D8:K8) | M8: =L8 | N8: =M8 | O8: =N8 | P8: =O8 | Q8: =P8 | R8: =Q8 | S8: =R8 | T8: =S8 | U8: =T8
B10: Shares Outstanding, Diluted | D10: =IFERROR(INDEX(Python!$1:$1048576,MATCH(DCF_Simple!D$1,Python!$A:$A,0),MATCH(DCF_Simple!$B10,Python!$1:$1,0))/1000000,0) | E10: =IFERROR(INDEX(Python!$1:$1048576,MATCH(DCF_Simple!E$1,Python!$A:$A,0),MATCH(DCF_Simple!$B10,Python!$1:$1,0))/1000000,0) | F10: =IFERROR(INDEX(Python!$1:$1048576,MATCH(DCF_Simple!F$1,Python!$A:$A,0),MATCH(DCF_Simple!$B10,Python!$1:$1,0))/1000000,0) | G10: =IFERROR(INDEX(Python!$1:$1048576,MATCH(DCF_Simple!G$1,Python!$A:$A,0),MATCH(DCF_Simple!$B10,Python!$1:$1,0))/1000000,0) | H10: =IFERROR(INDEX(Python!$1:$1048576,MATCH(DCF_Simple!H$1,Python!$A:$A,0),MATCH(DCF_Simple!$B10,Python!$1:$1,0))/1000000,0) | I10: =IFERROR(INDEX(Python!$1:$1048576,MATCH(DCF_Simple!I$1,Python!$A:$A,0),MATCH(DCF_Simple!$B10,Python!$1:$1,0))/1000000,0) | J10: =IFERROR(INDEX(Python!$1:$1048576,MATCH(DCF_Simple!J$1,Python!$A:$A,0),MATCH(DCF_Simple!$B10,Python!$1:$1,0))/1000000,0) | K10: =IFERROR(INDEX(Python!$1:$1048576,MATCH(DCF_Simple!K$1,Python!$A:$A,0),MATCH(DCF_Simple!$B10,Python!$1:$1,0))/1000000,0) | L10: =K10*(1+L11) | M10: =L10*(1+M11) | N10: =M10*(1+N11) | O10: =N10*(1+O11) | P10: =O10*(1+P11) | Q10: =P10*(1+Q11) | R10: =Q10*(1+R11) | S10: =R10*(1+S11) | ... U10: =T10*(1+U11) | V10: =U10
B11: Change (y/y) | E11: =IFERROR(E10/D10-1,"") | F11: =IFERROR(F10/E10-1,"") | G11: =IFERROR(G10/F10-1,"") | H11: =IFERROR(H10/G10-1,"") | I11: =IFERROR(I10/H10-1,"") | J11: =IFERROR(J10/I10-1,"") | K11: =IFERROR(K10/J10-1,"") | L11: =K11 | M11: =L11 | N11: =M11 | O11: =N11 | P11: =O11 | Q11: =P11 | R11: =Q11 | S11: =R11 | ... U11: =T11
B13: FCF per share | D13: =IFERROR(D7/D10,0) | E13: =IFERROR(E7/E10,0) | F13: =IFERROR(F7/F10,0) | G13: =IFERROR(G7/G10,0) | H13: =IFERROR(H7/H10,0) | I13: =IFERROR(I7/I10,0) | J13: =IFERROR(J7/J10,0) | K13: =IFERROR(K7/K10,0) | L13: =L7/L10 | M13: =M7/M10 | N13: =N7/N10 | O13: =O7/O10 | P13: =P7/P10 | Q13: =Q7/Q10 | R13: =R7/R10 | S13: =S7/S10 | ... U13: =U7/U10 | V13: =U13*(1+WACC!$B$13)/(WACC!$B$14-WACC!$B$13)
B14: Discounted FCF per share | L14: =L13/((1+WACC!$B$14)^(L3-$K$3)) | M14: =M13/((1+WACC!$B$14)^(M3-$K$3)) | N14: =N13/((1+WACC!$B$14)^(N3-$K$3)) | O14: =O13/((1+WACC!$B$14)^(O3-$K$3)) | P14: =P13/((1+WACC!$B$14)^(P3-$K$3)) | Q14: =Q13/((1+WACC!$B$14)^(Q3-$K$3)) | R14: =R13/((1+WACC!$B$14)^(R3-$K$3)) | S14: =S13/((1+WACC!$B$14)^(S3-$K$3)) | ... U14: =U13/((1+WACC!$B$14)^(U3-$K$3)) | V14: =V13/((1+WACC!$B$14)^(U3-$K$3))
B17: Terminal Value (TV) | C17: =V14 | L17: =C17/$C$19
B18: Total Discounted FCF | C18: =SUM(14:14)-V14 | L18: =C18/$C$19
B19: Enterprise Value | C19: =C17+C18
B20: Cash and Equivalents | C20: =Python!E3/1000000/K10
B21: Debt | C21: =WACC!B3/1000000/K10
B22: Equity Value | C22: =C19+C20-C21

Sheet Python

Sheet Sheet3
A1: date | B1: revenue | C1: Deriv1 | D1: Static1 | F1: revenue | G1: Deriv1 | H1: Static1 | J1: grossProfit_margin | K1: Deriv1 | L1: Static1 | N1: FCF_margin | O1: Deriv1 | P1: Static1 | R1: 2025 | S1: =R1+1 | T1: =S1+1 | U1: =T1+1 | V1: =U1+1 | W1: =V1+1 | X1: =W1+1 | Y1: =X1+1 | Z1: =Y1+1 | ... AT1: =AS1+1
A2: 45596 | B2: 0.24979962 | C2: =B2/B3-1 | D2: =B2-B3 | F2: 0.24979962 | G2: =F2/F6-1 | H2: =F2-F6 | R2: =F2 | S2: =R2*(1+$G$32) | T2: =S2*(1+$G$32) | U2: =T2*(1+$G$32) | V2: =U2*(1+$G$32) | W2: =V2*(1+$G$32) | X2: =W2*(1+$G$32) | Y2: =X2*(1+$G$32) | Z2: =Y2*(1+$G$32) | ... AT2: =AS2*(1+$G$32)
A3: 2024-07-31 | B3: 0.317 | C3: =B3/B4-1 | D3: =B3-B4 | F3: 0.317 | G3: =F3/F7-1 | H3: =F3-F7 | J3: 0.753 | K3: =J3/J7-1 | L3: =J3-J7 | N3: 0.315 | O3: =N3/N7-1 | P3: =N3-N7 | R3: =J3 | S3: =R3*(1+($K$32/2)) | T3: =S3*(1+($K$32/2)) | U3: =T3*(1+($K$32/2)) | V3: =U3*(1+($K$32/2)) | W3: =V3*(1+($K$32/2)) | X3: =W3*(1+($K$32/2)) | Y3: =X3*(1+($K$32/2)) | Z3: =Y3*(1+($K$32/2)) | ... AT3: =AS3*(1+($K$32/2))
A4: 2024-04-30 | B4: 0.33 | C4: =B4/B5-1 | D4: =B4-B5 | F4: 0.33 | G4: =F4/F8-1 | H4: =F4-F8 | J4: 0.753 | K4: =J4/J8-1 | L4: =J4-J8 | N4: 0.312 | O4: =N4/N8-1 | P4: =N4-N8
A5: 2024-01-31 | B5: 0.326 | C5: =B5/B6-1 | D5: =B5-B6 | F5: 0.326 | G5: =F5/F9-1 | H5: =F5-F9 | J5: 0.752 | K5: =J5/J9-1 | L5: =J5-J9 | N5: 0.304 | O5: =N5/N9-1 | P5: =N5-N9
A6: 2023-10-31 | B6: 0.353 | C6: =B6/B7-1 | D6: =B6-B7 | F6: 0.353 | G6: =F6/F10-1 | H6: =F6-F10 | J6: 0.746 | K6: =J6/J10-1 | L6: =J6-J10 | N6: 0.303 | O6: =N6/N10-1 | P6: =N6-N10 | R6: # Get a mathematical function written to get the first derivative. Maybe start with a graph, and go from there?
A7: 2023-07-31 | B7: 0.367 | C7: =B7/B8-1 | D7: =B7-B8 | F7: 0.367 | G7: =F7/F11-1 | H7: =F7-F11 | J7: 0.74 | K7: =J7/J11-1 | L7: =J7-J11 | N7: 0.302 | O7: =N7/N11-1 | P7: =N7-N11 | S7: calculus functions in python/r, to start, do a static program maybe, just to get a foundation going. Might be a little bit of a detour for now
A8: 2023-04-30 | B8: 0.42 | C8: =B8/B9-1 | D8: =B8-B9 | F8: 0.42 | G8: =F8/F12-1 | H8: =F8-F12 | J8: 0.737 | K8: =J8/J12-1 | L8: =J8-J12 | N8: 0.305 | O8: =N8/N12-1 | P8: =N8-N12
A9: 2023-01-31 | B9: 0.479 | C9: =B9/B10-1 | D9: =B9-B10 | F9: 0.479 | G9: =F9/F13-1 | H9: =F9-F13 | J9: 0.732 | K9: =J9/J13-1 | L9: =J9-J13 | N9: 0.301 | O9: =N9/N13-1 | P9: =N9-N13 | R9: I am leaving off by trying to determine a systematic way to project revenue growth. Keep it as simple as can be, for now
A10: 2022-10-31 | B10: 0.528 | C10: =B10/B11-1 | D10: =B10-B11 | F10: 0.528 | G10: =F10/F14-1 | H10: =F10-F14 | J10: 0.735 | K10: =J10/J14-1 | L10: =J10-J14 | N10: 0.292 | O10: =N10/N14-1 | P10: =N10-N14 | R10: Current figures are quarterly. I need annual
A11: 2022-07-31 | B11: 0.585 | C11: =B11/B12-1 | D11: =B11-B12 | F11: 0.585 | G11: =F11/F15-1 | H11: =F11-F15 | J11: 0.737 | K11: =J11/J15-1 | L11: =J11-J15 | N11: 0.296 | O11: =N11/N15-1 | P11: =N11-N15
A12: 2022-04-30 | B12: 0.611 | C12: =B12/B13-1 | D12: =B12-B13 | F12: 0.611 | G12: =F12/F16-1 | H12: =F12-F16 | J12: 0.736 | K12: =J12/J16-1 | L12: =J12-J16 | N12: 0.294 | O12: =N12/N16-1 | P12: =N12-N16
A13: 2022-01-31 | B13: 0.627 | C13: =B13/B14-1 | D13: =B13-B14 | F13: 0.627 | G13: =F13/F17-1 | H13: =F13-F17 | J13: 0.736 | K13: =J13/J17-1 | L13: =J13-J17 | N13: 0.304 | O13: =N13/N17-1 | P13: =N13-N17
A14: 2021-10-31 | B14: 0.635 | C14: =B14/B15-1 | D14: =B14-B15 | F14: 0.635 | G14: =F14/F18-1 | H14: =F14-F18 | J14: 0.738 | K14: =J14/J18-1 | L14: =J14-J18 | N14: 0.32 | O14: =N14/N18-1 | P14: =N14-N18 | R14: add more to show the return, and also the market cap valuations
A15: 2021-07-31 | B15: 0.697 | C15: =B15/B16-1 | D15: =B15-B16 | F15: 0.697 | G15: =F15/F19-1 | H15: =F15-F19 | J15: 0.739 | K15: =J15/J19-1 | L15: =J15-J19 | N15: 0.32 | O15: =N15/N19-1 | P15: =N15-N19
A16: 2021-04-30 | B16: 0.701 | C16: =B16/B17-1 | D16: =B16-B17 | F16: 0.701 | G16: =F16/F20-1 | H16: =F16-F20 | J16: 0.739 | K16: =J16/J20-1 | L16: =J16-J20 | N16: 0.323 | O16: =N16/N20-1 | P16: =N16-N20
A17: 2021-01-31 | B17: 0.742 | C17: =B17/B18-1 | D17: =B17-B18 | F17: 0.742 | G17: =F17/F21-1 | H17: =F17-F21 | J17: 0.737 | K17: =J17/J21-1 | L17: =J17-J21 | N17: 0.335 | O17: =N17/N21-1 | P17: =N17-N21
A18: 2020-10-31 | B18: 0.858 | C18: =B18/B19-1 | D18: =B18-B19 | F18: 0.858 | G18: =F18/F22-1 | H18: =F18-F22 | J18: 0.729 | K18: =J18/J22-1 | L18: =J18-J22 | N18: 0.323 | O18: =N18/N22-1 | P18: =N18-N22
A19: 2020-07-31 | B19: 0.84 | C19: =B19/B20-1 | D19: =B19-B20 | F19: 0.84 | G19: =F19/F23-1 | H19: =F19-F23 | J19: 0.722 | K19: =J19/J23-1 | L19: =J19-J23 | N19: 0.271 | O19: =N19/N23-1 | P19: =N19-N23
A20: 2020-04-30 | B20: 0.853 | C20: =B20/B21-1 | D20: =B20-B21 | F20: 0.853 | G20: =F20/F24-1 | H20: =F20-F24 | J20: 0.717 | K20: =J20/J24-1 | L20: =J20-J24 | N20: 0.205 | O20: =N20/N24-1 | P20: =N20-N24
A21: 2020-01-31 | B21: 0.891 | C21: =B21/B22-1 | D21: =B21-B22 | F21: 0.891 | G21: =F21/F25-1 | H21: =F21-F25 | J21: 0.706 | K21: =J21/J25-1 | L21: =J21-J25 | N21: 0.026 | O21: =N21/N25-1 | P21: =N21-N25
A22: 2019-10-31 | B22: 0.885 | C22: =B22/B23-1 | D22: =B22-B23 | F22: 0.885 | J22: 0.694 | N22: -0.094
A23: 2019-07-31 | B23: 0.941 | C23: =B23/B24-1 | D23: =B23-B24 | F23: 0.941 | J23: 0.686 | N23: -0.167
A24: 2019-04-30 | B24: 1.032 | C24: =B24/B25-1 | D24: =B24-B25 | F24: 1.032 | J24: 0.675 | N24: -0.218
A25: 2019-01-31 | B25: 1.078 | F25: 1.078 | J25: 0.651 | N25: -0.263
A26: 2018-10-31 | J26: 0.618 | N26: -0.364
A27: 2018-07-31
A28: 2018-04-30
A29: 2018-01-31
A31: Mean | C31: =AVERAGE(C2:C24) | G31: =AVERAGE(G2:G24) | K31: =AVERAGE(K2:K24) | O31: =AVERAGE(O2:O8)
A32: Median | C32: =MEDIAN(C2:C24) | G32: =MEDIAN(G2:G24) | K32: =MEDIAN(K2:K24) | O32: =MEDIAN(O2:O8)
