Workbook
Name tgr: 'Best Case'!$C$4
Name tgr: 'DCF-Detailed'!$C$5
Name tgr: WACC!#REF!
Name tgr: 'WACC (2)'!#REF!
Name tgr: #REF!
Name tgrr: 'Best Case'!$C$4
Name tgrr: 'DCF-Detailed'!$C$5
Name tgrr: #REF!
Name wacc: 'Best Case'!$C$3
Name wacc: 'DCF-Detailed'!$C$4
Name wacc: WACC!#REF!
Name wacc: 'WACC (2)'!#REF!
Name wacc: #REF!
Name waccc: 'Best Case'!$C$3
Name waccc: 'DCF-Detailed'!$C$4
Name waccc: #REF!

Sheet __FDSCACHE__
B1: This sheet contains FactSet XML data for use with this workbook's =FDS codes. Modifying the worksheet's contents may damage the workbook's =FDS functionality.

Sheet WACC (2)
B2: Weighted Average Cost of Capital | G2: ASML
G3: Total Liabilities 26030
B4: $ Debt | D4: =[1]CAPM!$B$2 -> 4311884000 | G4: Long-Term Debt 4608
B5: % Debt | D5: =D4/D16 -> 0.59866707 | G5: % Debt 0.2385
B6: Cost of Debt | D6: =[1]CAPM!$B$5 -> 0.026948299 | G6: Cost of Debt 0.0026
B7: Tax Rate | D7: 0.21 | G7: Tax Rate 0.2100
G8: Total Equity 14711
B9: $ Equity Value | D9: =[1]CAPM!$B$7 -> 2890590000 | G9: % Equity 0.7615
B10: % Equity | D10: =D9/D16 -> 0.40133293 | G10: CAPM 0.1418
B11: Cost of Equity | D11: =D12+D13*D14 -> 0.11972455 | G11: Risk-Free Rate 0.0381
B12: Risk Free Rate | D12: =[1]CAPM!$B$10 -> 0.040409999 | G12: Beta 1.4426
B13: Beta | D13: =[1]CAPM!$B$11 -> 1.1397406 | G13: Market Risk Premium 0.0719
B14: Market Risk Premium | D14: =[1]CAPM!$B$12 -> 0.069590001 | G14: FCF Recent Quarter 2930
G15: WACC 0.0525
B16: $ Debt & Equity | D16: =D4+D9 -> 7202474000
B18: WACC | D18: =(D5*D6*(1-D7))+(D10*D11) -> 0.060794519

Sheet WACC
B2: Weighted Average Cost of Capital | G2: ASML
G3: Total Liabilities 26030
B4: $ Debt | D4: =INDEX(Python!$1:$1048576,MATCH("longTermDebt",Python!$A:$A,0),2) -> #N/A | G4: Long-Term Debt 4608
B5: % Debt | D5: =D4/D16 -> #N/A | G5: % Debt 0.2385
B6: Cost of Debt | D6: 0.0308 | G6: Cost of Debt 0.0026
B7: Tax Rate | D7: 0.21 | G7: Tax Rate 0.2100
G8: Total Equity 14711
B9: $ Equity Value | D9: =INDEX(Python!$1:$1048576,MATCH("totalEquity",Python!$A:$A,0),2) -> #N/A | G9: % Equity 0.7615
B10: % Equity | D10: =D9/D16 -> #N/A | G10: CAPM 0.1418
B11: Cost of Equity | D11: =D12+D13*D14 -> 0.091 | G11: Risk-Free Rate 0.0381
B12: Risk Free Rate | D12: 0.044 | G12: Beta 1.4426
B13: Beta | D13: =2 -> 2 | G13: Market Risk Premium 0.0719
B14: Market Risk Premium | D14: =0.0675-D12 -> 0.0235 | G14: FCF Recent Quarter 2930
G15: WACC 0.0525
B16: $ Debt & Equity | D16: =D4+D9 -> #N/A
B18: WACC | D18: =(D5*D6*(1-D7))+(D10*D11) -> #N/A

Sheet DCF-Detailed
D1: 2014-03-31 | E1: 2014-06-30 | F1: 2014-09-30 | G1: 2014-12-31 | H1: 2015-03-31 | I1: 2015-06-30 | J1: 2015-09-30 | K1: 2015-12-31 | L1: 2016-03-31 | M1: 2016-06-30 | N1: 2016-09-30 | O1: 2016-12-31 | P1: 2017-03-31 | Q1: 2017-06-30 | R1: 2017-09-30 | S1: 2017-12-31 | T1: 2018-03-31 | U1: 2018-06-30 | V1: 2018-09-30 | W1: 2018-12-31 | X1: 2019-03-31 | Y1: 2019-06-30 | Z1: 2019-09-30 | AA1: 2019-12-31 | AB1: 2020-03-31 | AC1: 2020-06-30 | AD1: 2020-09-30 | AE1: 2020-12-31 | AF1: 2021-03-31 | AG1: 2021-06-30 | AH1: 2021-09-30 | AI1: 2021-12-31 | AJ1: 2022-03-31 | AK1: 2022-06-30 | AL1: 2022-09-30 | AM1: 2022-12-31 | AN1: 2023-03-31 | AO1: 2023-06-30 | AP1: 2023-09-30 | AQ1: 2023-12-31 | AR1: 2024-03-31
B3: Valuation Assumptions
B4: Discount Rate | C4: =WACC!D18 -> #N/A
B5: Terminal Growth Rate | C5: 0.02
B7: Figures in $ millions | D7: Q1 2014 | E7: Q2 2014 | F7: Q3 2014 | G7: Q4 2014 | H7: =LEFT(D7,2) & " " & 1+_xlfn.NUMBERVALUE(RIGHT(D7,LEN(D7)-2)) -> Q1 2015 | I7: =LEFT(E7,2) & " " & 1+_xlfn.NUMBERVALUE(RIGHT(E7,LEN(E7)-2)) -> Q2 2015 | J7: =LEFT(F7,2) & " " & 1+_xlfn.NUMBERVALUE(RIGHT(F7,LEN(F7)-2)) -> Q3 2015 | K7: =LEFT(G7,2) & " " & 1+_xlfn.NUMBERVALUE(RIGHT(G7,LEN(G7)-2)) -> Q4 2015 | L7: =LEFT(H7,2) & " " & 1+_xlfn.NUMBERVALUE(RIGHT(H7,LEN(H7)-2)) -> Q1 2016 | M7: =LEFT(I7,2) & " " & 1+_xlfn.NUMBERVALUE(RIGHT(I7,LEN(I7)-2)) -> Q2 2016 | N7: =LEFT(J7,2) & " " & 1+_xlfn.NUMBERVALUE(RIGHT(J7,LEN(J7)-2)) -> Q3 2016 | O7: =LEFT(K7,2) & " " & 1+_xlfn.NUMBERVALUE(RIGHT(K7,LEN(K7)-2)) -> Q4 2016 | ... BX7: =LEFT(BT7,2) & " " & 1+_xlfn.NUMBERVALUE(RIGHT(BT7,LEN(BT7)-2)) -> Q1 2032
B8: Revenue | D8: =INDEX(Python!$1:$1048576,MATCH('DCF-Detailed'!$B8,Python!$A:$A,0),MATCH('DCF-Detailed'!D$1,Python!$1:$1,0)) -> #N/A | E8: =INDEX(Python!$1:$1048576,MATCH('DCF-Detailed'!$B8,Python!$A:$A,0),MATCH('DCF-Detailed'!E$1,Python!$1:$1,0)) -> #N/A | F8: =INDEX(Python!$1:$1048576,MATCH('DCF-Detailed'!$B8,Python!$A:$A,0),MATCH('DCF-Detailed'!F$1,Python!$1:$1,0)) -> #N/A | G8: =INDEX(Python!$1:$1048576,MATCH('DCF-Detailed'!$B8,Python!$A:$A,0),MATCH('DCF-Detailed'!G$1,Python!$1:$1,0)) -> #N/A | H8: =INDEX(Python!$1:$1048576,MATCH('DCF-Detailed'!$B8,Python!$A:$A,0),MATCH('DCF-Detailed'!H$1,Python!$1:$1,0)) -> #N/A | I8: =INDEX(Python!$1:$1048576,MATCH('DCF-Detailed'!$B8,Python!$A:$A,0),MATCH('DCF-Detailed'!I$1,Python!$1:$1,0)) -> #N/A | J8: =INDEX(Python!$1:$1048576,MATCH('DCF-Detailed'!$B8,Python!$A:$A,0),MATCH('DCF-Detailed'!J$1,Python!$1:$1,0)) -> #N/A | K8: =INDEX(Python!$1:$1048576,MATCH('DCF-Detailed'!$B8,Python!$A:$A,0),MATCH('DCF-Detailed'!K$1,Python!$1:$1,0)) -> #N/A | ... AR8: =INDEX(Python!$1:$1048576,MATCH('DCF-Detailed'!$B8,Python!$A:$A,0),MATCH('DCF-Detailed'!AR$1,Python!$1:$1,0)) -> #N/A | AS8: 0 | AT8: =AP8*(1+AT9) -> #N/A | AU8: =AQ8*(1+AU9) -> #N/A | AV8: =AR8*(1+AV9) -> #N/A | AW8: =AS8*(1+AW9) -> #N/A | AX8: =AT8*(1+AX9) -> #N/A | AY8: =AU8*(1+AY9) -> #N/A | AZ8: =AV8*(1+AZ9) -> #N/A | BA8: =AW8*(1+BA9) -> #N/A | ... BX8: =BT8*(1+BX9) -> #N/A
B9: Growth y/y | H9: =IFERROR(H8/D8-1,0) -> 0 | I9: =IFERROR(I8/E8-1,0) -> 0 | J9: =IFERROR(J8/F8-1,0) -> 0 | K9: =IFERROR(K8/G8-1,0) -> 0 | L9: =IFERROR(L8/H8-1,0) -> 0 | M9: =IFERROR(M8/I8-1,0) -> 0 | N9: =IFERROR(N8/J8-1,0) -> 0 | O9: =IFERROR(O8/K8-1,0) -> 0 | ... AO9: =IFERROR(AO8/AK8-1,0) -> 0 | AP9: =AP8/AL8-1 -> #N/A | AQ9: =AQ8/AM8-1 -> #N/A | AR9: =AR8/AN8-1 -> #N/A | AS9: =AS8/AO8-1 -> #N/A | AT9: =AS9 -> #N/A | AU9: =AT9 -> #N/A | AV9: =AU9 -> #N/A | AW9: =AV9 -> #N/A | AX9: =AW9 -> #N/A | AY9: =AX9 -> #N/A | AZ9: =AY9 -> #N/A | BA9: =AZ9 -> #N/A | ... BX9: =BW9 -> #N/A
B11: Gross Profit | D11: =INDEX(Python!$1:$1048576,MATCH('DCF-Detailed'!$B11,Python!$A:$A,0),MATCH('DCF-Detailed'!D$1,Python!$1:$1,0)) -> #N/A | E11: =INDEX(Python!$1:$1048576,MATCH('DCF-Detailed'!$B11,Python!$A:$A,0),MATCH('DCF-Detailed'!E$1,Python!$1:$1,0)) -> #N/A | F11: =INDEX(Python!$1:$1048576,MATCH('DCF-Detailed'!$B11,Python!$A:$A,0),MATCH('DCF-Detailed'!F$1,Python!$1:$1,0)) -> #N/A | G11: =INDEX(Python!$1:$1048576,MATCH('DCF-Detailed'!$B11,Python!$A:$A,0),MATCH('DCF-Detailed'!G$1,Python!$1:$1,0)) -> #N/A | H11: =INDEX(Python!$1:$1048576,MATCH('DCF-Detailed'!$B11,Python!$A:$A,0),MATCH('DCF-Detailed'!H$1,Python!$1:$1,0)) -> #N/A | I11: =INDEX(Python!$1:$1048576,MATCH('DCF-Detailed'!$B11,Python!$A:$A,0),MATCH('DCF-Detailed'!I$1,Python!$1:$1,0)) -> #N/A | J11: =INDEX(Python!$1:$1048576,MATCH('DCF-Detailed'!$B11,Python!$A:$A,0),MATCH('DCF-Detailed'!J$1,Python!$1:$1,0)) -> #N/A | K11: =INDEX(Python!$1:$1048576,MATCH('DCF-Detailed'!$B11,Python!$A:$A,0),MATCH('DCF-Detailed'!K$1,Python!$1:$1,0)) -> #N/A | ... BX11: =INDEX(Python!$1:$1048576,MATCH('DCF-Detailed'!$B11,Python!$A:$A,0),MATCH('DCF-Detailed'!BX$1,Python!$1:$1,0)) -> #N/A
B12: Gross Profit Margin | D12: =D11/D$8 -> #N/A | E12: =E11/E$8 -> #N/A | F12: =F11/F$8 -> #N/A | G12: =G11/G$8 -> #N/A | H12: =H11/H$8 -> #N/A | I12: =I11/I$8 -> #N/A | J12: =J11/J$8 -> #N/A | K12: =K11/K$8 -> #N/A | ... BX12: =BX11/BX$8 -> #N/A
B14: Research & Development | D14: =-INDEX(Python!$1:$1048576,MATCH('DCF-Detailed'!$B14,Python!$A:$A,0),MATCH('DCF-Detailed'!D$1,Python!$1:$1,0)) -> #N/A | E14: =-INDEX(Python!$1:$1048576,MATCH('DCF-Detailed'!$B14,Python!$A:$A,0),MATCH('DCF-Detailed'!E$1,Python!$1:$1,0)) -> #N/A | F14: =-INDEX(Python!$1:$1048576,MATCH('DCF-Detailed'!$B14,Python!$A:$A,0),MATCH('DCF-Detailed'!F$1,Python!$1:$1,0)) -> #N/A | G14: =-INDEX(Python!$1:$1048576,MATCH('DCF-Detailed'!$B14,Python!$A:$A,0),MATCH('DCF-Detailed'!G$1,Python!$1:$1,0)) -> #N/A | H14: =-INDEX(Python!$1:$1048576,MATCH('DCF-Detailed'!$B14,Python!$A:$A,0),MATCH('DCF-Detailed'!H$1,Python!$1:$1,0)) -> #N/A | I14: =-INDEX(Python!$1:$1048576,MATCH('DCF-Detailed'!$B14,Python!$A:$A,0),MATCH('DCF-Detailed'!I$1,Python!$1:$1,0)) -> #N/A | J14: =-INDEX(Python!$1:$1048576,MATCH('DCF-Detailed'!$B14,Python!$A:$A,0),MATCH('DCF-Detailed'!J$1,Python!$1:$1,0)) -> #N/A | K14: =-INDEX(Python!$1:$1048576,MATCH('DCF-Detailed'!$B14,Python!$A:$A,0),MATCH('DCF-Detailed'!K$1,Python!$1:$1,0)) -> #N/A | ... BX14: =-INDEX(Python!$1:$1048576,MATCH('DCF-Detailed'!$B14,Python!$A:$A,0),MATCH('DCF-Detailed'!BX$1,Python!$1:$1,0)) -> #N/A
B15: % of sales | D15: =D14/D$8 -> #N/A | E15: =E14/E$8 -> #N/A | F15: =F14/F$8 -> #N/A | G15: =G14/G$8 -> #N/A | H15: =H14/H$8 -> #N/A | I15: =I14/I$8 -> #N/A | J15: =J14/J$8 -> #N/A | K15: =K14/K$8 -> #N/A | ... BX15: =BX14/BX$8 -> #N/A
B17: Selling, General, & Administrative | D17: =-INDEX(Python!$1:$1048576,MATCH('DCF-Detailed'!$B17,Python!$A:$A,0),MATCH('DCF-Detailed'!D$1,Python!$1:$1,0)) -> #N/A | E17: =-INDEX(Python!$1:$1048576,MATCH('DCF-Detailed'!$B17,Python!$A:$A,0),MATCH('DCF-Detailed'!E$1,Python!$1:$1,0)) -> #N/A | F17: =-INDEX(Python!$1:$1048576,MATCH('DCF-Detailed'!$B17,Python!$A:$A,0),MATCH('DCF-Detailed'!F$1,Python!$1:$1,0)) -> #N/A | G17: =-INDEX(Python!$1:$1048576,MATCH('DCF-Detailed'!$B17,Python!$A:$A,0),MATCH('DCF-Detailed'!G$1,Python!$1:$1,0)) -> #N/A | H17: =-INDEX(Python!$1:$1048576,MATCH('DCF-Detailed'!$B17,Python!$A:$A,0),MATCH('DCF-Detailed'!H$1,Python!$1:$1,0)) -> #N/A | I17: =-INDEX(Python!$1:$1048576,MATCH('DCF-Detailed'!$B17,Python!$A:$A,0),MATCH('DCF-Detailed'!I$1,Python!$1:$1,0)) -> #N/A | J17: =-INDEX(Python!$1:$1048576,MATCH('DCF-Detailed'!$B17,Python!$A:$A,0),MATCH('DCF-Detailed'!J$1,Python!$1:$1,0)) -> #N/A | K17: =-INDEX(Python!$1:$1048576,MATCH('DCF-Detailed'!$B17,Python!$A:$A,0),MATCH('DCF-Detailed'!K$1,Python!$1:$1,0)) -> #N/A | ... BX17: =-INDEX(Python!$1:$1048576,MATCH('DCF-Detailed'!$B17,Python!$A:$A,0),MATCH('DCF-Detailed'!BX$1,Python!$1:$1,0)) -> #N/A
B18: % of sales | D18: =D17/D$8 -> #N/A | E18: =E17/E$8 -> #N/A | F18: =F17/F$8 -> #N/A | G18: =G17/G$8 -> #N/A | H18: =H17/H$8 -> #N/A | I18: =I17/I$8 -> #N/A | J18: =J17/J$8 -> #N/A | K18: =K17/K$8 -> #N/A | ... BX18: =BX17/BX$8 -> #N/A
B20: Other Operating Expenses | D20: =-INDEX(Python!$1:$1048576,MATCH('DCF-Detailed'!$B20,Python!$A:$A,0),MATCH('DCF-Detailed'!D$1,Python!$1:$1,0)) -> #N/A | E20: =-INDEX(Python!$1:$1048576,MATCH('DCF-Detailed'!$B20,Python!$A:$A,0),MATCH('DCF-Detailed'!E$1,Python!$1:$1,0)) -> #N/A | F20: =-INDEX(Python!$1:$1048576,MATCH('DCF-Detailed'!$B20,Python!$A:$A,0),MATCH('DCF-Detailed'!F$1,Python!$1:$1,0)) -> #N/A | G20: =-INDEX(Python!$1:$1048576,MATCH('DCF-Detailed'!$B20,Python!$A:$A,0),MATCH('DCF-Detailed'!G$1,Python!$1:$1,0)) -> #N/A | H20: =-INDEX(Python!$1:$1048576,MATCH('DCF-Detailed'!$B20,Python!$A:$A,0),MATCH('DCF-Detailed'!H$1,Python!$1:$1,0)) -> #N/A | I20: =-INDEX(Python!$1:$1048576,MATCH('DCF-Detailed'!$B20,Python!$A:$A,0),MATCH('DCF-Detailed'!I$1,Python!$1:$1,0)) -> #N/A | J20: =-INDEX(Python!$1:$1048576,MATCH('DCF-Detailed'!$B20,Python!$A:$A,0),MATCH('DCF-Detailed'!J$1,Python!$1:$1,0)) -> #N/A | K20: =-INDEX(Python!$1:$1048576,MATCH('DCF-Detailed'!$B20,Python!$A:$A,0),MATCH('DCF-Detailed'!K$1,Python!$1:$1,0)) -> #N/A | ... BX20: =-INDEX(Python!$1:$1048576,MATCH('DCF-Detailed'!$B20,Python!$A:$A,0),MATCH('DCF-Detailed'!BX$1,Python!$1:$1,0)) -> #N/A
B21: % of sales | D21: =D20/D$8 -> #N/A | E21: =E20/E$8 -> #N/A | F21: =F20/F$8 -> #N/A | G21: =G20/G$8 -> #N/A | H21: =H20/H$8 -> #N/A | I21: =I20/I$8 -> #N/A | J21: =J20/J$8 -> #N/A | K21: =K20/K$8 -> #N/A | ... BX21: =BX20/BX$8 -> #N/A
B23: Operating Income (EBIT) | D23: =D11+D14+D17+D20 -> #N/A | E23: =E11+E14+E17+E20 -> #N/A | F23: =F11+F14+F17+F20 -> #N/A | G23: =G11+G14+G17+G20 -> #N/A | H23: =H11+H14+H17+H20 -> #N/A | I23: =I11+I14+I17+I20 -> #N/A | J23: =J11+J14+J17+J20 -> #N/A | K23: =K11+K14+K17+K20 -> #N/A | ... BX23: =BX11+BX14+BX17+BX20 -> #N/A
B24: Operarting Margin | D24: =D23/D$8 -> #N/A | E24: =E23/E$8 -> #N/A | F24: =F23/F$8 -> #N/A | G24: =G23/G$8 -> #N/A | H24: =H23/H$8 -> #N/A | I24: =I23/I$8 -> #N/A | J24: =J23/J$8 -> #N/A | K24: =K23/K$8 -> #N/A | ... BX24: =BX23/BX$8 -> #N/A
B26: Taxes | D26: =-INDEX(Python!$1:$1048576,MATCH('DCF-Detailed'!$B26,Python!$A:$A,0),MATCH('DCF-Detailed'!D$1,Python!$1:$1,0)) -> #N/A | E26: =-INDEX(Python!$1:$1048576,MATCH('DCF-Detailed'!$B26,Python!$A:$A,0),MATCH('DCF-Detailed'!E$1,Python!$1:$1,0)) -> #N/A | F26: =-INDEX(Python!$1:$1048576,MATCH('DCF-Detailed'!$B26,Python!$A:$A,0),MATCH('DCF-Detailed'!F$1,Python!$1:$1,0)) -> #N/A | G26: =-INDEX(Python!$1:$1048576,MATCH('DCF-Detailed'!$B26,Python!$A:$A,0),MATCH('DCF-Detailed'!G$1,Python!$1:$1,0)) -> #N/A | H26: =-INDEX(Python!$1:$1048576,MATCH('DCF-Detailed'!$B26,Python!$A:$A,0),MATCH('DCF-Detailed'!H$1,Python!$1:$1,0)) -> #N/A | I26: =-INDEX(Python!$1:$1048576,MATCH('DCF-Detailed'!$B26,Python!$A:$A,0),MATCH('DCF-Detailed'!I$1,Python!$1:$1,0)) -> #N/A | J26: =-INDEX(Python!$1:$1048576,MATCH('DCF-Detailed'!$B26,Python!$A:$A,0),MATCH('DCF-Detailed'!J$1,Python!$1:$1,0)) -> #N/A | K26: =-INDEX(Python!$1:$1048576,MATCH('DCF-Detailed'!$B26,Python!$A:$A,0),MATCH('DCF-Detailed'!K$1,Python!$1:$1,0)) -> #N/A | ... BX26: =-INDEX(Python!$1:$1048576,MATCH('DCF-Detailed'!$B26,Python!$A:$A,0),MATCH('DCF-Detailed'!BX$1,Python!$1:$1,0)) -> #N/A
B27: Effective Tax Rate | D27: =D26/D23 -> #N/A | E27: =E26/E23 -> #N/A | F27: =F26/F23 -> #N/A | G27: =G26/G23 -> #N/A | H27: =H26/H23 -> #N/A | I27: =I26/I23 -> #N/A | J27: =J26/J23 -> #N/A | K27: =K26/K23 -> #N/A | ... BX27: =BX26/BX23 -> #N/A
B29: Depreciation & Amortization | D29: =INDEX(Python!$1:$1048576,MATCH('DCF-Detailed'!$B29,Python!$A:$A,0),MATCH('DCF-Detailed'!D$1,Python!$1:$1,0)) -> #N/A | E29: =INDEX(Python!$1:$1048576,MATCH('DCF-Detailed'!$B29,Python!$A:$A,0),MATCH('DCF-Detailed'!E$1,Python!$1:$1,0)) -> #N/A | F29: =INDEX(Python!$1:$1048576,MATCH('DCF-Detailed'!$B29,Python!$A:$A,0),MATCH('DCF-Detailed'!F$1,Python!$1:$1,0)) -> #N/A | G29: =INDEX(Python!$1:$1048576,MATCH('DCF-Detailed'!$B29,Python!$A:$A,0),MATCH('DCF-Detailed'!G$1,Python!$1:$1,0)) -> #N/A | H29: =INDEX(Python!$1:$1048576,MATCH('DCF-Detailed'!$B29,Python!$A:$A,0),MATCH('DCF-Detailed'!H$1,Python!$1:$1,0)) -> #N/A | I29: =INDEX(Python!$1:$1048576,MATCH('DCF-Detailed'!$B29,Python!$A:$A,0),MATCH('DCF-Detailed'!I$1,Python!$1:$1,0)) -> #N/A | J29: =INDEX(Python!$1:$1048576,MATCH('DCF-Detailed'!$B29,Python!$A:$A,0),MATCH('DCF-Detailed'!J$1,Python!$1:$1,0)) -> #N/A | K29: =INDEX(Python!$1:$1048576,MATCH('DCF-Detailed'!$B29,Python!$A:$A,0),MATCH('DCF-Detailed'!K$1,Python!$1:$1,0)) -> #N/A | ... BX29: =INDEX(Python!$1:$1048576,MATCH('DCF-Detailed'!$B29,Python!$A:$A,0),MATCH('DCF-Detailed'!BX$1,Python!$1:$1,0)) -> #N/A
B30: % of sales | D30: =D29/D$8 -> #N/A | E30: =E29/E$8 -> #N/A | F30: =F29/F$8 -> #N/A | G30: =G29/G$8 -> #N/A | H30: =H29/H$8 -> #N/A | I30: =I29/I$8 -> #N/A | J30: =J29/J$8 -> #N/A | K30: =K29/K$8 -> #N/A | ... BX30: =BX29/BX$8 -> #N/A
B32: Capital Expenditure | D32: =INDEX(Python!$1:$1048576,MATCH('DCF-Detailed'!$B32,Python!$A:$A,0),MATCH('DCF-Detailed'!D$1,Python!$1:$1,0)) -> #N/A | E32: =INDEX(Python!$1:$1048576,MATCH('DCF-Detailed'!$B32,Python!$A:$A,0),MATCH('DCF-Detailed'!E$1,Python!$1:$1,0)) -> #N/A | F32: =INDEX(Python!$1:$1048576,MATCH('DCF-Detailed'!$B32,Python!$A:$A,0),MATCH('DCF-Detailed'!F$1,Python!$1:$1,0)) -> #N/A | G32: =INDEX(Python!$1:$1048576,MATCH('DCF-Detailed'!$B32,Python!$A:$A,0),MATCH('DCF-Detailed'!G$1,Python!$1:$1,0)) -> #N/A | H32: =INDEX(Python!$1:$1048576,MATCH('DCF-Detailed'!$B32,Python!$A:$A,0),MATCH('DCF-Detailed'!H$1,Python!$1:$1,0)) -> #N/A | I32: =INDEX(Python!$1:$1048576,MATCH('DCF-Detailed'!$B32,Python!$A:$A,0),MATCH('DCF-Detailed'!I$1,Python!$1:$1,0)) -> #N/A | J32: =INDEX(Python!$1:$1048576,MATCH('DCF-Detailed'!$B32,Python!$A:$A,0),MATCH('DCF-Detailed'!J$1,Python!$1:$1,0)) -> #N/A | K32: =INDEX(Python!$1:$1048576,MATCH('DCF-Detailed'!$B32,Python!$A:$A,0),MATCH('DCF-Detailed'!K$1,Python!$1:$1,0)) -> #N/A | ... BX32: =INDEX(Python!$1:$1048576,MATCH('DCF-Detailed'!$B32,Python!$A:$A,0),MATCH('DCF-Detailed'!BX$1,Python!$1:$1,0)) -> #N/A
B33: % of sales | D33: =D32/D$8 -> #N/A | E33: =E32/E$8 -> #N/A | F33: =F32/F$8 -> #N/A | G33: =G32/G$8 -> #N/A | H33: =H32/H$8 -> #N/A | I33: =I32/I$8 -> #N/A | J33: =J32/J$8 -> #N/A | K33: =K32/K$8 -> #N/A | ... BX33: =BX32/BX$8 -> #N/A
B35: Change in Working Capital | D35: =-INDEX('Working Capital'!$1:$1048576,MATCH('DCF-Detailed'!$B35,'Working Capital'!$C:$C,0),MATCH('DCF-Detailed'!D$1,'Working Capital'!$1:$1,0)) -> #N/A | E35: =-INDEX('Working Capital'!$1:$1048576,MATCH('DCF-Detailed'!$B35,'Working Capital'!$C:$C,0),MATCH('DCF-Detailed'!E$1,'Working Capital'!$1:$1,0)) -> #N/A | F35: =-INDEX('Working Capital'!$1:$1048576,MATCH('DCF-Detailed'!$B35,'Working Capital'!$C:$C,0),MATCH('DCF-Detailed'!F$1,'Working Capital'!$1:$1,0)) -> #N/A | G35: =-INDEX('Working Capital'!$1:$1048576,MATCH('DCF-Detailed'!$B35,'Working Capital'!$C:$C,0),MATCH('DCF-Detailed'!G$1,'Working Capital'!$1:$1,0)) -> #N/A | H35: =-INDEX('Working Capital'!$1:$1048576,MATCH('DCF-Detailed'!$B35,'Working Capital'!$C:$C,0),MATCH('DCF-Detailed'!H$1,'Working Capital'!$1:$1,0)) -> #N/A | I35: =-INDEX('Working Capital'!$1:$1048576,MATCH('DCF-Detailed'!$B35,'Working Capital'!$C:$C,0),MATCH('DCF-Detailed'!I$1,'Working Capital'!$1:$1,0)) -> #N/A | J35: =-INDEX('Working Capital'!$1:$1048576,MATCH('DCF-Detailed'!$B35,'Working Capital'!$C:$C,0),MATCH('DCF-Detailed'!J$1,'Working Capital'!$1:$1,0)) -> #N/A | K35: =-INDEX('Working Capital'!$1:$1048576,MATCH('DCF-Detailed'!$B35,'Working Capital'!$C:$C,0),MATCH('DCF-Detailed'!K$1,'Working Capital'!$1:$1,0)) -> #N/A | ... BX35: =-INDEX('Working Capital'!$1:$1048576,MATCH('DCF-Detailed'!$B35,'Working Capital'!$C:$C,0),MATCH('DCF-Detailed'!BX$1,'Working Capital'!$1:$1,0)) -> #N/A
B36: % of sales | D36: =D35/D$8 -> #N/A | E36: =E35/E$8 -> #N/A | F36: =F35/F$8 -> #N/A | G36: =G35/G$8 -> #N/A | H36: =H35/H$8 -> #N/A | I36: =I35/I$8 -> #N/A | J36: =J35/J$8 -> #N/A | K36: =K35/K$8 -> #N/A | ... BX36: =BX35/BX$8 -> #N/A
B38: Free Cash Flow (FCF) | D38: =D23+D26+D29+D32+D35 -> #N/A | E38: =E23+E26+E29+E32+E35 -> #N/A | F38: =F23+F26+F29+F32+F35 -> #N/A | G38: =G23+G26+G29+G32+G35 -> #N/A | H38: =H23+H26+H29+H32+H35 -> #N/A | I38: =I23+I26+I29+I32+I35 -> #N/A | J38: =J23+J26+J29+J32+J35 -> #N/A | K38: =K23+K26+K29+K32+K35 -> #N/A | ... BX38: =BX23+BX26+BX29+BX32+BX35 -> #N/A
B39: Discounted FCF | AS39: =AS38/(1+$C$4)^((_xlfn.NUMBERVALUE(RIGHT(AS7,LEN(AS7)-3)))-((_xlfn.NUMBERVALUE(RIGHT($AR$7,LEN($AR$7)-3)))-1)-(1-(MID(AS7,2,1)/MID($AQ$7,2,1)))) -> #N/A | AT39: =AT38/(1+$C$4)^((_xlfn.NUMBERVALUE(RIGHT(AT7,LEN(AT7)-3)))-((_xlfn.NUMBERVALUE(RIGHT($AR$7,LEN($AR$7)-3)))-1)-(1-(MID(AT7,2,1)/MID($AQ$7,2,1)))) -> #N/A | AU39: =AU38/(1+$C$4)^((_xlfn.NUMBERVALUE(RIGHT(AU7,LEN(AU7)-3)))-((_xlfn.NUMBERVALUE(RIGHT($AR$7,LEN($AR$7)-3)))-1)-(1-(MID(AU7,2,1)/MID($AQ$7,2,1)))) -> #N/A | AV39: =AV38/(1+$C$4)^((_xlfn.NUMBERVALUE(RIGHT(AV7,LEN(AV7)-3)))-((_xlfn.NUMBERVALUE(RIGHT($AR$7,LEN($AR$7)-3)))-1)-(1-(MID(AV7,2,1)/MID($AQ$7,2,1)))) -> #N/A | AW39: =AW38/(1+$C$4)^((_xlfn.NUMBERVALUE(RIGHT(AW7,LEN(AW7)-3)))-((_xlfn.NUMBERVALUE(RIGHT($AR$7,LEN($AR$7)-3)))-1)-(1-(MID(AW7,2,1)/MID($AQ$7,2,1)))) -> #N/A | AX39: =AX38/(1+$C$4)^((_xlfn.NUMBERVALUE(RIGHT(AX7,LEN(AX7)-3)))-((_xlfn.NUMBERVALUE(RIGHT($AR$7,LEN($AR$7)-3)))-1)-(1-(MID(AX7,2,1)/MID($AQ$7,2,1)))) -> #N/A | AY39: =AY38/(1+$C$4)^((_xlfn.NUMBERVALUE(RIGHT(AY7,LEN(AY7)-3)))-((_xlfn.NUMBERVALUE(RIGHT($AR$7,LEN($AR$7)-3)))-1)-(1-(MID(AY7,2,1)/MID($AQ$7,2,1)))) -> #N/A | AZ39: =AZ38/(1+$C$4)^((_xlfn.NUMBERVALUE(RIGHT(AZ7,LEN(AZ7)-3)))-((_xlfn.NUMBERVALUE(RIGHT($AR$7,LEN($AR$7)-3)))-1)-(1-(MID(AZ7,2,1)/MID($AQ$7,2,1)))) -> #N/A | ... BX39: =BX38/(1+$C$4)^((_xlfn.NUMBERVALUE(RIGHT(BX7,LEN(BX7)-3)))-((_xlfn.NUMBERVALUE(RIGHT($AR$7,LEN($AR$7)-3)))-1)-(1-(MID(BX7,2,1)/MID($AQ$7,2,1)))) -> #N/A
B42: Terminal Value (TV) | C42: =('DCF-Detailed'!BX38*(1+C5))/(C4-C5) -> #N/A
B43: Present Value of TV | C43: =C42/(1+C4)^((_xlfn.NUMBERVALUE(RIGHT(BX7,LEN(BX7)-3)))-((_xlfn.NUMBERVALUE(RIGHT($AR$7,LEN($AR$7)-3)))-1)) -> #N/A
B44: Total Discounted FCF | C44: =SUM(39:39) -> #N/A
B45: Enterprise Value | C45: =C43+C44 -> #N/A
B46: Cash and Equivalents | C46: 1551
B47: Debt | C47: =WACC!D4 -> #N/A
B48: Equity Value | C48: =C45+C46-C47 -> #N/A
B49: Shares | C49: =Summary!C6 -> 1026
B50: Intrinsic Share Value | C50: =C48/C49 -> #N/A

Sheet Summary
B2: # Standard | C2: DCF-10
B3: Value per share | C3: ='DCF-Detailed'!C50 -> #N/A
B5: Current Share Price | C5: 127.37
B6: Shares Outstanding (millions) | C6: 1026
B7: Market Capitalization ($ millions) | C7: =C5*C6 -> 130681.62
B10: Enterprise Value ($ millions) | C10: ='DCF-Detailed'!C45 -> #N/A
B11: Equity Value ($ millions) | C11: ='DCF-Detailed'!C48 -> #N/A
B13: Terminal Value Composition | C13: ='DCF-Detailed'!C43/C11 -> #N/A
B14: Upside (Downside) | C14: =C3/C5-1 -> #N/A
B16: Arithmetic average annual return | C16: =C14/ABS(RIGHT(C2,2)) -> #N/A
B17: CAGR of return | C17: =((C3/C5)^(1/ABS(RIGHT(C2,2))))-1 -> #N/A
B19: P/S
B20: TTM | C20: =C7/SUM('DCF-Detailed'!AN8:AQ8) -> #N/A
B21: NTM | C21: =C7/SUM('DCF-Detailed'!AR8:AU8) -> #N/A
B23: P/FCF
B24: TTM | C24: =C7/SUM('DCF-Detailed'!AN38:AQ38) -> #N/A
B25: NTM | C25: =C7/SUM('DCF-Detailed'!AR38:AU38) -> #N/A
B27: P/EBITDA
B28: TTM | C28: =C7/(SUM('DCF-Detailed'!AN23:AQ23)+SUM('DCF-Detailed'!AN26:AQ26)+SUM('DCF-Detailed'!AN29:AQ29)) -> #N/A
B29: NTM | C29: =C7/(SUM('DCF-Detailed'!AR23:AU23)+SUM('DCF-Detailed'!AR26:AU26)+SUM('DCF-Detailed'!AR29:AU29)) -> #N/A
B31: End of projection for.EDA | C31: =C7/(SUM('DCF-Detailed'!BU23:BX23)+SUM('DCF-Detailed'!BU26:BX26)+SUM('DCF-Detailed'!BU29:BX29)) -> #N/A

Sheet Working Capital
D1: 2013-12-31 | E1: ='DCF-Detailed'!D1 -> 2014-03-31 | F1: ='DCF-Detailed'!E1 -> 2014-06-30 | G1: ='DCF-Detailed'!F1 -> 2014-09-30 | H1: ='DCF-Detailed'!G1 -> 2014-12-31 | I1: ='DCF-Detailed'!H1 -> 2015-03-31 | J1: ='DCF-Detailed'!I1 -> 2015-06-30 | K1: ='DCF-Detailed'!J1 -> 2015-09-30 | L1: ='DCF-Detailed'!K1 -> 2015-12-31 | ... AS1: ='DCF-Detailed'!AR1 -> 2024-03-31
C2: totalCurrentAssets | D2: =INDEX(Python!$1:$1048576,MATCH('Working Capital'!$C2,Python!$A:$A,0),MATCH('Working Capital'!D$1,Python!$1:$1,0)) -> #N/A | E2: =INDEX(Python!$1:$1048576,MATCH('Working Capital'!$C2,Python!$A:$A,0),MATCH('Working Capital'!E$1,Python!$1:$1,0)) -> #N/A | F2: =INDEX(Python!$1:$1048576,MATCH('Working Capital'!$C2,Python!$A:$A,0),MATCH('Working Capital'!F$1,Python!$1:$1,0)) -> #N/A | G2: =INDEX(Python!$1:$1048576,MATCH('Working Capital'!$C2,Python!$A:$A,0),MATCH('Working Capital'!G$1,Python!$1:$1,0)) -> #N/A | H2: =INDEX(Python!$1:$1048576,MATCH('Working Capital'!$C2,Python!$A:$A,0),MATCH('Working Capital'!H$1,Python!$1:$1,0)) -> #N/A | I2: =INDEX(Python!$1:$1048576,MATCH('Working Capital'!$C2,Python!$A:$A,0),MATCH('Working Capital'!I$1,Python!$1:$1,0)) -> #N/A | J2: =INDEX(Python!$1:$1048576,MATCH('Working Capital'!$C2,Python!$A:$A,0),MATCH('Working Capital'!J$1,Python!$1:$1,0)) -> #N/A | K2: =INDEX(Python!$1:$1048576,MATCH('Working Capital'!$C2,Python!$A:$A,0),MATCH('Working Capital'!K$1,Python!$1:$1,0)) -> #N/A | ... AS2: =INDEX(Python!$1:$1048576,MATCH('Working Capital'!$C2,Python!$A:$A,0),MATCH('Working Capital'!AS$1,Python!$1:$1,0)) -> #N/A
C3: totalCurrentLiabilities | D3: =INDEX(Python!$1:$1048576,MATCH('Working Capital'!$C3,Python!$A:$A,0),MATCH('Working Capital'!D$1,Python!$1:$1,0)) -> #N/A | E3: =INDEX(Python!$1:$1048576,MATCH('Working Capital'!$C3,Python!$A:$A,0),MATCH('Working Capital'!E$1,Python!$1:$1,0)) -> #N/A | F3: =INDEX(Python!$1:$1048576,MATCH('Working Capital'!$C3,Python!$A:$A,0),MATCH('Working Capital'!F$1,Python!$1:$1,0)) -> #N/A | G3: =INDEX(Python!$1:$1048576,MATCH('Working Capital'!$C3,Python!$A:$A,0),MATCH('Working Capital'!G$1,Python!$1:$1,0)) -> #N/A | H3: =INDEX(Python!$1:$1048576,MATCH('Working Capital'!$C3,Python!$A:$A,0),MATCH('Working Capital'!H$1,Python!$1:$1,0)) -> #N/A | I3: =INDEX(Python!$1:$1048576,MATCH('Working Capital'!$C3,Python!$A:$A,0),MATCH('Working Capital'!I$1,Python!$1:$1,0)) -> #N/A | J3: =INDEX(Python!$1:$1048576,MATCH('Working Capital'!$C3,Python!$A:$A,0),MATCH('Working Capital'!J$1,Python!$1:$1,0)) -> #N/A | K3: =INDEX(Python!$1:$1048576,MATCH('Working Capital'!$C3,Python!$A:$A,0),MATCH('Working Capital'!K$1,Python!$1:$1,0)) -> #N/A | ... AS3: =INDEX(Python!$1:$1048576,MATCH('Working Capital'!$C3,Python!$A:$A,0),MATCH('Working Capital'!AS$1,Python!$1:$1,0)) -> #N/A
C4: netWorkingCapital | D4: =D2-D3 -> #N/A | E4: =E2-E3 -> #N/A | F4: =F2-F3 -> #N/A | G4: =G2-G3 -> #N/A | H4: =H2-H3 -> #N/A | I4: =I2-I3 -> #N/A | J4: =J2-J3 -> #N/A | K4: =K2-K3 -> #N/A | ... AS4: =AS2-AS3 -> #N/A
C5: Change in Working Capital | E5: =E4-D4 -> #N/A | F5: =F4-E4 -> #N/A | G5: =G4-F4 -> #N/A | H5: =H4-G4 -> #N/A | I5: =I4-H4 -> #N/A | J5: =J4-I4 -> #N/A | K5: =K4-J4 -> #N/A | L5: =L4-K4 -> #N/A | ... AS5: =AS4-AR4 -> #N/A
C7: % | F7: =F5/E4 -> #N/A | G7: =G5/F4 -> #N/A | H7: =H5/G4 -> #N/A | I7: =I5/H4 -> #N/A | J7: =J5/I4 -> #N/A | K7: =K5/J4 -> #N/A | L7: =L5/K4 -> #N/A | M7: =M5/L4 -> #N/A | ... AS7: =AS5/AR4 -> #N/A
C10: Mean | D10: =AVERAGE(7:7) -> #N/A
C11: Median | D11: =MEDIAN(7:7) -> #N/A
C12: Min | D12: =MIN(7:7) -> #N/A
C13: Max | D13: =MAX(7:7) -> #N/A

Sheet IS Detail
C3: revenue
C4: cogs

Sheet Notes
C3: Green | D3: calculation/other sheet ref | J3: assuming that quarters before 3-31-23 are just moved up
C4: Blue | D4: hardcode/assumptions | H4: FCF | I4: -257 | J4: 42 | K4: 463 | L4: -140 | M4: 180 | N4: 259
H5: SBC | I5: 13 | J5: 34 | K5: -6 | L5: 140 | M5: 513 | N5: 199
H6: harcode O/i | J6: 294 | K6: 183 | L6: -50 | M6: 111 | N6: -156 | O6: 134
J8: ebitda
J9: Interest income
J10: interest expense
J11: stock based compensation
K12: add this back in order to get adjusted EBITDA
K14: have another sheet for IS detail, as well as comparative valuation metrics like EBITDA
K15: what actually is in 'other operating expesnes' or income
K16: inputs for rate of change of decline; ie, derivatives
K17: add formatting macros yeah?
K18: add formula for automating the quarters that come three next
K19: add shares outstanding
K20: get EPS
K21: confirm that quarterly discounted one is accurate
K23: TV figure needs to be updated for the quarterly values as well
K26: Will need a date to automate how forward looking this shit all is
K27: percentile ranks with that
... K62: one will be entirely blank for my own personal assumptionjs
C64: Pyrhon program
K65: operating scenarios
C66: 1. duplicate the excel file template | L66: base case
C67: 2. python export tabs | L67: moderately conservative
C68: 3. From there, let formlas populate??? | L68: upside case
C69: I need to 'show my work afterall', or do I?
K70: look at what drives change in NWC
C71: Or should the Python program not export the datafiles, and just run the program to input (similar to hardcoding format)
C73: Write the excel formulas in Python?
D74: have the formulas written in excel, and then have a template sheet tojust let python dump it there?
C76: before adding so many scenarios, I first need the dcf template I have as is COMPLETE, because any additions will be a pain in the ass
K79: FORGETTING ABPOUT THE TAX SHIELD

Sheet Python

Sheet Notes Q3-2024
B1: dates linked to each other, starting with a hidden row that has the actual dates
B2: rename the lineitem names so that they are properly formatted
B3: there will be another sheet that has the total historical data? Or will that not be necessary???
B5: how to make the dates dynamic so that they match the dates of the 10qs and 10ks

Sheet Best Case
B2: Valuation Assumptions
B3: Discount Rate | C3: =WACC!D18 -> #N/A
B4: Terminal Growth Rate | C4: 0.025
B6: Figures in $ millions | D6: Q2 2022 | E6: Q3 2022 | F6: Q4 2022 | G6: Q1 2023 | H6: =LEFT(D6,2) & " " & 1+_xlfn.NUMBERVALUE(RIGHT(D6,LEN(D6)-2)) -> Q2 2023 | I6: =LEFT(E6,2) & " " & 1+_xlfn.NUMBERVALUE(RIGHT(E6,LEN(E6)-2)) -> Q3 2023 | J6: =LEFT(F6,2) & " " & 1+_xlfn.NUMBERVALUE(RIGHT(F6,LEN(F6)-2)) -> Q4 2023 | K6: =LEFT(G6,2) & " " & 1+_xlfn.NUMBERVALUE(RIGHT(G6,LEN(G6)-2)) -> Q1 2024 | L6: =LEFT(H6,2) & " " & 1+_xlfn.NUMBERVALUE(RIGHT(H6,LEN(H6)-2)) -> Q2 2024 | M6: =LEFT(I6,2) & " " & 1+_xlfn.NUMBERVALUE(RIGHT(I6,LEN(I6)-2)) -> Q3 2024 | N6: =LEFT(J6,2) & " " & 1+_xlfn.NUMBERVALUE(RIGHT(J6,LEN(J6)-2)) -> Q4 2024 | O6: =LEFT(K6,2) & " " & 1+_xlfn.NUMBERVALUE(RIGHT(K6,LEN(K6)-2)) -> Q1 2025 | ... AQ6: =LEFT(AM6,2) & " " & 1+_xlfn.NUMBERVALUE(RIGHT(AM6,LEN(AM6)-2)) -> Q1 2032
B7: Revenue | E7: 692 | F7: 630 | G7: 633 | H7: 675 | I7: 806 | J7: 824 | K7: =(850+900)/2 -> 875 | L7: =H7*(1+L8) -> 877.5 | M7: =I7*(1+M8) -> 1047.8 | N7: =J7*(1+N8) -> 1071.2 | O7: =K7*(1+O8) -> 1137.5 | P7: =L7*(1+P8) -> 1140.75 | Q7: =M7*(1+Q8) -> 1362.14 | R7: =N7*(1+R8) -> 1392.56 | S7: =O7*(1+S8) -> 1478.75 | ... AQ7: =AM7*(1+AQ8) -> 7137.6438
B8: Growth y/y | H8: =IFERROR(H7/D7-1,0) -> 0 | I8: =I7/E7-1 -> 0.16473988 | J8: =J7/F7-1 -> 0.30793651 | K8: =K7/G7-1 -> 0.38230648 | L8: 0.3 | M8: =L8 -> 0.3 | N8: =M8 -> 0.3 | O8: =N8 -> 0.3 | P8: =O8 -> 0.3 | Q8: =P8 -> 0.3 | R8: =Q8 -> 0.3 | S8: =R8 -> 0.3 | T8: =S8 -> 0.3 | ... AQ8: =AP8 -> 0.3
B10: Gross Profit | E10: 667 | F10: 605 | G10: 606 | H10: 644 | I10: 760 | J10: 788 | K10: =K11*K7 -> 836.33215 | L10: =L11*L7 -> 838.72167 | M10: =M11*M7 -> 1001.4958 | N10: =N11*N7 -> 1023.8617 | O10: =O11*O7 -> 1087.2318 | P10: =P11*P7 -> 1090.3382 | Q10: =Q11*Q7 -> 1301.9445 | R10: =R11*R7 -> 1331.0202 | ... AQ10: =AQ11*AQ7 -> 6822.2183
B11: Gross Profit Margin | E11: =E10/E7 -> 0.96387283 | F11: =F10/F7 -> 0.96031746 | G11: =G10/G7 -> 0.95734597 | H11: =H10/H7 -> 0.95407407 | I11: =I10/I7 -> 0.94292804 | J11: =J10/J7 -> 0.95631068 | K11: =AVERAGE(E11:J11) -> 0.95580818 | L11: =K11 -> 0.95580818 | M11: =L11 -> 0.95580818 | N11: =M11 -> 0.95580818 | O11: =N11 -> 0.95580818 | P11: =O11 -> 0.95580818 | Q11: =P11 -> 0.95580818 | R11: =Q11 -> 0.95580818 | S11: =R11 -> 0.95580818 | ... AQ11: =AP11 -> 0.95580818
B13: Research & Development | E13: -218 | F13: -248 | G13: -381 | H13: -337 | I13: -626 | J13: -432 | K13: =K14*K$7 -> -385.60729 | L13: =L14*L$7 -> -386.70902 | M13: =M14*M$7 -> -461.75922 | N13: =N14*N$7 -> -472.07146 | O13: =O14*O$7 -> -501.28947 | P13: =P14*P$7 -> -502.72173 | Q13: =Q14*Q$7 -> -600.28698 | R13: =R14*R$7 -> -613.69289 | ... AQ13: =AQ14*AQ$7 -> -3145.5171
B14: % of sales | E14: =E13/E$7 -> -0.3150289 | F14: =F13/F$7 -> -0.39365079 | G14: =G13/G$7 -> -0.60189573 | H14: =H13/H$7 -> -0.49925926 | I14: =I13/I$7 -> -0.77667494 | J14: =J13/J$7 -> -0.52427184 | K14: =AVERAGE(E14:J14)*0.85 -> -0.44069404 | L14: =K14 -> -0.44069404 | M14: =L14 -> -0.44069404 | N14: =M14 -> -0.44069404 | O14: =N14 -> -0.44069404 | P14: =O14 -> -0.44069404 | Q14: =P14 -> -0.44069404 | R14: =Q14 -> -0.44069404 | S14: =R14 -> -0.44069404 | ... AQ14: =AP14 -> -0.44069404
B16: Selling, General, & Administrative | E16: -153 | F16: -172 | G16: -274 | H16: -196 | I16: -290 | J16: -216 | K16: =K17*K$7 -> -134.11426 | L16: =L17*L$7 -> -134.49745 | M16: =M17*M$7 -> -160.59991 | N16: =N17*N$7 -> -164.18651 | O16: =O17*O$7 -> -174.34854 | P16: =P17*P$7 -> -174.84668 | Q16: =Q17*Q$7 -> -208.77989 | R16: =R17*R$7 -> -213.44247 | ... AQ16: =AQ17*AQ$7 -> -1094.0112
B17: % of sales | E17: =E16/E$7 -> -0.22109827 | F17: =F16/F$7 -> -0.27301587 | G17: =G16/G$7 -> -0.4328594 | H17: =H16/H$7 -> -0.29037037 | I17: =I16/I$7 -> -0.35980149 | J17: =J16/J$7 -> -0.26213592 | K17: =AVERAGE(E17:J17)/2 -> -0.15327344 | L17: =K17 -> -0.15327344 | M17: =L17 -> -0.15327344 | N17: =M17 -> -0.15327344 | O17: =N17 -> -0.15327344 | P17: =O17 -> -0.15327344 | Q17: =P17 -> -0.15327344 | R17: =Q17 -> -0.15327344 | S17: =R17 -> -0.15327344 | ... AQ17: =AP17 -> -0.15327344
B19: Other Operating Expenses | E19: 4 | F19: 23 | G19: -1 | H19: -1 | I19: 14 | J19: -15 | K19: =K20*K$7 -> 5.5989597 | L19: =L20*L$7 -> 5.6149567 | M19: =M20*M$7 -> 6.7046743 | N19: =N20*N$7 -> 6.8544064 | O19: =O20*O$7 -> 7.2786476 | P19: =P20*P$7 -> 7.2994438 | Q19: =Q20*Q$7 -> 8.7160765 | R19: =R20*R$7 -> 8.9107284 | ... AQ19: =AQ20*AQ$7 -> 45.672434
B20: % of sales | E20: =E19/E$7 -> 0.0057803468 | F20: =F19/F$7 -> 0.036507937 | G20: =G19/G$7 -> -0.0015797788 | H20: =H19/H$7 -> -0.0014814815 | I20: =I19/I$7 -> 0.017369727 | J20: =J19/J$7 -> -0.018203883 | K20: =AVERAGE(E20:J20) -> 0.0063988111 | L20: =K20 -> 0.0063988111 | M20: =L20 -> 0.0063988111 | N20: =M20 -> 0.0063988111 | O20: =N20 -> 0.0063988111 | P20: =O20 -> 0.0063988111 | Q20: =P20 -> 0.0063988111 | R20: =Q20 -> 0.0063988111 | S20: =R20 -> 0.0063988111 | ... AQ20: =AP20 -> 0.0063988111
B22: Operating Income (EBIT) | E22: =E10+E13+E16+E19 -> 300 | F22: =F10+F13+F16+F19 -> 208 | G22: =G10+G13+G16+G19 -> -50 | H22: =H10+H13+H16+H19 -> 110 | I22: =I10+I13+I16+I19 -> -142 | J22: =J10+J13+J16+J19 -> 125 | K22: =K10+K13+K16+K19 -> 322.20956 | L22: =L10+L13+L16+L19 -> 323.13016 | ... AQ22: =AQ10+AQ13+AQ16+AQ19 -> 2628.3624
B23: Operarting Margin | E23: =E22/E7 -> 0.43352601 | F23: =F22/F7 -> 0.33015873 | G23: =G22/G7 -> -0.078988942 | H23: =H22/H7 -> 0.16296296 | I23: =I22/I7 -> -0.17617866 | J23: =J22/J7 -> 0.15169903 | K23: =K22/K7 -> 0.3682395 | L23: =L22/L7 -> 0.3682395 | ... AQ23: =AQ22/AQ7 -> 0.3682395
B25: Taxes | E25: 61 | F25: 38 | G25: 2 | H25: 22 | I25: -9 | J25: 59 | K25: =K26*K22 -> -67.664009 | L25: =L26*L22 -> -67.857334 | M25: =M26*M22 -> -81.026684 | N25: =N26*N22 -> -82.836212 | O25: =O26*O22 -> -87.963211 | P25: =P26*P22 -> -88.214535 | Q25: =Q26*Q22 -> -105.33469 | R25: =R26*R22 -> -107.68708 | ... AQ25: =AQ26*AQ22 -> -551.9561
B26: Effective Tax Rate | E26: =E25/E22 -> 0.20333333 | F26: =F25/F22 -> 0.18269231 | G26: =G25/G22 -> -0.04 | H26: =H25/H22 -> 0.2 | I26: =I25/I22 -> 0.063380282 | J26: =J25/J22 -> 0.472 | K26: =-WACC!D7 -> -0.21 | L26: =K26 -> -0.21 | M26: =L26 -> -0.21 | N26: =M26 -> -0.21 | O26: =N26 -> -0.21 | P26: =O26 -> -0.21 | Q26: =P26 -> -0.21 | R26: =Q26 -> -0.21 | S26: =R26 -> -0.21 | ... AQ26: =AP26 -> -0.21
B28: Depreciation & Amortization | E28: 42 | F28: 45 | G28: 40 | H28: 41 | I28: 41 | J28: 42 | K28: =K29*K7 -> 52.192797 | L28: =L29*L7 -> 52.34192 | M28: =M29*M7 -> 62.500129 | N28: =N29*N7 -> 63.895914 | O28: =O29*O7 -> 67.850636 | P28: =P29*P7 -> 68.044495 | Q28: =Q29*Q7 -> 81.250168 | R28: =R29*R7 -> 83.064688 | ... AQ28: =AQ29*AQ7 -> 425.75268
B29: % of sales | E29: =E28/E7 -> 0.060693642 | F29: =F28/F7 -> 0.071428571 | G29: =G28/G7 -> 0.063191153 | H29: =H28/H7 -> 0.060740741 | I29: =I28/I7 -> 0.050868486 | J29: =J28/J7 -> 0.050970874 | K29: =AVERAGE(E29:J29) -> 0.059648911 | L29: =K29 -> 0.059648911 | M29: =L29 -> 0.059648911 | N29: =M29 -> 0.059648911 | O29: =N29 -> 0.059648911 | P29: =O29 -> 0.059648911 | Q29: =P29 -> 0.059648911 | R29: =Q29 -> 0.059648911 | S29: =R29 -> 0.059648911 | ... AQ29: =AP29 -> 0.059648911
B31: CapEx | E31: -26 | F31: -34 | G31: -20 | H31: -26 | I31: -47 | J31: -51 | K31: =K32*K7 -> -41.104651 | L31: =L32*L7 -> -41.222093 | M31: =M32*M7 -> -49.222232 | N31: =N32*N7 -> -50.321488 | O31: =O32*O7 -> -53.436046 | P31: =P32*P7 -> -53.58872 | Q31: =Q32*Q7 -> -63.988902 | R31: =R32*R7 -> -65.417934 | ... AQ31: =AQ32*AQ7 -> -335.30326
B32: % of sales | E32: =E31/E$7 -> -0.037572254 | F32: =F31/F$7 -> -0.053968254 | G32: =G31/G$7 -> -0.031595577 | H32: =H31/H$7 -> -0.038518519 | I32: =I31/I$7 -> -0.058312655 | J32: =J31/J$7 -> -0.061893204 | K32: =AVERAGE(E32:J32) -> -0.046976744 | L32: =K32 -> -0.046976744 | M32: =L32 -> -0.046976744 | N32: =M32 -> -0.046976744 | O32: =N32 -> -0.046976744 | P32: =O32 -> -0.046976744 | Q32: =P32 -> -0.046976744 | R32: =Q32 -> -0.046976744 | S32: =R32 -> -0.046976744 | ... AQ32: =AP32 -> -0.046976744
B34: Change in NWC | E34: -537 | F34: -171 | G34: 481 | H34: -402 | I34: -224 | J34: -20 | K34: =K35*K7 -> -21.237864 | L34: =L35*L7 -> -21.298544 | M34: =M35*M7 -> -25.432039 | N34: =N35*N7 -> -26 | O34: =O35*O7 -> -27.609223 | P34: =P35*P7 -> -27.688107 | Q34: =Q35*Q7 -> -33.06165 | R34: =R35*R7 -> -33.8 | ... AQ34: =AQ35*AQ7 -> -173.24378
B35: % of sales | E35: =E34/E$7 -> -0.77601156 | F35: =F34/F$7 -> -0.27142857 | G35: =G34/G$7 -> 0.75987362 | H35: =H34/H$7 -> -0.59555556 | I35: =I34/I$7 -> -0.27791563 | J35: =J34/J$7 -> -0.024271845 | K35: =J35 -> -0.024271845 | L35: =K35 -> -0.024271845 | M35: =L35 -> -0.024271845 | N35: =M35 -> -0.024271845 | O35: =N35 -> -0.024271845 | P35: =O35 -> -0.024271845 | Q35: =P35 -> -0.024271845 | R35: =Q35 -> -0.024271845 | ... AQ35: =AP35 -> -0.024271845
B37: Free Cash Flow (FCF) | D37: =D22+D25+D28+D31+D34 -> 0 | E37: =E22+E25+E28+E31+E34 -> -160 | F37: =F22+F25+F28+F31+F34 -> 86 | G37: =G22+G25+G28+G31+G34 -> 453 | H37: =H22+H25+H28+H31+H34 -> -255 | I37: =I22+I25+I28+I31+I34 -> -381 | J37: =J22+J25+J28+J31+J34 -> 155 | K37: =K22+K25+K28+K31+K34 -> 244.39584 | ... AQ37: =AQ22+AQ25+AQ28+AQ31+AQ34 -> 1993.6119
B38: Discounted FCF | K38: =K37/(1+$C$3)^((_xlfn.NUMBERVALUE(RIGHT(K6,LEN(K6)-3)))-((_xlfn.NUMBERVALUE(RIGHT($K$6,LEN($K$6)-3)))-1)-(1-(MID(K6,2,1)/MID($J$6,2,1)))) -> #N/A | L38: =L37/(1+$C$3)^((_xlfn.NUMBERVALUE(RIGHT(L6,LEN(L6)-3)))-((_xlfn.NUMBERVALUE(RIGHT($K$6,LEN($K$6)-3)))-1)-(1-(MID(L6,2,1)/MID($J$6,2,1)))) -> #N/A | M38: =M37/(1+$C$3)^((_xlfn.NUMBERVALUE(RIGHT(M6,LEN(M6)-3)))-((_xlfn.NUMBERVALUE(RIGHT($K$6,LEN($K$6)-3)))-1)-(1-(MID(M6,2,1)/MID($J$6,2,1)))) -> #N/A | N38: =N37/(1+$C$3)^((_xlfn.NUMBERVALUE(RIGHT(N6,LEN(N6)-3)))-((_xlfn.NUMBERVALUE(RIGHT($K$6,LEN($K$6)-3)))-1)-(1-(MID(N6,2,1)/MID($J$6,2,1)))) -> #N/A | O38: =O37/(1+$C$3)^((_xlfn.NUMBERVALUE(RIGHT(O6,LEN(O6)-3)))-((_xlfn.NUMBERVALUE(RIGHT($K$6,LEN($K$6)-3)))-1)-(1-(MID(O6,2,1)/MID($J$6,2,1)))) -> #N/A | P38: =P37/(1+$C$3)^((_xlfn.NUMBERVALUE(RIGHT(P6,LEN(P6)-3)))-((_xlfn.NUMBERVALUE(RIGHT($K$6,LEN($K$6)-3)))-1)-(1-(MID(P6,2,1)/MID($J$6,2,1)))) -> #N/A | Q38: =Q37/(1+$C$3)^((_xlfn.NUMBERVALUE(RIGHT(Q6,LEN(Q6)-3)))-((_xlfn.NUMBERVALUE(RIGHT($K$6,LEN($K$6)-3)))-1)-(1-(MID(Q6,2,1)/MID($J$6,2,1)))) -> #N/A | R38: =R37/(1+$C$3)^((_xlfn.NUMBERVALUE(RIGHT(R6,LEN(R6)-3)))-((_xlfn.NUMBERVALUE(RIGHT($K$6,LEN($K$6)-3)))-1)-(1-(MID(R6,2,1)/MID($J$6,2,1)))) -> #N/A | ... AQ38: =AQ37/(1+$C$3)^((_xlfn.NUMBERVALUE(RIGHT(AQ6,LEN(AQ6)-3)))-((_xlfn.NUMBERVALUE(RIGHT($K$6,LEN($K$6)-3)))-1)-(1-(MID(AQ6,2,1)/MID($J$6,2,1)))) -> #N/A
D39: =#REF!+E28+E31+E34 -> #REF! | E39: =#REF!+F28+F31+F34 -> #REF! | F39: =#REF!+#REF!+#REF!+#REF! -> #REF! | G39: =#REF!+G28+G31+G34 -> #REF! | H39: =#REF!+H28+H31+H34 -> #REF! | I39: =#REF!+I28+I31+I34 -> #REF! | J39: =#REF!+J28+J31+J34 -> #REF!
D40: =D37/E22 -> 0 | E40: =E37/F22 -> -0.76923077 | F40: =F37/#REF! -> #REF! | G40: =G37/G22 -> -9.06 | H40: =H37/H22 -> -2.3181818 | I40: =I37/I22 -> 2.6830986 | J40: =J37/J22 -> 1.24
D41: adjust discount to by dividing by quarter to be more precise
B43: Terminal Value (TV) | C43: =('Best Case'!AQ37*(1+C4))/(C3-C4) -> #N/A
B44: Present Value of TV | C44: =C43/(1+C3)^((_xlfn.NUMBERVALUE(RIGHT(AQ6,LEN(AQ6)-3)))-((_xlfn.NUMBERVALUE(RIGHT($K$6,LEN($K$6)-3)))-1)) -> #N/A
B45: Total Discounted FCF | C45: =SUM(38:38) -> #N/A
B46: Enterprise Value | C46: =C44+C45 -> #N/A
B47: Cash and Equivalents | C47: 1551 | K47: =K22/$C$50 -> 0.31404441 | L47: =L22/$C$50 -> 0.31494168 | M47: =M22/$C$50 -> 0.37606369 | N47: =N22/$C$50 -> 0.38446214
B48: Debt | C48: =WACC!D4 -> #N/A
B49: Equity Value | C49: =C46+C47-C48 -> #N/A
B50: Shares | C50: =Summary!C6 -> 1026
B51: Intrinsic Share Value | C51: =C49/C50 -> #N/A
